[
  {
    "source": "༄༅།།",
    "target": "༄༅ ། །"
  },
  {
    "source": "རབ་བཏགས་ཀྱི་རྟོགས་བརྗོད་རྣ་བའི་རྒྱན་ཅེས་བྱ་བ་བཞུགས་སོ།།",
    "target": "རབ་བཏགས་ ཀྱི་ རྟོགས་བརྗོད་ རྣ་བ འི་ རྒྱན་ ཅེས་ བྱ་བ་ བཞུགས་ སོ ། །"
  },
  {
    "source": "༄༅།།",
    "target": "༄༅ ། །"
  },
  {
    "source": "དབྱངས་ཅན་མ་ལ་ཕྱག་འཚལ་ལོ།།",
    "target": "དབྱངས་ཅན་ མ་ ལ་ ཕྱག་ འཚལ་ ལོ ། །"
  },
  {
    "source": "དད་པས་བསྙེན་པའི་བློ་གྲོས་ཆུ་གཏེར་རྣམས།།",
    "target": "དད་པ ས་ བསྙེན་པ འི་ བློ་གྲོས་ ཆུ་གཏེར་ རྣམས ། །"
  },
  {
    "source": "བདུད་རྩིས་འཕྱུར་བྱེད་དབྱངས་ཅན་ཟླ་ཤེལ་ནི།།",
    "target": "བདུད་རྩི ས་ འཕྱུར་ བྱེད་ དབྱངས་ཅན་ ཟླ་ཤེལ་ ནི ། །"
  },
  {
    "source": "མཐོ་རིས་བུ་མོའི་རྒྱུ་སྐར་གྱིས་བསྐོར་བ།།",
    "target": "མཐོ་རིས་བུ་མོ འི་ རྒྱུ་ སྐར་ གྱིས་ བསྐོར་བ ། །"
  },
  {
    "source": "ཡིད་འཕྲོག་ནམ་མཁར་རོལ་དེས་ཤིས་པར་མཛོད།།",
    "target": "ཡིད་ འཕྲོག་ ནམ་ མཁ ར་ རོལ་ དེ ས་ ཤིས་པ ར་ མཛོད ། །"
  },
  {
    "source": "རབ་བཏགས་གཏམ་གྱི་གཟུགས་གསར་ནི།།",
    "target": "རབ་བཏགས་ གཏམ་ གྱི་ གཟུགས་ གསར་ ནི ། །"
  },
  {
    "source": "ཐུབ་པ་རིག་བྱེད་མཁན་རྣམས་ཀྱང་།།",
    "target": "ཐུབ་པ་ རིག་བྱེད་མཁན་ རྣམས་ ཀྱང་ ། །"
  },
  {
    "source": "ཆགས་པས་གནོན་པ་ཀུན་རྟོག་གི།",
    "target": "ཆགས་པ ས་ གནོན་པ་ ཀུན་རྟོག་ གི །"
  },
  {
    "source": "པིར་གྱི་འདུ་བྱེད་བསྒྱུར་ལས་འཐོན།།",
    "target": "པིར་ གྱི་ འདུ་བྱེད་ བསྒྱུར་ ལས་ འཐོན ། །"
  },
  {
    "source": "མ་སྨད་བསོད་ནམས་པད་རྫིང་གི།",
    "target": "མ་སྨད་ བསོད་ནམས་ པད་ རྫིང་ གི །"
  },
  {
    "source": "སྦྱངས་ཤུགས་སད་པའི་ཨུཏྤལ་རྩེར།།",
    "target": "སྦྱངས་ ཤུགས་ སད་པ འི་ ཨུཏྤལ་ རྩེ ར ། །"
  },
  {
    "source": "ཚངས་པའི་རིགས་ཀྱི་ཐིག་ལེ་གསར།།",
    "target": "ཚངས་པ འི་ རིགས་ ཀྱི་ ཐིག་ལེ་ གསར ། །"
  },
  {
    "source": "ཁྱེའུ་སྦྲང་རྩི་བཞིན་དུ་སྐྱེས།།",
    "target": "ཁྱེའུ་ སྦྲང་རྩི་ བཞིན་ དུ་ སྐྱེས ། །"
  },
  {
    "source": "དེ་ནི་བློ་གྲོས་ནོར་བསྒྲུབ་ལ།།",
    "target": "དེ་ ནི་ བློ་གྲོས་ ནོར་ བསྒྲུབ་ ལ ། །"
  },
  {
    "source": "གྲུབ་མཐའི་ཚོང་རྡལ་གཞན་སུས་ཀྱང་།།",
    "target": "གྲུབ་ མཐ འི་ ཚོང་རྡལ་ གཞན་ སུ ས་ ཀྱང་ ། །"
  },
  {
    "source": "མ་ནུས་དེས་བསྒྲུབས་བློ་རྣོ་བ།།",
    "target": "མ་ནུ ས་ དེ ས་ བསྒྲུབས་ བློ་ རྣོ་བ ། །"
  },
  {
    "source": "ཕུར་བུ་བས་ཀྱང་ཕུལ་དུ་ཕྱིན།།",
    "target": "ཕུར་བུ་ བས་ ཀྱང་ ཕུལ་ དུ་ ཕྱིན ། །"
  },
  {
    "source": "རིང་ནས་གོམས་པ་གཞན་གྱིས་མ་ལྷོགས་པར།།",
    "target": "རིང་ ནས་ གོམས་པ་ གཞན་ གྱིས་ མ་ ལྷོགས་པ ར ། །"
  },
  {
    "source": "ནགས་སུ་ཞི་བའི་བརྟུལ་ཞུགས་ངེས་དོན་གཉེར།།",
    "target": "ནགས་ སུ་ ཞི་བ འི་ བརྟུལ་ཞུགས་ ངེས་དོན་ གཉེར ། །"
  },
  {
    "source": "བསྐལ་བརྒྱར་འབད་པའི་དྲང་སྲོང་རྒན་པོའི་ཡིད།།",
    "target": "བསྐལ་ བརྒྱ ར་ འབད་པ འི་ དྲང་སྲོང་ རྒན་པོ འི་ ཡིད ། །"
  },
  {
    "source": "ངལ་བའི་ཏིང་འཛིན་བཟང་པོ་ཡུད་ཀྱིས་རྙེད།།",
    "target": "ངལ་བ འི་ ཏིང་འཛིན་ བཟང་པོ་ ཡུད་ ཀྱིས་ རྙེད ། །"
  },
  {
    "source": "འཆད་པའི་ཉི་འོད་བཀྱེ་ཚེ་སློབ་འདོད་བློའི།།",
    "target": "འཆད་པ འི་ ཉི་འོད་ བཀྱེ་ ཚེ་ སློབ་ འདོད་ བློ འི ། །"
  },
  {
    "source": "འདབ་བརྒྱ་མཁས་པའི་སྦྲང་རྩིས་ཁེབས་པ་དང་།།",
    "target": "འདབ་ བརྒྱ་ མཁས་པ འི་ སྦྲང་རྩི ས་ ཁེབས་པ་ དང་ ། །"
  },
  {
    "source": "རྩོད་པའི་རིག་པས་ཕས་རྒོལ་མར་བཞུ་ཞིང་།།",
    "target": "རྩོད་པ འི་ རིག་པ ས་ ཕས་རྒོལ་ མ ར་ བཞུ་ ཞིང་ ། །"
  },
  {
    "source": "རྩོམ་པའི་སྣང་སྤྲོ་མངོན་མེད་ནམ་མཁའི་གཉེན།།",
    "target": "རྩོམ་པ འི་ སྣང་ སྤྲོ་ མངོན་ མེད་ ནམ་ མཁ འི་ གཉེན ། །"
  },
  {
    "source": "དེ་ནི་ལྗོངས་ཀྱི་ལྟད་མོའི་མཚོར།།",
    "target": "དེ་ ནི་ ལྗོངས་ ཀྱི་ ལྟད་མོ འི་ མཚོར ། །"
  },
  {
    "source": "གསང་ཚིག་འདོན་པ་ལྔ་བརྒྱར་བཅས།།",
    "target": "གསང་ཚིག་ འདོན་པ་ ལྔ་ བརྒྱ ར་ བཅས ། །"
  },
  {
    "source": "ལེགས་བཤད་མགྲིན་པའི་འགྱུར་ཁུགས་ལ།།",
    "target": "ལེགས་བཤད་ མགྲིན་པ འི་ འགྱུར་ ཁུགས་ ལ ། །"
  },
  {
    "source": "འགྲན་ཟླ་མེད་པ་སྟོན་བཞིན་སོང་།།",
    "target": "འགྲན་ཟླ་ མེད་པ་ སྟོན་ བཞིན་ སོང་ ། །"
  },
  {
    "source": "གང་དུ་ཕུན་སུམ་ཚོགས་པའི་འདོད་རྒུ་རྣམས།།",
    "target": "གང་ དུ་ ཕུན་སུམ་ཚོགས་པ འི་ འདོད་ རྒུ་ རྣམས ། །"
  },
  {
    "source": "ཕན་ཚུན་ཕྲད་འདོད་ཚོང་ཟོང་མང་པོ་ཡིས།།",
    "target": "ཕན་ཚུན་ ཕྲད་ འདོད་ ཚོང་ཟོང་ མང་པོ་ ཡིས ། །"
  },
  {
    "source": "རྣམ་པར་བསྒྱུར་ཏེ་སྲང་བར་དུ་ཆས་ནས།།",
    "target": "རྣམ་པ ར་ བསྒྱུར་ ཏེ་ སྲང་ བར་ དུ་ ཆས་ ནས ། །"
  },
  {
    "source": "སྐྱེ་བོའི་ལག་པར་ཕེབས་པར་སྨྲ་བ་བཞིན།།",
    "target": "སྐྱེ་བོ འི་ ལག་པ ར་ ཕེབས་པ ར་ སྨྲ་བ་ བཞིན ། །"
  },
  {
    "source": "དེ་དབུས་རྣམ་པར་རྒྱལ་བ་ཡི།།",
    "target": "དེ་ དབུས་ རྣམ་པ ར་ རྒྱལ་བ་ ཡི ། །"
  },
  {
    "source": "ཁང་བཟང་དཔེ་འོས་བཀྲ་ཤིས་པར།།",
    "target": "ཁང་ བཟང་ དཔེ་ འོས་ བཀྲ་ཤིས་པ ར ། །"
  },
  {
    "source": "གྲུབ་པ་དཔལ་གྱི་འབྱུང་གནས་ཞེས།།",
    "target": "གྲུབ་པ་ དཔལ་ གྱི་ འབྱུང་གནས་ ཞེས ། །"
  },
  {
    "source": "གྲགས་པའི་ཕུལ་དུ་སོན་པར་ཕྱིན།།",
    "target": "གྲགས་པ འི་ ཕུལ་ དུ་ སོན་པ ར་ ཕྱིན ། །"
  },
  {
    "source": "དེ་ནས་ས་སྐྱོང་དགེ་བ་ཡིས།།",
    "target": "དེ་ ནས་ ས་སྐྱོང་ དགེ་བ་ ཡིས ། །"
  },
  {
    "source": "སྡིག་པའི་གོ་སྐབས་ཀུན་བཀག་ནས།།",
    "target": "སྡིག་པ འི་ གོ་སྐབས་ ཀུན་ བཀག་ ནས ། །"
  },
  {
    "source": "ཡིད་ནི་བསམ་གཏན་ལ་ཆགས་པའི།།",
    "target": "ཡིད་ ནི་ བསམ་གཏན་ ལ་ ཆགས་ པ འི ། །"
  },
  {
    "source": "དྲང་སྲོང་བཞིན་དུ་ཞི་བ་དེའི།།",
    "target": "དྲང་སྲོང་ བཞིན་ དུ་ ཞི་བ་ དེ འི ། །"
  },
  {
    "source": "བཙུན་མོར་འཆི་མེད་བུ་མོ་ནི།།",
    "target": "བཙུན་མོ ར་ འཆི་མེད་ བུ་མོ་ ནི ། །"
  },
  {
    "source": "བདེ་སོགས་མིང་ཅན་འོངས་པའམ།།",
    "target": "བདེ་ སོགས་ མིང་ཅན་ འོངས་པ འམ ། །"
  },
  {
    "source": "ཐུབ་པའི་བསྟན་འགོག་ཡིད་སྲུབས་ཀྱི།།",
    "target": "ཐུབ་པ འི་ བསྟན་ འགོག་ ཡིད་ སྲུབས་ ཀྱི ། །"
  },
  {
    "source": "ལོངས་སྤྱོད་སྙིང་པོར་སོམ་ཉི་བྱུང་།།",
    "target": "ལོངས་སྤྱོད་ སྙིང་པོ ར་ སོམ་ཉི་ བྱུང་ ། །"
  },
  {
    "source": "མཛེས་སྡུག་རྫོགས་པ་དེའི་སྨིན་མའི།།",
    "target": "མཛེས་སྡུག་ རྫོགས་པ་ དེ འི་ སྨིན་མ འི ། །"
  },
  {
    "source": "མཐོན་མཐིང་ནགས་སུ་རྩེ་འདོད་པའི།།",
    "target": "མཐོན་མཐིང་ ནགས་ སུ་ རྩེ་ འདོད་པ འི ། །"
  },
  {
    "source": "མིག་གི་བུང་བ་མར་གྱིས་ནི།།",
    "target": "མིག་ གི་ བུང་བ་ མར་ གྱིས་ ནི ། །"
  },
  {
    "source": "སྤར་བའི་སྒྲོན་མེ་བཞིན་དུ་གཡོ།།",
    "target": "སྤར་བ འི་ སྒྲོན་མེ་ བཞིན་ དུ་ གཡོ ། །"
  },
  {
    "source": "དེ་ཡི་སྐྲ་ཚོགས་མཐུག་པོའི་ངོགས།།",
    "target": "དེ་ ཡི་ སྐྲ་ ཚོགས་ མཐུག་པོ འི་ ངོགས ། །"
  },
  {
    "source": "མུ་ཏིག་ཆུན་པོ་ཆགས་པ་ནི།།",
    "target": "མུ་ཏིག་ ཆུན་པོ་ ཆགས་པ་ ནི ། །"
  },
  {
    "source": "མཚན་མོའི་ཤར་རིའི་ཐོར་ཅོག་ནི།།",
    "target": "མཚན་མོ འི་ ཤར་རི འི་ ཐོར་ ཅོག་ ནི ། །"
  },
  {
    "source": "རྒྱུ་སྐར་འཕྲེང་བ་དཀྲིས་པ་བཞིན།།",
    "target": "རྒྱུ་ སྐར་ འཕྲེང་བ་ དཀྲིས་པ་ བཞིན ། །"
  },
  {
    "source": "ནུ་རྒྱས་མེ་ཏོག་གིས་གཡོ་བ།།",
    "target": "ནུ་ རྒྱས་ མེ་ཏོག་ གིས་ གཡོ་བ ། །"
  },
  {
    "source": "ཕྲ་བའི་རྐེད་པའི་འཁྲི་ཤིང་གང་།།",
    "target": "ཕྲ་བ འི་ རྐེད་པ འི་ འཁྲི་ཤིང་ གང་ ། །"
  },
  {
    "source": "འཆག་ངོགས་འཕོངས་རྒྱས་གླང་པོའི་སྣ།།",
    "target": "འཆག་ ངོགས་ འཕོངས་ རྒྱ ས་ གླང་པོ འི་ སྣ ། །"
  },
  {
    "source": "གཉིས་ཀྱིས་འབད་པས་སྐྱོར་བ་སྙམ།།",
    "target": "གཉིས་ ཀྱིས་ འབད་པ ས་ སྐྱོར་བ་ སྙམ ། །"
  },
  {
    "source": "མཛེས་མ་དེ་ལ་ཉི་འཆར་ནི།།",
    "target": "མཛེས་མ་ དེ་ ལ་ ཉི་འཆར་ ནི ། །"
  },
  {
    "source": "སེམས་ཤོར་འཇའ་ཚོན་ཟོལ་སྦྱོར་གྱིས།།",
    "target": "སེམས་ ཤོར་ འཇའ་ཚོན་ ཟོལ་སྦྱོར་ གྱིས ། །"
  },
  {
    "source": "འཁྱུད་ཚེ་མཁུར་ཚོས་དཀར་དམར་གྱི།།",
    "target": "འཁྱུད་ ཚེ་ མཁུར་ ཚོས་ དཀར་དམར་ གྱི ། །"
  },
  {
    "source": "འཛུམ་པའི་འོད་དེ་མགྲོན་དུ་བྲིམས།",
    "target": "འཛུམ་པ འི་ འོད་ དེ་ མགྲོན་ དུ་ བྲིམས །"
  },
  {
    "source": "སུམ་ཙེན་ཚལ་གྱི་མཱ་ལི་ཀའི།",
    "target": "སུམ་ ཙེན་ ཚལ་ གྱི་ མཱ་ ལི་ ཀ འི །"
  },
  {
    "source": "མེ་ཏོག་སྤུངས་པ་བསེར་བུ་ཡིས།",
    "target": "མེ་ཏོག་ སྤུངས་པ་ བསེར་བུ་ ཡིས །"
  },
  {
    "source": "བསྐུལ་བའི་དྲི་བསུང་ཞིམ་པོ་རྣམས།",
    "target": "བསྐུལ་བ འི་ དྲི་བསུང་ ཞིམ་པོ་ རྣམས །"
  },
  {
    "source": "དེ་ཡི་ཁ་ཡི་དབུགས་དང་འགྲན།",
    "target": "དེ་ ཡི་ ཁ་ ཡི་ དབུགས་ དང་ འགྲན །"
  },
  {
    "source": "གང་གི་མགུལ་ལ་དབྱངས་ཅན་མ།།",
    "target": "གང་ གི་ མགུལ་ ལ་ དབྱངས་ ཅན་ མ ། །"
  },
  {
    "source": "འཁྲིལ་ཞིང་སྙིང་ལ་ཐམས་ཅད་མཁྱེན།།",
    "target": "འཁྲིལ་ ཞིང་ སྙིང་ ལ་ ཐམས་ཅད་ མཁྱེན ། །"
  },
  {
    "source": "བབ་པ་འདྲ་བས་མཁས་པའི་མདུན།།",
    "target": "བབ་པ་ འདྲ་བ ས་ མཁས་པ འི་ མདུན ། །"
  },
  {
    "source": "སྨྲ་བའི་སྤོབས་པ་མི་དམན་ཏོ།།",
    "target": "སྨྲ་བ འི་ སྤོབས་པ་ མི་ དམན་ ཏོ ། །"
  },
  {
    "source": "རྒྱལ་པོའི་མདུན་སར་སྐྱེ་བོས་གདོང་བསུས་པའི།།",
    "target": "རྒྱལ་པོ འི་ མདུན་ ས ར་ སྐྱེ་བོ ས་ གདོང་ བསུས་ པ འི ། །"
  },
  {
    "source": "མཁས་པའི་ཤིང་ཤུན་འཆང་བ་གསལ་བ་ཡི།།",
    "target": "མཁས་པ འི་ ཤིང་ཤུན་ འཆང་བ་ གསལ་བ་ ཡི ། །"
  },
  {
    "source": "རིལ་བས་ལག་བྲེལ་ཡིད་གཞུངས་ཨོཾ་ཡིག་གླུར།།",
    "target": "རིལ་བ ས་ ལག་ བྲེལ་ ཡིད་ གཞུངས་ ཨོཾ་ ཡིག་ གླུར ། །"
  },
  {
    "source": "ལེན་པ་མཛངས་པའི་ཐོར་ཅོག་ཅན་དེ་སླེབ།།",
    "target": "ལེན་པ་ མཛངས་པ འི་ ཐོར་ཅོག་ ཅན་ དེ་ སླེབ ། །"
  },
  {
    "source": "དེ་ཡི་སྲི་ཞུར་རྒྱལ་པོ་བཙུན་མོ་དང་།།",
    "target": "དེ་ ཡི་ སྲི་ཞུ ར་ རྒྱལ་པོ་ བཙུན་མོ་ དང་ ། །"
  },
  {
    "source": "བློན་པོ་དམག་སྡེར་བཅས་འོང་བཙུན་མོའི་མིག།",
    "target": "བློན་པོ་ དམག་ སྡེ ར་ བཅས་ འོང་ བཙུན་མོ འི་ མིག །"
  },
  {
    "source": "བརྗིད་པའི་དྲང་སྲོང་ཆེ་དེ་ཕྱོགས་སུ་ལྷུང་།།",
    "target": "བརྗིད་པ འི་ དྲང་སྲོང་ ཆེ་ དེ་ ཕྱོགས་ སུ་ ལྷུང་ ། །"
  },
  {
    "source": "སྐྱེ་བོས་འཇིགས་ནས་གཡོ་མེད་མ་ནུས་པར།།",
    "target": "སྐྱེ་བོ ས་ འཇིགས་ ནས་ གཡོ་ མེད་ མ་ ནུས་པ ར ། །"
  },
  {
    "source": "གཞན་ལྟའི་ཟོལ་གྱིས་ཡང་ཡང་དེ་ཉིད་བཙོས།།",
    "target": "གཞན་ ལྟ འི་ ཟོལ་ གྱིས་ ཡང་ ཡང་ དེ་ ཉིད་ བཙོས ། །"
  },
  {
    "source": "ཐུབ་པ་དེ་ཡང་གཏམ་གྱི་གསེང་བཙལ་ནས།།",
    "target": "ཐུབ་པ་ དེ་ ཡང་ གཏམ་ གྱི་ གསེང་ བཙལ་ ནས ། །"
  },
  {
    "source": "དགའ་མའི་བཞིན་རས་བསམ་གཏན་བསྒོམ་པའི་མཐར།།",
    "target": "དགའ་མ འི་ བཞིན་ རས་ བསམ་གཏན་ བསྒོམ་པ འི་ མཐ ར ། །"
  },
  {
    "source": "ལས་ཀྱི་སྐུད་པས་ཕན་ཚུན་འཚེམ་པ་བསྒྲུབས།།",
    "target": "ལས་ ཀྱི་ སྐུད་པ ས་ ཕན་ཚུན་ འཚེམ་ པ་ བསྒྲུབས ། །"
  },
  {
    "source": "དེ་གཉིས་སེམས་པའི་ངུར་པ་ཤུག།",
    "target": "དེ་ གཉིས་ སེམས་པ འི་ ངུར་པ་ ཤུག །"
  },
  {
    "source": "སྐྱེ་བར་འགྲོགས་པའི་སྲེད་པ་ནི།།",
    "target": "སྐྱེ་བ ར་ འགྲོགས་པ འི་ སྲེད་པ་ ནི ། །"
  },
  {
    "source": "ཡིད་གཅུགས་ཆུ་ཀླུང་དུ་ཞུགས་ཀྱང་།།",
    "target": "ཡིད་ གཅུགས་ ཆུ་ ཀླུང་ དུ་ ཞུགས་ ཀྱང་ ། །"
  },
  {
    "source": "མཛའ་བའི་ཀུ་ཅོ་འབྱིན་མ་ནུས།།",
    "target": "མཛའ་བ འི་ ཀུ་ཅོ་ འབྱིན་ མ་ ནུས ། །"
  },
  {
    "source": "དེ་ཚེ་ཉིན་བཞིན་ཟུར་མིག་གི།",
    "target": "དེ་ ཚེ་ ཉིན་ བཞིན་ ཟུར་མིག་ གི །"
  },
  {
    "source": "རྒྱ་ལ་ཕན་ཚུན་འཐུམས་མཐོང་ནས།།",
    "target": "རྒྱ་ ལ་ ཕན་ཚུན་ འཐུམས་ མཐོང་ ནས ། །"
  },
  {
    "source": "འགྲོལ་འདོད་གཏམ་གྱི་ཆུ་སྐྱར་གྱིས།།",
    "target": "འགྲོལ་ འདོད་ གཏམ་ གྱི་ ཆུ་སྐྱ ར་ གྱིས ། །"
  },
  {
    "source": "དེ་དག་བར་དུ་འགྲོ་འོང་བྱས།།",
    "target": "དེ་ དག་ བར་ དུ་ འགྲོ་འོང་ བྱས ། །"
  },
  {
    "source": "འགྲོགས་པའི་སྐབས་འཕོངས་དེ་དག་ལ།།",
    "target": "འགྲོགས་པ འི་ སྐབས་ འཕོངས་ དེ་ དག་ ལ ། །"
  },
  {
    "source": "སྐད་ཅིག་རེ་རེའང་འདི་མཚུངས་ཞེས།།",
    "target": "སྐད་ ཅིག་ རེ་རེ འང་ འདི་ མཚུངས་ ཞེས ། །"
  },
  {
    "source": "བྱང་དུ་བགྲོད་པའི་གོ་ལ་ཡིས།།",
    "target": "བྱང་ དུ་ བགྲོད་པ འི་ གོ་ ལ་ ཡིས ། །"
  },
  {
    "source": "ཤིན་ཏུ་རིང་བའི་ཉིན་མོ་སྤྲུལ།།",
    "target": "ཤིན་ ཏུ་ རིང་བ འི་ ཉིན་མོ་ སྤྲུལ ། །"
  },
  {
    "source": "དེ་ཚེ་འཁྲི་ཤིང་ན་ཆུང་གི།",
    "target": "དེ་ ཚེ་ འཁྲི་ ཤིང་ ན་ ཆུང་ གི །"
  },
  {
    "source": "ཁ་ལ་ཆུ་སྐྱེས་གཞོན་ནུས་སོ།།",
    "target": "ཁ་ ལ་ ཆུ་ སྐྱེས་ གཞོན་ནུ ས་ སོ ། །"
  },
  {
    "source": "བྱས་འདི་ཡིད་སྲུབས་བསླབ་པ་དེར།།",
    "target": "བྱས་ འདི་ ཡིད་ སྲུབས་ བསླབ་པ་ དེ ར ། །"
  },
  {
    "source": "སློབ་མའི་ཕོ་ཉ་དང་པོར་འོངས།།",
    "target": "སློབ་མ འི་ ཕོ་ཉ་ དང་པོ ར་ འོངས ། །"
  },
  {
    "source": "ན་ཆུང་གཟུགས་གསར་འདི་རྣམས་ལ།།",
    "target": "ན་ ཆུང་ གཟུགས་ གསར་ འདི་ རྣམས་ ལ ། །"
  },
  {
    "source": "འདོད་པའི་གདུང་བ་འདི་འདྲ་ཞེས།།",
    "target": "འདོད་པ འི་ གདུང་བ་ འདི་ འདྲ་ ཞེས ། །"
  },
  {
    "source": "དཔྱིད་ཀྱི་སྤྲིན་བྲལ་ཉིན་མོའི་གནམ།།",
    "target": "དཔྱིད་ ཀྱི་ སྤྲིན་ བྲལ་ ཉིན་ མོ འི་ གནམ ། །"
  },
  {
    "source": "མཛའ་བོར་སྦྲོན་པའི་ཆོ་ག་བྱེད།།",
    "target": "མཛའ་བོ ར་ སྦྲོན་ པ འི་ ཆོ་ག་ བྱེད ། །"
  },
  {
    "source": "གནམ་ཀའི་མདངས་འཛིན་མཚོ་སྡོན་མ།།",
    "target": "གནམ་ ཀ འི་ མདངས་ འཛིན་ མཚོ་ སྡོན་ མ ། །"
  },
  {
    "source": "གསེར་གྱི་ངུར་པས་རོལ་བའི་ཤིང་།།",
    "target": "གསེར་ གྱི་ ངུར་པ ས་ རོལ་བ འི་ ཤིང་ ། །"
  },
  {
    "source": "མཛའ་ཅན་མ་རྣམས་དྲན་སློང་པའི།།",
    "target": "མཛའ་ ཅན་ མ་ རྣམས་ དྲན་ སློང་ པ འི ། །"
  },
  {
    "source": "དེ་ལ་བྱེད་པོས་བཀོད་པ་བཞིན།།",
    "target": "དེ་ ལ་ བྱེད་པོ ས་ བཀོད་པ་ བཞིན ། །"
  },
  {
    "source": "དེ་ཚེ་གྲོང་གི་གཞོན་ནུ་རྣམས།།",
    "target": "དེ་ ཚེ་ གྲོང་ གི་ གཞོན་ནུ་ རྣམས ། །"
  },
  {
    "source": "ཕན་ཚུན་རྩེད་འཇོ་ཉམས་དགའི་ཚོགས།།",
    "target": "ཕན་ཚུན་ རྩེད་འཇོ་ ཉམས་ དག འི་ ཚོགས ། །"
  },
  {
    "source": "ཆར་སྤྲིན་འབྲུག་སྒྲ་ཅན་མཐོང་བའི།།",
    "target": "ཆར་ སྤྲིན་ འབྲུག་སྒྲ་ ཅན་ མཐོང་ བ འི ། །"
  },
  {
    "source": "རྨ་བྱའི་གར་གྱི་སྙེམས་འཕྲོག་ཟློས།།",
    "target": "རྨ་བྱ འི་ གར་ གྱི་ སྙེམས་ འཕྲོག་ ཟློས ། །"
  },
  {
    "source": "དེ་ནས་སྐབས་ཞིག་དཀའ་ཐུབ་པས།།",
    "target": "དེ་ ནས་ སྐབས་ ཞིག་ དཀའ་ཐུབ་པ ས ། །"
  },
  {
    "source": "རྨོངས་བྱེད་སྔགས་ཀྱི་སྐྱེ་བོ་རྣམས།།",
    "target": "རྨོངས་བྱེད་ སྔགས་ ཀྱི་ སྐྱེ་བོ་ རྣམས ། །"
  },
  {
    "source": "མུན་པའི་ནང་དུ་བསྙལ་བའི་མཐར།།",
    "target": "མུན་པ འི་ ནང་ དུ་ བསྙལ་བ འི་ མཐ ར ། །"
  },
  {
    "source": "དགུག་པའི་རིག་པ་དེ་ལ་སྦྱར།།",
    "target": "དགུག་པ འི་ རིག་པ་ དེ་ ལ་ སྦྱར ། །"
  },
  {
    "source": "བར་བཅད་མེད་པའི་ཁང་བུ་དེར།།",
    "target": "བར་ བཅད་ མེད་པ འི་ ཁང་བུ་ དེ ར ། །"
  },
  {
    "source": "འགྲོགས་པ་ཐོབ་པ་དེ་གཉིས་ཀྱིས།།",
    "target": "འགྲོགས་པ་ ཐོབ་པ་ དེ་ གཉིས་ ཀྱིས ། །"
  },
  {
    "source": "བསམ་གཏན་པ་ཡི་དགའ་བ་ཀུན།།",
    "target": "བསམ་གཏན་ པ་ ཡི་ དགའ་བ་ ཀུན ། །"
  },
  {
    "source": "ཡུད་ཀྱིས་སོར་མོའི་རྩེ་ལ་བླངས།།",
    "target": "ཡུད་ ཀྱིས་ སོར་མོ འི་ རྩེ་ ལ་ བླངས ། །"
  },
  {
    "source": "ཀྭ་ཡི་སྙིང་གྲོགས་བུང་བ་འདིའི།།",
    "target": "ཀྭ་ ཡི་ སྙིང་གྲོགས་ བུང་བ་ འདི འི ། །"
  },
  {
    "source": "ཁ་ཡི་ཆུ་སྐྱེས་ལ་ཇི་བཞིན།།",
    "target": "ཁ་ ཡི་ ཆུ་ སྐྱེས་ ལ་ ཇི་ བཞིན ། །"
  },
  {
    "source": "ག་ལེ་ཁྱོད་ཀྱིས་ཞལ་དེས་ཀྱང་།།",
    "target": "ག་ལེ་ ཁྱོད་ ཀྱིས་ ཞལ་ དེ ས་ ཀྱང་ ། །"
  },
  {
    "source": "ང་ལ་མཛོད་ཅེས་ཞུས་པའི་ལན།།",
    "target": "ང་ ལ་ མཛོད་ ཅེས་ ཞུས་པ འི་ ལན ། །"
  },
  {
    "source": "ཅ་རེ་བལྟས་པས་ཡིད་སིམ་མི་ནུས་ཀྱི།།",
    "target": "ཅ་ རེ་ བལྟས་པ ས་ ཡིད་ སིམ་ མི་ ནུས་ ཀྱི ། །"
  },
  {
    "source": "ཆ་ཤས་མྱུར་བའི་རེག་པ་གསར་པ་ནི།།",
    "target": "ཆ་ ཤས་ མྱུར་བ འི་ རེག་པ་ གསར་པ་ ནི ། །"
  },
  {
    "source": "ཇ་ཡིས་མི་མཚོན་བདུད་རྩིའི་རང་བཞིན་ཅན།།",
    "target": "ཇ་ ཡིས་ མི་ མཚོན་ བདུད་རྩི འི་ རང་བཞིན་ ཅན ། །"
  },
  {
    "source": "ཉ་པའི་ཟླས་བཞིན་བདག་ལ་སྦྱིན་ཞེས་སྨྲས།།",
    "target": "ཉ་པ འི་ ཟླས་ བཞིན་ བདག་ ལ་ སྦྱིན་ ཞེས་ སྨྲས ། །"
  },
  {
    "source": "ཏ་ལེ་ཉམ་འཕག་ཚད་དེར་ཡིད་འཛིན་མས།།",
    "target": "ཏ་ལེ་ ཉམ་ འཕག་ ཚད་ དེ ར་ ཡིད་ འཛིན་མ ས ། །"
  },
  {
    "source": "ཐ་དད་མེད་བསྡམས་ཁྱོད་ཀྱི་རྟག་ཏུ་ནི།།",
    "target": "ཐ་དད་ མེད་ བསྡམས་ ཁྱོད་ ཀྱི་ རྟག་ ཏུ་ ནི ། །"
  },
  {
    "source": "ད་ལྟ་བཞིན་དུ་ལུས་མེད་མདའ་བསྣུན་དང་།།",
    "target": "ད་ ལྟ་ བཞིན་ དུ་ ལུས་ མེད་ མདའ་ བསྣུན་ དང་ ། །"
  },
  {
    "source": "ན་བའི་སྨན་པ་མཛད་རོགས་གྱིས་ཞེས་གསོལ།།",
    "target": "ན་བ འི་ སྨན་པ་ མཛད་ རོགས་ གྱིས་ ཞེས་ གསོལ ། །"
  },
  {
    "source": "པ་ཏྲ་ལྟ་བུར་བསྐོར་ཞིང་གཅུ་བ་དང་།།",
    "target": "པ་ཏྲ་ ལྟ་བུ ར་ བསྐོར་ ཞིང་ གཅུ་བ་ དང་ ། །"
  },
  {
    "source": "ཕ་རོལ་སྐྱོབ་པའི་གདུགས་བཞིན་བཏེགས་ནས་སླར།།",
    "target": "ཕ་རོལ་ སྐྱོབ་པ འི་ གདུགས་ བཞིན་ བཏེགས་ ནས་ སླར ། །"
  },
  {
    "source": "བ་ལང་འདྲ་བར་གཉིད་ཀྱིས་གཞན་ནོན་ཚེ།།",
    "target": "བ་ལང་ འདྲ་བ ར་ གཉིད་ ཀྱིས་ གཞན་ ནོན་ ཚེ ། །"
  },
  {
    "source": "མ་གཅིག་ཁྱོད་འདོད་སྒྲུབ་ཅེས་གླེང་བའི་མཐར།།",
    "target": "མ་ གཅིག་ ཁྱོད་ འདོད་ སྒྲུབ་ ཅེས་ གླེང་བ འི་ མཐ ར ། །"
  },
  {
    "source": "ཙ་ར་ཀ་བཞིན་ཕྱོགས་གོས་ཅན།།",
    "target": "ཙ་ར་ ཀ་ བཞིན་ ཕྱོགས་ གོས་ ཅན ། །"
  },
  {
    "source": "ཚ་གྲང་གདུང་བ་ཀུན་བརྗེད་ནས།།",
    "target": "ཚ་གྲང་ གདུང་བ་ ཀུན་ བརྗེད་ ནས ། །"
  },
  {
    "source": "ཛ་ལང་ཡིད་སྲུབས་རྩེ་དགའི་དཔྱིད།།",
    "target": "ཛ་ལང་ ཡིད་ སྲུབས་ རྩེ་ དག འི་ དཔྱིད ། །"
  },
  {
    "source": "ཝ་ལེར་དྲན་པ་ཐམས་ཅད་བྱས།།",
    "target": "ཝ་ལེ ར་ དྲན་པ་ ཐམས་ཅད་ བྱས ། །"
  },
  {
    "source": "ཞྭ་ལྟར་མགོར་གྱོན་འོག་ཏུ་ནི།།",
    "target": "ཞྭ་ ལྟ ར་ མགོར་ གྱོན་ འོག་ ཏུ་ ནི ། །"
  },
  {
    "source": "ཟ་མ་བཞིན་དུ་ཞུགས་ནས་སུ།།",
    "target": "ཟ་མ་ བཞིན་ དུ་ ཞུགས་ ནས་ སུ ། །"
  },
  {
    "source": "འ་འུར་མེ་ལྕེ་མཉེད་པའི་རྡུལ།།",
    "target": "འ་འུར་ མེ་ལྕེ་ མཉེད་པ འི་ རྡུལ ། །"
  },
  {
    "source": "ཡ་རབས་རྣམས་ཀྱི་ཁྲུས་ཆུ་འདྲ།།",
    "target": "ཡ་རབས་ རྣམས་ ཀྱི་ ཁྲུས་ཆུ་ འདྲ ། །"
  },
  {
    "source": "ར་མ་ཎས་གཉེར་སཱི་ཏ་འམ།།",
    "target": "ར་མ་ ཎས་ གཉེར་ སཱི་ཏ་ འམ ། །"
  },
  {
    "source": "ལ་ལེའི་མཻ་ན་ཀ་གང་ཞེས།།",
    "target": "ལ་ ལེ འི་ མཻ་ ན་ ཀ་ གང་ ཞེས ། །"
  },
  {
    "source": "ཤ་ཚ་དེ་ལ་སླར་དྲིས་ལན།།",
    "target": "ཤ་ཚ་ དེ་ ལ་ སླ ར་ དྲིས་ལན ། །"
  },
  {
    "source": "ས་སྟེང་ཁྱོད་འདྲའི་སྙིང་གྲོགས་ད་མི་རྙེད།།",
    "target": "ས་ སྟེང་ ཁྱོད་ འདྲ འི་ སྙིང་གྲོགས་ ད་ མི་ རྙེད ། །"
  },
  {
    "source": "ཧ་ཅང་དུང་ང་ཁྱོད་དང་འབྲལ་མི་ཕོད།།",
    "target": "ཧ་ཅང་ དུང་ ང་ ཁྱོད་ དང་ འབྲལ་ མི་ ཕོད ། །"
  },
  {
    "source": "ཨ་ཙི་ཕོ་བྲང་འཁོར་འདིར་བཞུགས་ནས་སུ།།",
    "target": "ཨ་ཙི་ ཕོ་བྲང་ འཁོར་ འདི ར་ བཞུགས་ ནས་ སུ ། །"
  },
  {
    "source": "མཛའ་མོའི་རེ་བ་རྫོགས་པའི་བསམ་གཏན་མཛོད།།",
    "target": "མཛའ་མོ འི་ རེ་བ་ རྫོགས་པ འི་ བསམ་གཏན་ མཛོད ། །"
  },
  {
    "source": "དེ་ཚུལ་རིག་པ་འབངས་མོ་ཡི།།",
    "target": "དེ་ ཚུལ་ རིག་པ་ འབངས་མོ་ ཡི ། །"
  },
  {
    "source": "ཙ་ཀོ་ར་དེ་དགའ་བའི་ནགས།།",
    "target": "ཙ་ ཀོ་ ར་ དེ་ དགའ་བ འི་ ནག ས ། །"
  },
  {
    "source": "སྐྱོ་བ་བསངས་པའི་བཞད་བགད་གླུས།།",
    "target": "སྐྱོ་བ་ བསངས་པ འི་ བཞད་ བགད་ གླུས ། །"
  },
  {
    "source": "དྲི་ཟའི་འདུན་ས་བཞིན་དུ་བཀང་།།",
    "target": "དྲི་ཟ འི་ འདུན་ས་ བཞིན་ དུ་ བཀང་ ། །"
  },
  {
    "source": "ཨ་ཕྱི་འཁྲིག་པའི་ཚིག་ཟུར་ཆུ།།",
    "target": "ཨ་ཕྱི་ འཁྲིག་པ འི་ ཚིག་ ཟུར་ ཆུ ། །"
  },
  {
    "source": "ཅོ་འདྲིའི་བླུ་འཕྲེང་ཅན་རྣམས་ལས།།",
    "target": "ཅོ་འདྲི འི་ བླུ་ འཕྲེང་ ཅན་ རྣམས་ ལས ། །"
  },
  {
    "source": "སྙིང་པོས་འཕོངས་པའི་ལན་ཟམ་བཏང་།།",
    "target": "སྙིང་པོ ས་ འཕོངས་པ འི་ ལན་ ཟམ་ བཏང་ ། །"
  },
  {
    "source": "རང་འདོད་གསང་བས་བསྒྲལ་བར་བྱས།།",
    "target": "རང་འདོད་ གསང་ བས་ བསྒྲལ་བ ར་ བྱས ། །"
  },
  {
    "source": "འདབ་ཆགས་རྣམས་ཀྱིས་དེ་རིག་ནས།།",
    "target": "འདབ་ཆགས་ རྣམས་ ཀྱིས་ དེ་ རིག་ ནས ། །"
  },
  {
    "source": "ཕན་ཚུན་གླེང་བསླང་སྐབས་བཙལ་ཚེ།།",
    "target": "ཕན་ཚུན་ གླེང་ བསླང་ སྐབས་ བཙལ་ ཚེ ། །"
  },
  {
    "source": "ཚོད་ཅན་ཁུ་བྱུག་གིས་བཟློག་ཏུ།།",
    "target": "ཚོད་ ཅན་ ཁུ་བྱུག་ གིས་ བཟློག་ ཏུ ། །"
  },
  {
    "source": "མོན་གྱི་ཕྱོགས་ནས་དེ་དུས་འོངས།།",
    "target": "མོན་ གྱི་ ཕྱོགས་ ནས་ དེ་ དུས་ འོངས ། །"
  },
  {
    "source": "དེ་ཡིས་འབིགས་བྱེད་དྲན་སྐྱེས་ནས།།",
    "target": "དེ་ ཡིས་ འབིགས་བྱེད་ དྲན་ སྐྱེས་ ནས ། །"
  },
  {
    "source": "རང་གི་དགའ་མ་ལ་འཁྱུད་པའི།།",
    "target": "རང་ གི་ དགའ་ མ་ལ་ འཁྱུད་ པ འི ། །"
  },
  {
    "source": "དྲོད་ཀྱིས་བཞུ་བའི་རྔུལ་གྱི་ཐིགས།།",
    "target": "དྲོད་ ཀྱིས་ བཞུ་བ འི་ རྔུལ་ གྱི་ ཐིགས ། །"
  },
  {
    "source": "དབྱར་སྐྱེས་རྔ་སྒྲའི་མཐའ་དེར་ཕབ།།",
    "target": "དབྱར་སྐྱེས་རྔ་ སྒྲ འི་ མཐའ་ དེ ར་ ཕབ ། །"
  },
  {
    "source": "ཉལ་འགྲོ་མ་རྣམས་མེ་ལོང་གི",
    "target": "ཉལ་ འགྲོ་ མ་ རྣམས་ མེ་ལོང་ གི"
  },
  {
    "source": "།",
    "target": "།"
  },
  {
    "source": "དབྱིབས་གཟུང་ནོར་འཛིན་བུ་མོ་ཡི།།",
    "target": "དབྱིབས་ གཟུང་ ནོར་ འཛིན་བུ་ མོ་ ཡི ། །"
  },
  {
    "source": "སྐེད་པའི་ཁོར་ཡུག་ཀུན་བརྒྱན་ནས།།",
    "target": "སྐེད་པ འི་ ཁོར་ཡུག་ ཀུན་ བརྒྱན་ ནས ། །"
  },
  {
    "source": "མཛའ་བོའི་ཟླ་བརྙན་ཡིད་ཀྱིས་འཛིན།།",
    "target": "མཛའ་བོ འི་ ཟླ་ བརྙན་ ཡིད་ ཀྱིས་ འཛིན ། །"
  },
  {
    "source": "ས་གཞི་སྔོ་ལྗང་མྱུ་གུ་དང་།།",
    "target": "ས་གཞི་ སྔོ་ལྗང་ མྱུ་གུ་ དང་ ། །"
  },
  {
    "source": "མེ་ཏོག་བུང་བ་ལྡིང་རྣམས་ཀྱིས།།",
    "target": "མེ་ཏོག་ བུང་བ་ ལྡིང་ རྣམས་ ཀྱིས ། །"
  },
  {
    "source": "སྤྲས་པ་ཡོངས་འདུའི་དྲུང་ལྟ་བུའི།།",
    "target": "སྤྲས་པ་ ཡོངས་ འདུ འི་ དྲུང་ ལྟ་བུ འི ། །"
  },
  {
    "source": "དྲི་བཟང་དར་བའི་དབྱར་དུས་སུ།།",
    "target": "དྲི་བཟང་ དར་བ འི་ དབྱར་ དུས་ སུ ། །"
  },
  {
    "source": "འདུ་བའི་དབྱི་མོང་ཕྲག་དོག་གིས།།",
    "target": "འདུ་བ འི་ དབྱི་མོང་ ཕྲག་དོག་ གིས ། །"
  },
  {
    "source": "འཁྲུགས་པས་ཡིད་སྲུབས་རྩེ་དགའི་ཤིང་།།",
    "target": "འཁྲུགས་པ ས་ ཡིད་ སྲུབས་ རྩེ་ དག འི་ ཤིང་ ། །"
  },
  {
    "source": "དར་བའི་གོ་བཀག་དེ་སེལ་དུ།།",
    "target": "དར་བ འི་ གོ་ བཀག་ དེ་ སེལ་ དུ ། །"
  },
  {
    "source": "ཤེས་པའི་སྟ་རེ་བཟུང་སྟེ་འོང་།།",
    "target": "ཤེས་པ འི་ སྟ་རེ་ བཟུང་ སྟེ་ འོང་ ། །"
  },
  {
    "source": "དེས་དེའི་བཞིན་གྱི་པདྨོ་ལ།།",
    "target": "དེ ས་ དེ འི་ བཞིན་ གྱི་ པདྨོ་ ལ ། །"
  },
  {
    "source": "གསེར་གྱི་བུང་བས་བཞིན་བྱས་ནས།།",
    "target": "གསེར་ གྱི་ བུང་བ ས་ བཞིན་ བྱས་ ནས ། །"
  },
  {
    "source": "འཁྱུད་པ་ལུས་ལ་ལྕགས་སྒྲོག་བཞིན།།",
    "target": "འཁྱུད་པ་ ལུས་ ལ་ ལྕགས་སྒྲོག་ བཞིན ། །"
  },
  {
    "source": "དེ་ཡི་ལུས་ལ་དེ་ཡིས་བསྡམས།།",
    "target": "དེ་ ཡི་ ལུས་ ལ་ དེ་ ཡིས་ བསྡམས ། །"
  },
  {
    "source": "སྟོན་ཀའི་འབྲུ་ཡི་དཔལ་རྣམས་ལ།།",
    "target": "སྟོན་ཀ འི་ འབྲུ་ ཡི་ དཔལ་ རྣམས་ ལ ། །"
  },
  {
    "source": "མཛེས་པ་སྟོན་དུ་ཟླ་བའི་གདོང་།།",
    "target": "མཛེས་པ་ སྟོན་ དུ་ ཟླ་བ འི་ གདོང་ ། །"
  },
  {
    "source": "རི་བོང་མཚན་མའི་སྨུག་རྩི་ཡིས།།",
    "target": "རི་བོང་མཚན་མ འི་ སྨུག་རྩི་ ཡིས ། །"
  },
  {
    "source": "བུ་མོའི་བཞིན་ལ་འགྲན་པ་འོང་།།",
    "target": "བུ་མོ འི་ བཞིན་ ལ་ འགྲན་པ་ འོང་ ། །"
  },
  {
    "source": "རྩི་ཤིང་འདབ་མ་འགྱུར་བའི་དུས།།",
    "target": "རྩི་ཤིང་ འདབ་མ་ འགྱུར་བ འི་ དུས ། །"
  },
  {
    "source": "བ་མོས་མེ་ཏོག་བརྙིངས་བྱས་པར།།",
    "target": "བ་མོ ས་ མེ་ཏོག་ བརྙིངས་ བྱས་པ ར ། །"
  },
  {
    "source": "སྐྱོ་བཞིན་མཛའ་བོ་རིང་སོང་བའི།།",
    "target": "སྐྱོ་ བཞིན་ མཛའ་བོ་ རིང་ སོང་ བ འི ། །"
  },
  {
    "source": "བཤུལ་རིང་གླལ་དགོས་དེ་ལ་བྱུང་།།",
    "target": "བཤུལ་ རིང་ གླལ་ དགོས་ དེ་ ལ་ བྱུང་ ། །"
  },
  {
    "source": "ལྗོན་ཤིང་རྣམས་ཀྱི་འདབ་མའི་གོས།།",
    "target": "ལྗོན་ཤིང་ རྣམས་ ཀྱི་ འདབ་མ འི་ གོས ། །"
  },
  {
    "source": "སྔོ་ལྗང་གསར་པ་གྱོན་བཞིན་གཞན།།",
    "target": "སྔོ་ལྗང་ གསར་པ་ གྱོན་ བཞིན་ གཞན ། །"
  },
  {
    "source": "མྱུ་གུའི་རྒྱན་གྱིས་ནོར་འཛིན་མ།།",
    "target": "མྱུ་གུ འི་ རྒྱན་ གྱིས་ ནོར་འཛིན་ མ ། །"
  },
  {
    "source": "བརྒྱན་པའི་དཔྱིད་ཀ་དུས་འཛོམ་བྱས།།",
    "target": "བརྒྱན་པ འི་ དཔྱིད་ཀ་ དུས་ འཛོམ་ བྱས ། །"
  },
  {
    "source": "ཡིད་ནི་རྒྱལ་པོའི་དགའ་མ་ལ།།",
    "target": "ཡིད་ ནི་ རྒྱལ་པོ འི་ དགའ་མ་ ལ ། །"
  },
  {
    "source": "བཞག་པའི་ཚངས་སྲས་དེ་དབེན་པར།།",
    "target": "བཞག་པ འི་ ཚངས་ སྲས་ དེ་ དབེན་པ ར ། །"
  },
  {
    "source": "འདུག་པ་མེ་ཏོག་གིས་ལྕི་བའི།།",
    "target": "འདུག་པ་ མེ་ཏོག་ གིས་ ལྕི་བ འི ། །"
  },
  {
    "source": "ཆུ་ཤིང་སྡོང་པོ་གཞན་པ་བཞིན།།",
    "target": "ཆུ་ཤིང་ སྡོང་པོ་ གཞན་པ་ བཞིན ། །"
  },
  {
    "source": "སླར་ཡང་མཆོད་སྦྱིན་གཙོ་བོར་དེ་འོངས་ཚེ།།",
    "target": "སླ ར་ ཡང་ མཆོད་སྦྱིན་ གཙོ་བོ ར་ དེ་ འོངས་ ཚེ ། །"
  },
  {
    "source": "བདག་པོར་ཉེ་བ་དོན་གཞན་བཀོད་པའི་རྒྱན།།",
    "target": "བདག་ པོ ར་ ཉེ་བ་ དོན་ གཞན་ བཀོད་པ འི་ རྒྱན ། །"
  },
  {
    "source": "སྙན་དངགས་མཁན་དབང་མང་པོའི་ཁ་ལ་ནི།།",
    "target": "སྙན་དངགས་ མཁན་ དབང་ མང་པོ འི་ ཁ་ ལ་ ནི ། །"
  },
  {
    "source": "སྔོན་ཆད་མ་བརྒྱུས་བཙུན་མོས་དེ་འདུན་དྲན།།",
    "target": "སྔོན་ཆད་ མ་ བརྒྱུ ས་ བཙུན་མོ ས་ དེ་ འདུན་ དྲན ། །"
  },
  {
    "source": "ན་ཆུང་ལས་གཟིགས་ལི་ཁྲིའི་མཚམས་སྤྲིན་གྱིས།།",
    "target": "ན་ ཆུང་ ལས་ གཟིགས་ ལི་ཁྲི འི་ མཚམས་ སྤྲིན་ གྱིས ། །"
  },
  {
    "source": "དྷཱུ་ཏཱིའི་ནམ་མཁའ་བཀང་སྟེ་མངོན་བྱང་གི།",
    "target": "དྷཱུ་ ཏཱིའི་ ནམ་མཁའ་ བཀང་ སྟེ་ མངོན་བྱང་ གི །"
  },
  {
    "source": "ནུབ་རིར་ཐུབ་པའི་ཉི་མ་གཉིད་ལོག་པ།།",
    "target": "ནུབ་རི ར་ ཐུབ་པ འི་ ཉི་མ་ གཉིད་ ལོག་པ ། །"
  },
  {
    "source": "རྣམ་བཅས་རླུང་གིས་སད་ཚེ་ཟུང་འཇུག་མཁར།།",
    "target": "རྣམ་ བཅས་ རླུང་ གིས་ སད་ ཚེ་ ཟུང་འཇུག་ མཁར ། །"
  },
  {
    "source": "གཞན་གྱི་ལུས་སེམས་ཐར་པའི་རང་བཞིན་དུ།།",
    "target": "གཞན་ གྱི་ ལུས་སེམས་ ཐར་པ འི་ རང་བཞིན་ དུ ། །"
  },
  {
    "source": "དལ་བུར་སྤྲོ་བ་སྲིད་མཐར་མི་ཉམས་པས།།",
    "target": "དལ་བུ ར་ སྤྲོ་བ་ སྲིད་ མཐ ར་ མི་ ཉམས་པ ས ། །"
  },
  {
    "source": "ཡོན་ཏན་འདབ་བརྒྱའི་གེ་སར་འཕྲེང་སྤེལ་དུ།།",
    "target": "ཡོན་ཏན་ འདབ་ བརྒྱ འི་ གེ་ ས ར་ འཕྲེང་ སྤེལ་ དུ ། །"
  },
  {
    "source": "ལེགས་པར་རྒྱུ་སྟེ་རྣ་བའི་དཔྱིད་ཅིས་མིན།།",
    "target": "ལེགས་པ ར་ རྒྱུ་ སྟེ་ རྣ་བ འི་ དཔྱིད་ ཅི ས་ མིན ། །"
  },
  {
    "source": "རབ་བཏགས་ཀྱི་གཏམ་རྣ་བའི་རྒྱན་ཞེས་བྱ་བ་པདྨ་དཀར་པོས་སྦྱར་བ་རྫོགས་སོ།།",
    "target": "རབ་བཏགས་ ཀྱི་ གཏམ་ རྣ་བ འི་ རྒྱན་ ཞེས་ བྱ་བ་ པདྨ་ དཀར་པོ ས་ སྦྱར་བ་ རྫོགས་ སོ ། །"
  },
  {
    "source": "།།",
    "target": "། །"
  },
  {
    "source": "སརྦ་མངྒལཾ།།",
    "target": "སརྦ་ མངྒལཾ ། །"
  },
  {
    "source": "།།",
    "target": "། །"
  }
]
