[
  {
    "source": "༄༅།།",
    "target": "༄༅ ། །"
  },
  {
    "source": "མི་རྒོད་རྣམ་པར་འཇོམས་པ་ཞེས་བྱ་བ་བཞུགས།",
    "target": "མི་རྒོད་ རྣམ་པ ར་ འཇོམས་པ་ ཞེས་ བྱ་བ་ བཞུགས །"
  },
  {
    "source": "༄༅།།",
    "target": "༄༅ ། །"
  },
  {
    "source": "རྒྱ་གར་སྐད་དུ།",
    "target": "རྒྱ་གར་ སྐད་ དུ །"
  },
  {
    "source": "ཨཱརྻ་ཙོ་ར་བི་དྷ་ན་ས་ན་ནཱ་མ་དྷ་ར་ཎི།",
    "target": "ཨཱརྻ་ ཙོ་ར་ བི་དྷ་ ན་ ས་ ན་ ནཱ་མ་ དྷ་ར་ཎི །"
  },
  {
    "source": "བོད་སྐད་དུ།",
    "target": "བོད་ སྐད་ དུ །"
  },
  {
    "source": "འཕགས་པ་མི་རྒོད་རྣམ་པར་འཇོམས་པ་ཞེས་བྱ་བའི་གཟུངས།",
    "target": "འཕགས་པ་ མི་རྒོད་ རྣམ་པ ར་ འཇོམས་པ་ ཞེས་ བྱ་བ འི་ གཟུངས །"
  },
  {
    "source": "སངས་རྒྱས་དང་།",
    "target": "སངས་རྒྱས་ དང་ །"
  },
  {
    "source": "བྱང་ཆུབ་སེམས་དཔའ་ཐམས་ཅད་ལ་ཕྱག་འཚལ་ལོ།།",
    "target": "བྱང་ཆུབ་སེམས་དཔའ་ ཐམས་ཅད་ ལ་ ཕྱག་ འཚལ་ ལོ ། །"
  },
  {
    "source": "འདི་སྐད་བདག་གིས་ཐོས་པ་དུས་གཅིག་ན།",
    "target": "འདི་ སྐད་ བདག་ གིས་ ཐོས་པ་ དུས་ གཅིག་ ན །"
  },
  {
    "source": "བཅོམ་ལྡན་འདས་ཞབས་འབྲིང་བ་ཚེ་དང་ལྡན་པ་ཀུན་དགའ་བོ་དང་ཐབས་གཅིག་ཏུ།",
    "target": "བཅོམ་ལྡན་འདས་ ཞབས་འབྲིང་ བ་ ཚེ་ དང་ ལྡན་པ་ ཀུན་དགའ་བོ་ དང་ ཐབས་ གཅིག་ ཏུ །"
  },
  {
    "source": "ལུས་འཕགས་རི་ལ་གཤེགས་པའི་ཚེ།",
    "target": "ལུས་ འཕགས་ རི་ ལ་ གཤེགས་པ འི་ ཚེ །"
  },
  {
    "source": "ཚེ་དང་ལྡན་པ་ཀུན་དགའ་བོས།",
    "target": "ཚེ་ དང་ ལྡན་པ་ ཀུན་དགའ་བོ ས །"
  },
  {
    "source": "མི་རྒོད་ཕལ་པོ་ཆེ་ཞིག་རྒྱང་མ་ནས་མཐོང་ངོ་།།",
    "target": "མི་རྒོད་ ཕལ་པོ་ཆེ་ ཞིག་ རྒྱང་མ་ ནས་ མཐོང་ ངོ་ ། །"
  },
  {
    "source": "མཐོང་ནས་ཀྱང་སྐྲག་སྟེ།",
    "target": "མཐོང་ ནས་ ཀྱང་ སྐྲག་ སྟེ །"
  },
  {
    "source": "སྤུ་ཟིང་ཞེས་བྱེད་ནས།",
    "target": "སྤུ་ཟིང་ ཞེས་ བྱེད་ ནས །"
  },
  {
    "source": "བཅོམ་ལྡན་འདས་ལ་འདི་སྐད་ཅེས་གསོལ་ཏོ།།",
    "target": "བཅོམ་ལྡན་འདས་ ལ་ འདི་ སྐད་ ཅེས་ གསོལ་ ཏོ ། །"
  },
  {
    "source": "བཅོམ་ལྡན་འདས་མི་རྒོད་དག་ཅིག་གོ།",
    "target": "བཅོམ་ལྡན་འདས་ མི་རྒོད་ དག་ ཅིག་ གོ །"
  },
  {
    "source": "བདེ་བར་གཤེགས་པ་མི་རྒོད་དག་ཅིག་གོ།",
    "target": "བདེ་བ ར་ གཤེགས་པ་ མི་རྒོད་ དག་ ཅིག་ གོ །"
  },
  {
    "source": "བཅོམ་ལྡན་འདས་ཀྱིས་བཀའ་སྩལ་པ།",
    "target": "བཅོམ་ལྡན་འདས་ ཀྱིས་ བཀའ་ སྩལ་པ །"
  },
  {
    "source": "ཀུན་དགའ་བོ་ཁྱོད་མི་རྒོད་རྣམས་ཀྱིས་འཇིགས་སམ།",
    "target": "ཀུན་དགའ་བོ་ ཁྱོད་ མི་རྒོད་ རྣམས་ ཀྱིས་ འཇིགས་ སམ །"
  },
  {
    "source": "གསོལ་པ།",
    "target": "གསོལ་པ །"
  },
  {
    "source": "བཅོམ་ལྡན་འདས་འཇིགས་ལགས་སོ།།",
    "target": "བཅོམ་ལྡན་འདས་ འཇིགས་ ལགས་ སོ ། །"
  },
  {
    "source": "བདེ་བར་གཤེགས་པ་འཇིགས་ལགས་སོ།།",
    "target": "བདེ་བ ར་ གཤེགས་པ་ འཇིགས་ ལགས་ སོ ། །"
  },
  {
    "source": "བཅོམ་ལྡན་འདས་ཀྱིས་བཀའ་སྩལ་པ།",
    "target": "བཅོམ་ལྡན་འདས་ ཀྱིས་ བཀའ་ སྩལ་པ །"
  },
  {
    "source": "ཀུན་དགའ་བོ།",
    "target": "ཀུན་དགའ་བོ །"
  },
  {
    "source": "མི་རྒོད་རྣམས་ཀྱིས་མ་འཇིགས་ཤིག།",
    "target": "མི་རྒོད་ རྣམས་ ཀྱིས་ མ་ འཇིགས་ ཤིག །"
  },
  {
    "source": "དེ་ནས་བཅོམ་ལྡན་འདས་ཀྱིས་དེའི་ཚེ།",
    "target": "དེ་ ནས་ བཅོམ་ལྡན་འདས་ ཀྱིས་ དེ འི་ ཚེ །"
  },
  {
    "source": "གཏི་མུག་ཆེན་པོའི་ཚོགས་རབ་ཏུ་གཞོམ་པ་འདི་བཀའ་བསྩལ་ཏོ།།",
    "target": "གཏི་མུག་ ཆེན་པོ འི་ ཚོགས་ རབ་ ཏུ་ གཞོམ་པ་ འདི་ བཀའ་ བསྩལ་ ཏོ ། །"
  },
  {
    "source": "ཏདྱ་ཐཱ།",
    "target": "ཏདྱ་ཐཱ །"
  },
  {
    "source": "ཨ་ནུ་ལོ་མེ་པྲ་ཏི་ལོ་མེ།",
    "target": "ཨ་ནུ་ ལོ་ མེ་ པྲ་ཏི་ ལོ་ མེ །"
  },
  {
    "source": "ཨ་ནུ་ལོ་མ།",
    "target": "ཨ་ནུ་ ལོ་མ །"
  },
  {
    "source": "པྲ་ཏི་ལོ་མ།",
    "target": "པྲ་ཏི་ ལོ་ མ །"
  },
  {
    "source": "ཨ་ཏིཾ་ཀེ།",
    "target": "ཨ་ ཏིཾ་ ཀེ །"
  },
  {
    "source": "པྲ་ཏིཾ་ཀེ།",
    "target": "པྲ་ ཏིཾ་ ཀེ །"
  },
  {
    "source": "བཾ་ཀེ།",
    "target": "བཾ་ ཀེ །"
  },
  {
    "source": "ཨ་ཏི་པཾ་ཀེ།",
    "target": "ཨ་ཏི་ པཾ་ ཀེ །"
  },
  {
    "source": "གོ་རི།",
    "target": "གོ་ རི །"
  },
  {
    "source": "གནྡྷ་རི།",
    "target": "གནྡྷ་ རི །"
  },
  {
    "source": "ཙནྜ་ལཱི།",
    "target": "ཙནྜ་ ལཱི །"
  },
  {
    "source": "མ་ཏཾ་གི།",
    "target": "མ་ཏཾ་ གི །"
  },
  {
    "source": "པུཀྐ་སི།",
    "target": "པུཀྐ་ སི །"
  },
  {
    "source": "རི་མི་རི་མི།",
    "target": "རི་ མི་ རི་ མི །"
  },
  {
    "source": "རིདྡྷི།",
    "target": "རིདྡྷི །"
  },
  {
    "source": "མ་ཙེ་བིཥྚ་ཏི་ཙཽ་ར་པྲ་དནྟུ།",
    "target": "མ་ཙེ་ བིཥྚ་ ཏི་ ཙཽ་ར་ པྲ་ དནྟུ །"
  },
  {
    "source": "བི་སྠ་ཧནྟུ།",
    "target": "བི་ སྠ་ ཧནྟུ །"
  },
  {
    "source": "བྷ་མནྟུ།",
    "target": "བྷ་ མནྟུ །"
  },
  {
    "source": "མཱ་མི་ཡནྟུ།",
    "target": "མཱ་ མི་ ཡནྟུ །"
  },
  {
    "source": "ཡ་བད་གྲ་ན་ཐི་ན་མུཉྩ་མི་སྭཱ་ཧཱ།",
    "target": "ཡ་ བད་ གྲ་ ན་ ཐི་ ན་ མུཉྩ་ མི་ སྭཱ་ཧཱ །"
  },
  {
    "source": "ཀུན་དགའ་བོ།།",
    "target": "ཀུན་དགའ་བོ ། །"
  },
  {
    "source": "ངས་དཔག་ཚད་བཅུ་ཚུན་ཆད་ཀུན་ཏུ་སྲུང་བ་དང་།",
    "target": "ང ས་ དཔག་ཚད་ བཅུ་ ཚུན་ཆད་ ཀུན་ ཏུ་ སྲུང་བ་ དང་ །"
  },
  {
    "source": "མི་རྒོད་ཐམས་ཅད་དང་།",
    "target": "མི་རྒོད་ ཐམས་ཅད་ དང་ །"
  },
  {
    "source": "རི་སུལ་གྱི་གྲོང་ཁྱེར་གྱི་མི་ཐམས་ཅད་དང་།",
    "target": "རི་སུལ་ གྱི་ གྲོང་ཁྱེར་ གྱི་ མི་ ཐམས་ཅད་ དང་ །"
  },
  {
    "source": "གསེབ་ལམ་སྲུང་བ་ཐམས་ཅད་དང་།",
    "target": "གསེབ་ལམ་ སྲུང་བ་ ཐམས་ཅད་ དང་ །"
  },
  {
    "source": "གནོད་པར་སེམས་པ་ཐམས་ཅད་ཀྱི་རྐང་པ་བཅིངས་པར་བྱས་སོ།།",
    "target": "གནོད་པ ར་ སེམས་པ་ ཐམས་ཅད་ ཀྱི་ རྐང་པ་ བཅིངས་པ ར་ བྱས་ སོ ། །"
  },
  {
    "source": "རྨུགས་པར་བྱས་སོ།།",
    "target": "རྨུགས་པ ར་ བྱས་ སོ ། །"
  },
  {
    "source": "རེངས་པར་བྱས་སོ།།",
    "target": "རེངས་པ ར་ བྱས་ སོ ། །"
  },
  {
    "source": "ཇི་ལྟར་རྫ་མཁན་གྱིས་འཁོར་ལོ་བསྐོར་བའམ།",
    "target": "ཇི་ ལྟ ར་ རྫ་ མཁན་ གྱིས་ འཁོར་ལོ་ བསྐོར་བ འམ །"
  },
  {
    "source": "ཇི་ལྟར་རྫ་མཁན་གྱིས་འཁོར་ལོ་ཡོངས་སུ་བསྐོར་བ་ལྟར།",
    "target": "ཇི་ ལྟ ར་ རྫ་ མཁན་ གྱིས་ འཁོར་ལོ་ ཡོངས་ སུ་ བསྐོར་བ་ ལྟ ར །"
  },
  {
    "source": "མི་རྒོད་རྣམས་འདར་བར་གྱུར་ཅིག།",
    "target": "མི་རྒོད་ རྣམས་ འདར་བ ར་ གྱུར་ ཅིག །"
  },
  {
    "source": "རེངས་པར་གྱུར་ཅིག།",
    "target": "རེངས་པ ར་ གྱུར་ ཅིག །"
  },
  {
    "source": "མགོ་རྨོངས་པར་གྱུར་ཅིག",
    "target": "མགོ་རྨོངས་པ ར་ གྱུར་ ཅིག"
  },
  {
    "source": "།",
    "target": "།"
  },
  {
    "source": "བཅོམ་ལྡན་འདས་ཀྱིས་དེ་སྐད་ཅེས་བཀའ་བསྩལ་ནས།",
    "target": "བཅོམ་ལྡན་འདས་ ཀྱིས་ དེ་ སྐད་ ཅེས་ བཀའ་ བསྩལ་ ནས །"
  },
  {
    "source": "ཚེ་དང་ལྡན་པ་ཀུན་དགའ་བོ་ཡི་རངས་ཏེ།",
    "target": "ཚེ་ དང་ ལྡན་པ་ ཀུན་དགའ་བོ་ ཡི་ རངས་ ཏེ །"
  },
  {
    "source": "བཅོམ་ལྡན་འདས་ཀྱིས་གསུངས་པ་ལ་མངོན་པར་བསྟོད་དོ།།",
    "target": "བཅོམ་ལྡན་འདས་ ཀྱིས་ གསུངས་པ་ ལ་ མངོན་པ ར་ བསྟོད་ དོ ། །"
  },
  {
    "source": "ཆོ་ག་ནི་ཤིང་ཀུན་དང་།",
    "target": "ཆོ་ག་ ནི་ ཤིང་ ཀུན་ དང་ །"
  },
  {
    "source": "བོང་བུའི་སྤུ་བྲེགས་ཏེ།",
    "target": "བོང་བུ འི་ སྤུ་ བྲེགས་ ཏེ །"
  },
  {
    "source": "བུ་མོ་གཙང་མས་བཀལ་བའི་སྲད་བུ་ལ་ལན་ཉི་ཤུ་རྩ་གཅིག་བཟླས་བརྗོད་བྱའོ།།",
    "target": "བུ་མོ་ གཙང་མ ས་ བཀལ་ བ འི་ སྲད་བུ་ ལ་ ལན་ ཉི་ཤུ་ རྩ་ གཅིག་ བཟླས་ བརྗོད་ བྱ འོ ། །"
  },
  {
    "source": "ཡང་ན་གོས་ཀྱི་མཐའ་མ་ལ་མདུད་པ་བོར་ཏེ།",
    "target": "ཡང་ ན་ གོས་ ཀྱི་ མཐའ་མ་ ལ་ མདུད་པ་ བོར་ ཏེ །"
  },
  {
    "source": "བདེ་བར་ཕྱིན་ནས་དགྲོལ་བར་བྱའོ།།",
    "target": "བདེ་བ ར་ ཕྱིན་ ནས་ དགྲོལ་བ ར་ བྱ འོ ། །"
  },
  {
    "source": "འདི་ནི་གྲུབ་པའོ།།",
    "target": "འདི་ ནི་ གྲུབ་པ འོ ། །"
  },
  {
    "source": "འཕགས་པ་མི་རྒོད་རྣམ་པར་འཇོམས་པ་ཞེས་བྱ་བའི་གཟུངས་རྫོགས་སོ།།",
    "target": "འཕགས་པ་ མི་རྒོད་ རྣམ་པ ར་ འཇོམས་པ་ ཞེས་ བྱ་བ འི་ གཟུངས་ རྫོགས་ སོ ། །"
  },
  {
    "source": "།།",
    "target": "། །"
  },
  {
    "source": "༈རྒྱ་གར་སྐད་དུ།",
    "target": "༈ རྒྱ་གར་ སྐད་ དུ །"
  },
  {
    "source": "ཨཱརྻ་སརྦ་ཨནྟ་ར་སཾ་གྲཱ་ས་དྷཱ་ར་ཎི་མནྟྲ།",
    "target": "ཨཱརྻ་ སརྦ་ ཨནྟ་ར་ སཾ་ གྲཱ་ས་ དྷཱ་ར་ ཎི་ མནྟྲ །"
  },
  {
    "source": "བོད་སྐད་དུ།",
    "target": "བོད་ སྐད་ དུ །"
  },
  {
    "source": "འཕགས་པ་བར་དུ་གཅོད་པ་ཐམས་ཅད་སེལ་བའི་གཟུངས་སྔགས་སངས་རྒྱས་དང་བྱང་ཆུབ་སེམས་དཔའ་ཐམས་ཅད་ལ་ཕྱག་འཚལ་ལོ།།",
    "target": "འཕགས་པ་ བར་ དུ་ གཅོད་པ་ ཐམས་ཅད་ སེལ་བ འི་ གཟུངས་སྔགས་ སངས་རྒྱས་ དང་ བྱང་ཆུབ་སེམས་དཔའ་ ཐམས་ཅད་ ལ་ ཕྱག་ འཚལ་ ལོ ། །"
  },
  {
    "source": "བཅོམ་ལྡན་འདས་ཀྱིས་བྱང་ཆུབ་སེམས་དཔའ་སེམས་དཔའ་ཆེན་པོ་ཕྱག་ན་རྡོ་རྗེ་ལ་བཀའ་སྩལ་པ།",
    "target": "བཅོམ་ལྡན་འདས་ ཀྱིས་ བྱང་ཆུབ་སེམས་དཔའ་ སེམས་དཔའ་ ཆེན་པོ་ ཕྱག་ ན་ རྡོ་རྗེ་ ལ་ བཀའ་ སྩལ་པ །"
  },
  {
    "source": "ཕྱག་ན་རྡོ་རྗེ་གཟུངས་སྔགས་འདི་སུས་འཛིན་པ་དང་།",
    "target": "ཕྱག་ ན་ རྡོ་རྗེ་ གཟུངས་ སྔགས་ འདི་ སུ ས་ འཛིན་པ་ དང་ །"
  },
  {
    "source": "འཆང་བ་དང་།",
    "target": "འཆང་བ་ དང་ །"
  },
  {
    "source": "བཟླས་བརྗོད་བྱེད་པ་དེ་ལ་ནི་དུག་དང་།",
    "target": "བཟླས་བརྗོད་ བྱེད་པ་ དེ་ ལ་ ནི་ དུག་ དང་ །"
  },
  {
    "source": "མཚོན་གྱིས་འཆི་བ་དང་།",
    "target": "མཚོན་ གྱིས་ འཆི་བ་ དང་ །"
  },
  {
    "source": "ལྟོགས་པ་དང་།",
    "target": "ལྟོགས་པ་ དང་ །"
  },
  {
    "source": "མཚོན་བརྒྱབ་པ་དང་།",
    "target": "མཚོན་ བརྒྱབ་ པ་ དང་ །"
  },
  {
    "source": "གཅན་གཟན་མ་རུངས་པས་ཟ་བ་དང་།",
    "target": "གཅན་གཟན་ མ་ རུངས་པ ས་ ཟ་བ་ དང་ །"
  },
  {
    "source": "མེས་འཚིག་པ་དང་།",
    "target": "མེ ས་ འཚིག་པ་ དང་ །"
  },
  {
    "source": "ཆུར་འཆི་བ་དང་།",
    "target": "ཆུ ར་ འཆི་བ་ དང་ །"
  },
  {
    "source": "འགོ་བའི་རིམས་གཞན་ཡ་ང་བ་དང་།",
    "target": "འགོ་བ འི་ རིམས་ གཞན་ ཡ་ང་བ་ དང་ །"
  },
  {
    "source": "མཛེའི་ནད་དང་།",
    "target": "མཛེ འི་ ནད་ དང་ །"
  },
  {
    "source": "གསོར་མི་རུང་བའི་ནད་ཡ་ང་བ་དང་།",
    "target": "གསོར་ མི་ རུང་བ འི་ ནད་ ཡ་ང་བ་ དང་ །"
  },
  {
    "source": "གཡང་ལ་ལྷུང་བ་དང་།",
    "target": "གཡང་ ལ་ ལྷུང་བ་ དང་ །"
  },
  {
    "source": "གཞན་གྱི་བྱད་དང་།",
    "target": "གཞན་ གྱི་ བྱད་ དང་ །"
  },
  {
    "source": "ཟས་ཀྱིས་བརྣངས་པ་དང་།",
    "target": "ཟས་ ཀྱིས་ བརྣངས་པ་ དང་ །"
  },
  {
    "source": "བདག་རང་གིས་གསོད་པ་དང་།",
    "target": "བདག་ རང་ གིས་ གསོད་པ་ དང་ །"
  },
  {
    "source": "དེ་ལྟར་གཤིས་ངན་དུ་འཆི་བ་བཅུ་གསུམ་གྱིས་རྐྱེན་བྱེད་པར་མི་འགྱུར་རོ།།",
    "target": "དེ་ ལྟ ར་ གཤིས་ ངན་ དུ་ འཆི་བ་ བཅུ་ གསུམ་ གྱིས་ རྐྱེན་ བྱེད་པ ར་ མི་ འགྱུར་ རོ ། །"
  },
  {
    "source": "ཕྱག་ན་རྡོ་རྗེ་གཟུངས་སྔགས་འདི་སུས་འཛིན་པ་དང་།",
    "target": "ཕྱག་ ན་ རྡོ་རྗེ་ གཟུངས་ སྔགས་ འདི་ སུ ས་ འཛིན་པ་ དང་ །"
  },
  {
    "source": "འཆང་བ་དང་།",
    "target": "འཆང་བ་ དང་ །"
  },
  {
    "source": "བཟླས་བརྗོད་བྱེད་པ་དེ་ལ་ནི་ས་དང་ནམ་མཁའ་ལ་གནས་པའི་གེགས་དྲེགས་པ་ཅན་མ་རུངས་པ་རྣམས་ཀྱིས་ཀྱང་གླགས་རྙེད་པར་མི་འགྱུར་རོ།།",
    "target": "བཟླས་བརྗོད་ བྱེད་པ་ དེ་ ལ་ ནི་ ས་ དང་ ནམ་མཁའ་ ལ་ གནས་པ འི་ གེགས་ དྲེགས་པ་ ཅན་ མ་ རུངས་པ་ རྣམས་ ཀྱིས་ ཀྱང་ གླགས་ རྙེད་པ ར་ མི་ འགྱུར་ རོ ། །"
  },
  {
    "source": "ཕྱག་ན་རྡོ་རྗེ་གཟུངས་སྔགས་འདི་སུས་འཛིན་པ་དང་།",
    "target": "ཕྱག་ ན་ རྡོ་རྗེ་ གཟུངས་ སྔགས་ འདི་ སུ ས་ འཛིན་པ་ དང་ །"
  },
  {
    "source": "འཆང་བ་དང་།",
    "target": "འཆང་བ་ དང་ །"
  },
  {
    "source": "བཟླས་བརྗོད་བྱེད་པ་དེ་ལ་ལས་ཀྱི་སྒྲིབ་པ་དང་།",
    "target": "བཟླས་བརྗོད་ བྱེད་པ་ དེ་ ལ་ ལས་ ཀྱི་ སྒྲིབ་པ་ དང་ །"
  },
  {
    "source": "ཉོན་མོངས་པའི་སྒྲིབ་པ་དང་།",
    "target": "ཉོན་ མོངས་པ འི་ སྒྲིབ་པ་ དང་ །"
  },
  {
    "source": "ཤེས་བྱའི་སྒྲིབ་པ་ཐམས་ཅད་བྱང་ཞིང་དག་སྟེ།",
    "target": "ཤེས་བྱ འི་ སྒྲིབ་པ་ ཐམས་ཅད་ བྱང་ ཞིང་ དག་ སྟེ །"
  },
  {
    "source": "བདེ་བ་ཅན་གྱི་འཇིག་རྟེན་དུ་སྐྱེ་བར་འགྱུར་རོ།།",
    "target": "བདེ་བ་ཅན་ གྱི་ འཇིག་རྟེན་ དུ་ སྐྱེ་བ ར་ འགྱུར་ རོ ། །"
  },
  {
    "source": "ཨོཾ་བཛྲ་ཙནྜ་མ་ཧཱ་རོ་ཥ་ན་ཧཱུཾ་ཕཊ།",
    "target": "ཨོཾ་ བཛྲ་ ཙནྜ་ མ་ ཧཱ་ རོ་ ཥ་ ན་ ཧཱུཾ་ ཕཊ །"
  },
  {
    "source": "ཨ་པྲ་ཏི་ཧ་ཏ་བ་ལ་ཧཱུཾ་ཕཊ།",
    "target": "ཨ་པྲ་ ཏི་ ཧ་ ཏ་བ་ ལ་ ཧཱུཾ་ ཕཊ །"
  },
  {
    "source": "སརྦ་བིགྷྣཾ་ཨནྟ་ར་ཡ་བི་ནཱ་ཤ་ཀ་ར་མཱ་ར་ཡ་ཧཱུཾ་ཕཊ།",
    "target": "སརྦ་ བིགྷྣཾ་ ཨནྟ་ར་ ཡ་ བི་ནཱ་ཤ་ ཀ་ར་ མཱ་ར་ཡ་ ཧཱུཾ་ ཕཊ །"
  },
  {
    "source": "ཅེས་བརྒྱ་རྩ་བརྗོད་ན་འགྲུབ་བོ།།",
    "target": "ཅེས་ བརྒྱ་ རྩ་ བརྗོད་ ན་ འགྲུབ་ བོ ། །"
  },
  {
    "source": "ངེས་པར་འགྲུབ་བོ་ཞེས་གསུངས་སོ།།",
    "target": "ངེས་པ ར་ འགྲུབ་བོ་ ཞེས་ གསུངས་ སོ ། །"
  },
  {
    "source": "འཕགས་པ་བར་དུ་གཅོད་པ་ཐམས་ཅད་སེལ་བའི་གཟུངས་སྔགས་རྫོགས་སོ།།",
    "target": "འཕགས་པ་ བར་ དུ་ གཅོད་པ་ ཐམས་ཅད་ སེལ་བ འི་ གཟུངས་ སྔགས་ རྫོགས་ སོ ། །"
  },
  {
    "source": "།།",
    "target": "། །"
  },
  {
    "source": "༄༅།།",
    "target": "༄༅ ། །"
  },
  {
    "source": "འཕགས་པ་སྤྱན་རས་གཟིགས་དབང་ཕྱུག་གི་གཟུངས་ཞེས་བྱ་བ་བཞུགས།",
    "target": "འཕགས་པ་ སྤྱན་རས་གཟིགས་ དབང་ཕྱུག་ གི་ གཟུངས་ ཞེས་ བྱ་བ་ བཞུགས །"
  },
  {
    "source": "༄༅།།",
    "target": "༄༅ ། །"
  },
  {
    "source": "རྒྱ་གར་སྐད་དུ།",
    "target": "རྒྱ་གར་ སྐད་ དུ །"
  },
  {
    "source": "ཨཱརྻ་ཨ་བ་ལོ་ཀི་ཏེ་ཤྭ་ར་ནཱ་མ་དྷ་ར་ཎི།",
    "target": "ཨཱརྻ་ ཨ་བ་ ལོ་ ཀི་ ཏེ་ ཤྭ་ ར་ ནཱ་མ་ དྷ་ར་ཎི །"
  },
  {
    "source": "བོད་སྐད་དུ།",
    "target": "བོད་ སྐད་ དུ །"
  },
  {
    "source": "འཕགས་པ་སྤྱན་རས་གཟིགས་དབང་ཕྱུག་གི་གཟུངས་ཞེས་བྱ་བ།",
    "target": "འཕགས་པ་ སྤྱན་རས་གཟིགས་ དབང་ཕྱུག་ གི་ གཟུངས་ ཞེས་ བྱ་བ །"
  },
  {
    "source": "འཕགས་པ་སྤྱན་རས་གཟིགས་ཐུགས་རྗེ་ཆེན་པོ་དང་ལྡན་པ་ལ་ཕྱག་འཚལ་ལོ།།",
    "target": "འཕགས་པ་ སྤྱན་རས་གཟིགས་ ཐུགས་རྗེ་ ཆེན་པོ་ དང་ ལྡན་པ་ ལ་ ཕྱག་ འཚལ་ ལོ ། །"
  },
  {
    "source": "འཕགས་པ་སྤྱན་རས་གཟགས་དབང་ཕྱུག་བྱམས་པའི་ངང་ལས་སྙིང་རྗེའི་ཤུགས་ཀྱིས་བྱང་ཆུབ་ཀྱི་སེམས་རབ་ཏུ་བསྐྱེད་ནས།",
    "target": "འཕགས་པ་ སྤྱན་ རས་ གཟགས་ དབང་ཕྱུག་ བྱམས་པ འི་ ངང་ ལས་ སྙིང་རྗེ འི་ ཤུགས་ ཀྱིས་ བྱང་ཆུབ་ ཀྱི་ སེམས་ རབ་ ཏུ་ བསྐྱེད་ ནས །"
  },
  {
    "source": "པདྨ་དང་ཉི་མ་དང་ཟླ་བའི་གདན་ལ་ཧྲཱིའི་འཕྲོ་འདུ་ལས་ཞལ་གཅིག་པ་ལ་ཕྱག་བཞི་པ།",
    "target": "པདྨ་ དང་ ཉི་མ་ དང་ ཟླ་བ འི་ གདན་ ལ་ ཧྲཱི འི་ འཕྲོ་ འདུ་ ལས་ ཞལ་ གཅིག་པ་ ལ་ ཕྱག་ བཞི་པ །"
  },
  {
    "source": "དང་པོ་གཉིས་ཐལ་མོ་སྦྱར་བ།",
    "target": "དང་པོ་ གཉིས་ ཐལ་མོ་ སྦྱར་ བ །"
  },
  {
    "source": "གཡས་འོག་མ་ན་བགྲང་ཕྲེང་མུ་ཏིག་དཀར་པོ།",
    "target": "གཡས་ འོག་མ་ ན་ བགྲང་ཕྲེང་ མུ་ཏིག་ དཀར་པོ །"
  },
  {
    "source": "གཡོན་འོག་མ་ན་པདྨ་དཀར་པོ་བསྣམས་པ།",
    "target": "གཡོན་ འོག་མ་ ན་ པདྨ་ དཀར་པོ་ བསྣམས་པ །"
  },
  {
    "source": "སྐུ་མདོག་དཀར་པོ་ཞབས་རྫོགས་པའི་སྐྱིལ་ཀྲུང་བཅས་པ།",
    "target": "སྐུ་མདོག་ དཀར་པོ་ ཞབས་ རྫོགས་པ འི་ སྐྱིལ་ཀྲུང་ བཅས་པ །"
  },
  {
    "source": "རིན་པོ་ཆེའི་རྒྱན་སྣ་ཚོགས་དང་།",
    "target": "རིན་པོ་ཆེ འི་ རྒྱན་ སྣ་ཚོགས་ དང་ །"
  },
  {
    "source": "རིན་པོ་ཆེའི་དབུ་རྒྱན་གྱིས་མཛེས་པ།",
    "target": "རིན་པོ་ཆེ འི་ དབུ་རྒྱན་ གྱིས་ མཛེས་པ །"
  },
  {
    "source": "ཡུམ་ལྷ་མོ་དྲུག་མ་དང་།",
    "target": "ཡུམ་ ལྷ་མོ་ དྲུག་ མ་ དང་ །"
  },
  {
    "source": "ཡབ་ནོར་བུ་རིན་པོ་ཆེས་བརྟེན་པ།",
    "target": "ཡབ་ ནོར་བུ་ རིན་པོ་ཆེ ས་ བརྟེན་པ །"
  },
  {
    "source": "བྱང་ཆུབ་སེམས་དཔའ་དང་།",
    "target": "བྱང་ཆུབ་སེམས་དཔའ་ དང་ །"
  },
  {
    "source": "སེམས་མ་རབ་ཏུ་མང་པོས་བསྐོར་ཏེ་འདི་སྐད་ཅེས་གསུངས་སོ།།",
    "target": "སེམས་ མ་ རབ་ ཏུ་ མང་པོ ས་ བསྐོར་ ཏེ་ འདི་ སྐད་ ཅེས་ གསུངས་ སོ ། །"
  },
  {
    "source": "རིགས་ཀྱི་བུའམ།",
    "target": "རིགས་ ཀྱི་ བུ འམ །"
  },
  {
    "source": "རིགས་ཀྱི་བུ་མོ་སྔགས་འདི་ལན་གཅིག་ཙམ་བརྗོད་དམ་དྲན་ཞིང་ཡིད་ལ་བྱས་སམ།",
    "target": "རིགས་ ཀྱི་ བུ་མོ་ སྔགས་ འདི་ ལན་ གཅིག་ ཙམ་ བརྗོད་ དམ་ དྲན་ ཞིང་ ཡིད་ ལ་ བྱས་ སམ །"
  },
  {
    "source": "བྲིས་ནས་ལུས་ལ་བཅངས་སམ།",
    "target": "བྲིས་ ནས་ ལུས་ ལ་ བཅངས་ སམ །"
  },
  {
    "source": "མོས་ཤིང་གུས་པར་བྱས་ན་མཚམས་མེད་པ་ལྔ་དང་དེ་དང་ཉེ་བའི་སྡིག་པའི་ལས་ཐམས་ཅད་བྱང་ཞིང་།",
    "target": "མོས་ ཤིང་ གུས་པ ར་ བྱས་ ན་ མཚམས་ མེད་པ་ ལྔ་ དང་ དེ་ དང་ ཉེ་བ འི་ སྡིག་པ འི་ ལས་ ཐམས་ཅད་ བྱང་ ཞིང་ །"
  },
  {
    "source": "ངན་སོང་གསུམ་དང་།",
    "target": "ངན་སོང་ གསུམ་ དང་ །"
  },
  {
    "source": "མི་ཁོམ་པ་བརྒྱད་དང་།",
    "target": "མི་ཁོམ་པ་ བརྒྱད་ དང་ །"
  },
  {
    "source": "སྡུག་བསྔལ་དང་བཅས་པར་མི་སྐྱེའོ།།",
    "target": "སྡུག་བསྔལ་ དང་ བཅས་པ ར་ མི་ སྐྱེ འོ ། །"
  },
  {
    "source": "མི་དང་མི་མ་ཡིན་པ་དང་།",
    "target": "མི་ དང་ མི་ མ་ ཡིན་པ་ དང་ །"
  },
  {
    "source": "གཅན་གཟན་གྱི་འཇིགས་པ་ཐམས་ཅད་ལས་གྲོལ་བར་གྱུར་རོ།།",
    "target": "གཅན་གཟན་ གྱི་ འཇིགས་པ་ ཐམས་ཅད་ ལས་ གྲོལ་བ ར་ གྱུར་ རོ ། །"
  },
  {
    "source": "ནད་དང་གདོན་ཐམས་ཅད་ལས་ཐར་བར་འགྱུར་རོ།།",
    "target": "ནད་ དང་ གདོན་ ཐམས་ཅད་ ལས་ ཐར་བ ར་ འགྱུར་ རོ ། །"
  },
  {
    "source": "ཨོཾ་མ་ཎི་པདྨེ་ཧཱུཾ།",
    "target": "ཨོཾ་ མ་ ཎི་ པདྨེ་ ཧཱུཾ །"
  },
  {
    "source": "ཞེས་བརྗོད་པས་འཕགས་པ་སྤྱན་རས་གཟིགས་ཀྱི་ཞལ་མཐོང་བར་འགྱུར་ཞིང་།",
    "target": "ཞེས་ བརྗོད་པ ས་ འཕགས་པ་ སྤྱན་རས་གཟིགས་ ཀྱི་ ཞལ་ མཐོང་བ ར་ འགྱུར་ ཞིང་ །"
  },
  {
    "source": "ཚེ་འཕོས་ནས་ཀྱང་བདེ་བ་ཅན་དུ་སྐྱེ་སྟེ་འདི་ལ་ཐེ་ཚོམ་མམ།",
    "target": "ཚེ་ འཕོས་ ནས་ ཀྱང་ བདེ་བ་ཅན་ དུ་ སྐྱེ་ སྟེ་ འདི་ ལ་ ཐེ་ཚོམ་ མམ །"
  },
  {
    "source": "སོམ་ཉིའམ།",
    "target": "སོམ་ཉི འམ །"
  },
  {
    "source": "ཡིད་གཉིས་མ་ཟ་ཞིག།",
    "target": "ཡིད་ གཉིས་ མ་ ཟ་ ཞིག །"
  },
  {
    "source": "འཕགས་པ་སྤྱན་རས་གཟིགས་དབང་ཕྱུག་གི་གཟུངས་རྫོགས་སོ།།",
    "target": "འཕགས་པ་ སྤྱན་རས་གཟིགས་ དབང་ཕྱུག་ གི་ གཟུངས་ རྫོགས་ སོ ། །"
  },
  {
    "source": "།།",
    "target": "། །"
  },
  {
    "source": "༈སངས་རྒྱས་ལ་ཕྱག་འཚལ་ལོ།།",
    "target": "༈ སངས་རྒྱས་ ལ་ ཕྱག་ འཚལ་ ལོ ། །"
  },
  {
    "source": "ཆོས་ལ་ཕྱག་འཚལ་ལོ།།",
    "target": "ཆོས་ ལ་ ཕྱག་ འཚལ་ ལོ ། །"
  },
  {
    "source": "དགེ་འདུན་ལ་ཕྱག་འཚལ་ལོ།།",
    "target": "དགེ་འདུན་ ལ་ ཕྱག་ འཚལ་ ལོ ། །"
  },
  {
    "source": "འཕགས་པ་སྤྱན་རས་གཟིགས་ཀྱི་དབང་པོ་བྱང་ཆུབ་སེམས་དཔའ་སེམས་དཔའ་ཆེན་པོ་ལ་ཕྱག་འཚལ་ལོ།།",
    "target": "འཕགས་པ་ སྤྱན་རས་གཟིགས་ ཀྱི་ དབང་པོ་ བྱང་ཆུབ་སེམས་དཔའ་ སེམས་དཔའ་ ཆེན་པོ་ ལ་ ཕྱག་ འཚལ་ ལོ ། །"
  },
  {
    "source": "དེ་རྣམས་ལ་ཕྱག་འཚལ་ནས་རིག་པ་འདི་བརྗོད་ཀྱིས་རིག་པ་འདི་དག་གྲུབ་པར་འགྱུར་ཅིག།",
    "target": "དེ་ རྣམས་ ལ་ ཕྱག་ འཚལ་ ནས་ རིག་པ་ འདི་ བརྗོད་ ཀྱིས་ རིག་པ་ འདི་ དག་ གྲུབ་པ ར་ འགྱུར་ ཅིག །"
  },
  {
    "source": "ཏདྱ་ཐཱ།",
    "target": "ཏདྱ་ཐཱ །"
  },
  {
    "source": "ཧ་ཧ་ཧ་ས་ནེ།",
    "target": "ཧ་ཧ་ ཧ་ས་ ནེ །"
  },
  {
    "source": "ནི་བ་ས་ནི།",
    "target": "ནི་བ་ ས་ ནི །"
  },
  {
    "source": "ཏ་བ་ཏ་བ་ནེ།",
    "target": "ཏ་བ་ ཏ་བ་ ནེ །"
  },
  {
    "source": "ཛྭ་ལ་ཛྭ་ལ་ནེ།",
    "target": "ཛྭ་ ལ་ ཛྭ་ ལ་ ནེ །"
  },
  {
    "source": "ཙལ་ཙལ་ནེ།",
    "target": "ཙལ་ ཙལ་ ནེ །"
  },
  {
    "source": "པུརྦ་ཡོག་སྨྲ་པདྨ་ཧསྟཱ་ཡ་སྭཱ་ཧཱ།",
    "target": "པུརྦ་ ཡོག་ སྨྲ་ པདྨ་ ཧསྟཱ་ ཡ་ སྭཱ་ཧཱ །"
  },
  {
    "source": "གང་གིས་རིག་པ་འདི་བཀླགས་པ་དེས་ཚེ་རབས་བརྒྱ་སྟོང་སྐྱེ་བ་དྲན་པར་གྱུར་ཏེ།",
    "target": "གང་ གིས་ རིག་པ་ འདི་ བཀླགས་པ་ དེ ས་ ཚེ་རབས་ བརྒྱ་ སྟོང་ སྐྱེ་བ་ དྲན་པ ར་ གྱུར་ ཏེ །"
  },
  {
    "source": "འདི་ནས་ཤི་འཕོས་ནས་ཀྱང་བདེ་བ་ཅན་གྱི་འཇིག་རྟེན་དུ་སྐྱེ་བར་འགྱུར་རོ།།",
    "target": "འདི་ ནས་ ཤི་ འཕོས་ ནས་ ཀྱང་ བདེ་བ་ཅན་ གྱི་ འཇིག་རྟེན་ དུ་ སྐྱེ་བ ར་ འགྱུར་ རོ ། །"
  },
  {
    "source": "འཕགས་པ་སྤྱན་རས་གཟིགས་ཀྱི་སྙིང་པོ་རྫོགས་སོ།།",
    "target": "འཕགས་པ་ སྤྱན་རས་གཟིགས་ ཀྱི་ སྙིང་པོ་ རྫོགས་ སོ ། །"
  },
  {
    "source": "།།",
    "target": "། །"
  },
  {
    "source": "༈ན་མོ་རཏྣ་ཏྲ་ཡཱ་ཡ།",
    "target": "༈ ན་མོ་ རཏྣ་ ཏྲ་ ཡཱ་ ཡ །"
  },
  {
    "source": "ན་མ་ཨཱརྻ་ཨ་བ་ལོ་ཀི་ཤྭ་རཱ་ཡ།",
    "target": "ན་ མ་ ཨཱརྻ་ ཨ་བ་ ལོ་ ཀི་ ཤྭ་ རཱ་ ཡ །"
  },
  {
    "source": "བོ་དྷི་ས་ཏྭ་ཡ།",
    "target": "བོ་དྷི་ས་ཏྭ་ ཡ །"
  },
  {
    "source": "མ་ཧཱ་ས་ཏྭ་ཡ།",
    "target": "མ་ཧཱ་ ས་ ཏྭ་ ཡ །"
  },
  {
    "source": "མ་ཧཱ་ཀཱ་རུ་ཎི་ཀ་ཡ།",
    "target": "མ་ཧཱ་ ཀཱ་རུ་ ཎི་ ཀ་ ཡ །"
  },
  {
    "source": "ཏདྱ་ཐཱ།",
    "target": "ཏདྱ་ཐཱ །"
  },
  {
    "source": "ཨོཾ་ཨ་ཀ་ཊེ།",
    "target": "ཨོཾ་ ཨ་ཀ་ ཊེ །"
  },
  {
    "source": "བི་ཀ་ཊེ།",
    "target": "བི་ཀ་ ཊེ །"
  },
  {
    "source": "ནི་ཀ་ཊེ།",
    "target": "ནི་ ཀ་ ཊེ །"
  },
  {
    "source": "ཀ་ཊཾ་ཀ་ཊཾ།",
    "target": "ཀ་ ཊཾ་ ཀ་ ཊཾ །"
  },
  {
    "source": "ཀ་རོ་ཊེ།",
    "target": "ཀ་ རོ་ ཊེ །"
  },
  {
    "source": "ཀ་རོ་ཊེ།",
    "target": "ཀ་ རོ་ ཊེ །"
  },
  {
    "source": "བཱི་རྻེ་སྭཱ་ཧཱ།",
    "target": "བཱི་ རྻེ་ སྭཱ་ཧཱ །"
  },
  {
    "source": "བཅོམ་ལྡན་འདས་དེའི་སྤྱན་སྔར་བའི་ལྕི་བ་ས་ལ་མ་ལྷུང་བས་སོ་སོར་མཎྜལ་བརྒྱད་བྱས་ལ།",
    "target": "བཅོམ་ལྡན་འདས་ དེ འི་ སྤྱན་སྔ ར་ བ འི་ ལྕི་བ་ ས་ ལ་ མ་ ལྷུང་བ ས་ སོ་སོ ར་ མཎྜལ་ བརྒྱད་ བྱས་ ལ །"
  },
  {
    "source": "མཎྜལ་རེ་རེ་ལ་ལན་བཅུ་གསུམ་གྱི་བར་དུ་བཟླས་ལ།",
    "target": "མཎྜལ་ རེ་རེ་ ལ་ ལན་ བཅུ་ གསུམ་ གྱི་ བར་ དུ་ བཟླས་ ལ །"
  },
  {
    "source": "ལྕི་བ་ལྷག་མ་ལ་སྔགས་བཟླས་ཏེ།",
    "target": "ལྕི་བ་ ལྷག་མ་ ལ་ སྔགས་ བཟླས་ ཏེ །"
  },
  {
    "source": "ནད་པ་ལ་ཉེ་བར་བྱུགས་ན་ནད་ཐམས་ཅད་ཞི་བར་འགྱུར་རོ།།",
    "target": "ནད་པ་ ལ་ ཉེ་བ ར་ བྱུགས་ ན་ ནད་ ཐམས་ཅད་ ཞི་བ ར་ འགྱུར་ རོ ། །"
  },
  {
    "source": "གལ་ཏེ་ཉི་མ་བདུན་ནམ།",
    "target": "གལ་ ཏེ་ ཉི་མ་ བདུན་ ནམ །"
  },
  {
    "source": "བཅུ་གསུམ་མམ་ཉི་ཤུ་རྩ་གཅིག་གིས་འགྲུབ་སྟེ།",
    "target": "བཅུ་གསུམ་ མམ་ ཉི་ཤུ་ རྩ་ གཅིག་ གིས་ འགྲུབ་ སྟེ །"
  },
  {
    "source": "མཚམས་མེད་པ་ལྔ་བྱས་པས་ནི་མ་ཡིན་ནོ།།",
    "target": "མཚམས་ མེད་པ་ ལྔ་ བྱས་པ ས་ ནི་ མ་ ཡིན་ ནོ ། །"
  },
  {
    "source": "དེ་ལྟར་མ་གྲུབ་ན་བདག་གིས་མཚམས་མེད་ལྔ་བྱས་པར་འགྱུར་རོ།།",
    "target": "དེ་ ལྟ ར་ མ་ གྲུབ་ ན་ བདག་ གིས་ མཚམས་ མེད་ ལྔ་ བྱས་པ ར་ འགྱུར་ རོ ། །"
  },
  {
    "source": "སེང་གེ་སྒྲའི་གཟུངས་རྫོགས་སོ།།",
    "target": "སེང་གེ་ སྒྲ འི་ གཟུངས་ རྫོགས་ སོ ། །"
  },
  {
    "source": "།།",
    "target": "། །"
  },
  {
    "source": "རྒྱ་གར་གྱི་མཁན་པོ་ངག་གི་དབང་ཕྱུག་དང་།།",
    "target": "རྒྱ་གར་ གྱི་ མཁན་པོ་ ངག་ གི་ དབང་ཕྱུག་ དང་ ། །"
  },
  {
    "source": "གློག་སྐྱ་ཤེས་རབ་བརྩེགས་ཀྱིས་བསྒྱུར་བའོ།།",
    "target": "གློག་ སྐྱ་ ཤེས་རབ་ བརྩེགས་ ཀྱིས་ བསྒྱུར་བ འོ ། །"
  },
  {
    "source": "།།",
    "target": "། །"
  },
  {
    "source": "༈འཕགས་པ་དོན་ཡོད་ཞགས་པའི་སྙིང་པོ་ཞེས་བྱ་བའི་གཟུངས་བཞུགས།",
    "target": "༈ འཕགས་པ་ དོན་ཡོད་ཞགས་པ འི་ སྙིང་པོ་ ཞེས་ བྱ་བ འི་ གཟུངས་ བཞུགས །"
  },
  {
    "source": "འཕགས་པ་དོན་ཡོད་ཞགས་པའི་སྙིང་པོ་ཞེས་བྱ་བའི་གཟུངས།",
    "target": "འཕགས་པ་ དོན་ཡོད་ཞགས་པ འི་ སྙིང་པོ་ ཞེས་ བྱ་བ འི་ གཟུངས །"
  },
  {
    "source": "སངས་རྒྱས་དང་བྱང་ཆུབ་སེམས་དཔའ་དུས་གསུམ་དུ་གཤེགས་ཤིང་བཞུགས་པ་ཐམས་ཅད་ལ་ཕྱག་འཚལ་ལོ།",
    "target": "སངས་རྒྱས་ དང་ བྱང་ཆུབ་སེམས་དཔའ་ དུས་ གསུམ་ དུ་ གཤེགས་ ཤིང་ བཞུགས་པ་ ཐམས་ཅད་ ལ་ ཕྱག་ འཚལ་ ལོ །"
  },
  {
    "source": "འདས་པ་དང་།",
    "target": "འདས་པ་ དང་ །"
  },
  {
    "source": "མ་བྱོན་པ་དང་།",
    "target": "མ་ བྱོན་པ་ དང་ །"
  },
  {
    "source": "ད་ལྟ་བྱུང་བའི་སངས་རྒྱས་དང་།",
    "target": "ད་ ལྟ་ བྱུང་བ འི་ སངས་རྒྱས་ དང་ །"
  },
  {
    "source": "འཕགས་པ་ཉན་ཐོས་ཀྱི་དགེ་འདུན་རྣམས་ལ་ཕྱག་འཚལ་ལོ།།",
    "target": "འཕགས་པ་ ཉན་ཐོས་ ཀྱི་ དགེ་འདུན་ རྣམས་ ལ་ ཕྱག་ འཚལ་ ལོ ། །"
  },
  {
    "source": "ཡང་དག་པར་སོང་བ་རྣམས་དང་།",
    "target": "ཡང་ དག་པ ར་ སོང་བ་ རྣམས་ དང་ །"
  },
  {
    "source": "ཡང་དག་པར་ཞུགས་པ་རྣམས་ལ་ཕྱག་འཚལ་ལོ།།",
    "target": "ཡང་ དག་པ ར་ ཞུགས་པ་ རྣམས་ ལ་ ཕྱག་ འཚལ་ ལོ ། །"
  },
  {
    "source": "གནས་བརྟན་བློ་གྲོས་ཆེན་པོ་ཤྭ་ར་དྭ་ཏིའི་བུ་ལ་ཕྱག་འཚལ་ལོ།།",
    "target": "གནས་བརྟན་ བློ་གྲོས་ ཆེན་པོ་ ཤྭ་ ར་ དྭ་ ཏི འི་ བུ་ ལ་ ཕྱག་ འཚལ་ ལོ ། །"
  },
  {
    "source": "འཕགས་པ་བྱམས་པ་ལ་སོགས་པ་བྱང་ཆུབ་སེམས་དཔའ་རྣམས་ལ་ཕྱག་འཚལ་ལོ།།",
    "target": "འཕགས་པ་ བྱམས་པ་ ལ་ སོགས་པ་ བྱང་ཆུབ་སེམས་དཔའ་ རྣམས་ ལ་ ཕྱག་ འཚལ་ ལོ ། །"
  },
  {
    "source": "དེ་བཞིན་གཤེགས་པ་དགྲ་བཅོམ་པ་ཡང་དག་པར་རྫོགས་པའི་སངས་རྒྱས་ཚེ་དཔག་མེད་ལ་ཕྱག་འཚལ་ལོ།།",
    "target": "དེ་བཞིན་གཤེགས་པ་ དགྲ་བཅོམ་པ་ ཡང་ དག་པ ར་ རྫོགས་པ འི་ སངས་རྒྱས་ ཚེ་ དཔག་མེད་ ལ་ ཕྱག་ འཚལ་ ལོ ། །"
  },
  {
    "source": "དཀོན་མཆོག་སུམ་ལ་ཕྱག་འཚལ་ལོ།",
    "target": "དཀོན་མཆོག་ སུམ་ ལ་ ཕྱག་ འཚལ་ ལོ །"
  },
  {
    "source": "བྱང་ཆུབ་སེམས་དཔའ་སེམས་དཔའ་ཆེན་པོ་འཕགས་པ་སྤྱན་རས་གཟིགས་དབང་ཕྱུག་ཐུགས་རྗེ་ཆེན་པོ་དང་ལྡན་པ་ལ་ཕྱག་འཚལ་ལོ།།",
    "target": "བྱང་ཆུབ་སེམས་དཔའ་ སེམས་དཔའ་ ཆེན་པོ་ འཕགས་པ་ སྤྱན་རས་གཟིགས་ དབང་ཕྱུག་ ཐུགས་རྗེ་ ཆེན་པོ་ དང་ ལྡན་པ་ ལ་ ཕྱག་ འཚལ་ ལོ ། །"
  },
  {
    "source": "དེ་རྣམས་ལ་ཕྱག་འཚལ་ནས།",
    "target": "དེ་ རྣམས་ ལ་ ཕྱག་ འཚལ་ ནས །"
  },
  {
    "source": "འཕགས་པ་སྤྱན་རས་གཟིགས་དབང་ཕྱུག་གིས།",
    "target": "འཕགས་པ་ སྤྱན་རས་གཟིགས་ དབང་ཕྱུག་ གིས །"
  },
  {
    "source": "དེ་བཞིན་གཤེགས་པའི་སྤྱན་སྔར་འཁོར་མང་པོའི་དབུས་སུ་སྨྲས་པ།",
    "target": "དེ་བཞིན་གཤེགས་པ འི་ སྤྱན་སྔ ར་ འཁོར་ མང་པོ འི་ དབུས་ སུ་ སྨྲས་པ །"
  },
  {
    "source": "དོན་ཡོད་ཞགས་པའི་སྙིང་པོ་དེ་བདག་གིས་བརྗོད་པར་བགྱིའོ།།",
    "target": "དོན་ཡོད་ཞགས་པ འི་ སྙིང་པོ་ དེ་ བདག་ གིས་ བརྗོད་པ ར་ བགྱི འོ ། །"
  },
  {
    "source": "བདག་གིས་སྔགས་ཚིག་དང་།",
    "target": "བདག་ གིས་ སྔགས་ ཚིག་ དང་ །"
  },
  {
    "source": "དགོས་པ་ཐམས་ཅད་འགྲུབ་པར་གྱུར་ཅིག།",
    "target": "དགོས་པ་ ཐམས་ཅད་ འགྲུབ་པ ར་ གྱུར་ ཅིག །"
  },
  {
    "source": "ཏདྱ་ཐཱ།",
    "target": "ཏདྱ་ཐཱ །"
  },
  {
    "source": "ཨོཾ་ཙ་ར་ཙ་ར།",
    "target": "ཨོཾ་ ཙ་ར་ ཙ་ར །"
  },
  {
    "source": "ཙི་རི་ཙི་རི།",
    "target": "ཙི་ རི་ ཙི་ རི །"
  },
  {
    "source": "ཙུ་རི་ཙུ་རུ།",
    "target": "ཙུ་ རི་ ཙུ་ རུ །"
  },
  {
    "source": "མ་ཧཱ་ཀཱ་རུ་ཎི་ཀ།",
    "target": "མ་ཧཱ་ ཀཱ་རུ་ ཎི་ ཀ །"
  },
  {
    "source": "ས་ར་ས་ར།",
    "target": "ས་ ར་ས་ ར །"
  },
  {
    "source": "སི་རི་སི་རི།",
    "target": "སི་ རི་ སི་ རི །"
  },
  {
    "source": "སུ་རུ་སུ་རུ།",
    "target": "སུ་ རུ་ སུ་ རུ །"
  },
  {
    "source": "ཙི་རི་ཙི་རི།",
    "target": "ཙི་ རི་ ཙི་ རི །"
  },
  {
    "source": "བི་རི་བི་རི།",
    "target": "བི་ རི་ བི་ རི །"
  },
  {
    "source": "མ་ཧཱ་པདྨ་ཧསྟཱ།",
    "target": "མ་ཧཱ་ པདྨ་ ཧསྟཱ །"
  },
  {
    "source": "ཀ་ལ་ཀ་ལ།",
    "target": "ཀ་ལ་ ཀ་ ལ །"
  },
  {
    "source": "ཀི་ལི་ཀི་ལི།",
    "target": "ཀི་ ལི་ ཀི་ ལི །"
  },
  {
    "source": "ཀུ་ལུ་ཀུ་ལུ།",
    "target": "ཀུ་ ལུ་ ཀུ་ ལུ །"
  },
  {
    "source": "མ་ཧཱ་ཤུདྡྷ་ས་ཏྭ།",
    "target": "མ་ཧཱ་ ཤུདྡྷ་ ས་ ཏྭ །"
  },
  {
    "source": "ཨེ་ཧྱ་ཧི།",
    "target": "ཨེ་ ཧྱ་ ཧི །"
  },
  {
    "source": "བུདྡྷ་བུདྡྷ།",
    "target": "བུདྡྷ་བུདྡྷ །"
  },
  {
    "source": "དྷ་བ་དྷ་བ།",
    "target": "དྷ་བ་ དྷ་བ །"
  },
  {
    "source": "བོ་དྷ་ཡ་བོ་དྷ་ཡ།",
    "target": "བོ་དྷ་ཡ་ བོ་དྷ་ཡ །"
  },
  {
    "source": "ཀ་ཎ་ཀ་ཎ།",
    "target": "ཀ་ཎ་ ཀ་ ཎ །"
  },
  {
    "source": "ཀི་ཎི་ཀི་ཎི།",
    "target": "ཀི་ ཎི་ ཀི་ ཎི །"
  },
  {
    "source": "ཀུ་ཎུ་ཀུ་ཎུ།",
    "target": "ཀུ་ ཎུ་ ཀུ་ ཎུ །"
  },
  {
    "source": "མ་ཧཱ་ཤུདྡྷ་སྭཱ་ཧཱ།",
    "target": "མ་ཧཱ་ ཤུདྡྷ་ སྭཱ་ཧཱ །"
  },
  {
    "source": "ཀ་ར་ཀ་ར།",
    "target": "ཀ་ར་ཀ་ར །"
  },
  {
    "source": "ཀི་རི་ཀི་རི།",
    "target": "ཀི་ རི་ ཀི་ རི །"
  },
  {
    "source": "ཀུ་རུ་ཀུ་རུ།",
    "target": "ཀུ་རུ་ ཀུ་རུ །"
  },
  {
    "source": "མ་ཧཱ་སྟམ་པྲ་བྷཱ་ཏེ།",
    "target": "མ་ཧཱ་ སྟམ་ པྲ་བྷཱ་ ཏེ །"
  },
  {
    "source": "ཙ་ལ་ཙ་ལ།",
    "target": "ཙ་ ལ་ ཙ་ ལ །"
  },
  {
    "source": "སན་ཙ་ལ་སན་ཙ་ལ།",
    "target": "སན་ ཙ་ལ་ སན་ ཙ་ ལ །"
  },
  {
    "source": "བི་ཙ་ལ་བི་ཙ་ལ།",
    "target": "བི་ ཙ་ལ་ བི་ ཙ་ ལ །"
  },
  {
    "source": "པྲ་ཙ་ལ་པྲ་ཙ་ལ།",
    "target": "པྲ་ ཙ་ལ་ པྲ་ ཙ་ ལ །"
  },
  {
    "source": "ཨེ་ཊ་ཊ་ཨེ་ཊ་ཊ།",
    "target": "ཨེ་ ཊ་ ཊ་ ཨེ་ ཊ་ ཊ །"
  },
  {
    "source": "བྷ་ར་བྷ་ར།",
    "target": "བྷ་ར་བྷ་ར །"
  },
  {
    "source": "བྷི་རི་བྷི་རི།",
    "target": "བྷི་ རི་ བྷི་ རི །"
  },
  {
    "source": "བྷུ་རུ་བྷུ་རུ།",
    "target": "བྷུ་ རུ་ བྷུ་ རུ །"
  },
  {
    "source": "ཨེ་ཧྱ་ཧི།",
    "target": "ཨེ་ ཧྱ་ ཧི །"
  },
  {
    "source": "མ་ཧཱ་ཀ་རུ་ཎི་ཀ།",
    "target": "མ་ཧཱ་ ཀ་རུ་ ཎི་ ཀ །"
  },
  {
    "source": "མ་ཧཱ་བ་ཤུ་བ་ཏི་བི་ཤ་དྷ་ར།",
    "target": "མ་ཧཱ་བ་ ཤུ་བ་ ཏི་ བི་ཤ་ དྷ་ར །"
  },
  {
    "source": "དྷ་ར་དྷ་ར།",
    "target": "དྷ་ར་ དྷ་ར །"
  },
  {
    "source": "སི་རི་སི་རི།",
    "target": "སི་ རི་ སི་ རི །"
  },
  {
    "source": "སུ་རུ་སུ་རུ།",
    "target": "སུ་ རུ་ སུ་ རུ །"
  },
  {
    "source": "ཙ་ར་ཙ་ར།",
    "target": "ཙ་ར་ ཙ་ར །"
  },
  {
    "source": "བྷ་ར་བྷ་ར།",
    "target": "བྷ་ར་བྷ་ར །"
  },
  {
    "source": "བྷ་ར་བྷ་ར།",
    "target": "བྷ་ར་བྷ་ར །"
  },
  {
    "source": "ཧ་ར་ཧ་ར།",
    "target": "ཧ་ར་ ཧ་ ར །"
  },
  {
    "source": "ཧ་ཧ་ཧི་ཧི་ཧུ་ཧུ།",
    "target": "ཧ་ཧ་ ཧི་ཧི་ ཧུ་ ཧུ །"
  },
  {
    "source": "ཨོཾ་ཀ་ར་ཀ་ར།",
    "target": "ཨོཾ་ ཀ་ར་ཀ་ར །"
  },
  {
    "source": "མ་ཧཱ་པྲ་ཝ་ཤ།",
    "target": "མ་ཧཱ་ པྲ་ ཝ་ ཤ །"
  },
  {
    "source": "དྷ་ར་དྷ་ར།",
    "target": "དྷ་ར་ དྷ་ར །"
  },
  {
    "source": "དྷི་རི་དྷི་རི།",
    "target": "དྷི་ རི་ དྷི་ རི །"
  },
  {
    "source": "དྷ་རུ་དྷ་རུ།",
    "target": "དྷ་རུ་ དྷ་རུ །"
  },
  {
    "source": "ཏ་ར་ཏ་ར།",
    "target": "ཏ་ར་ ཏ་ར །"
  },
  {
    "source": "ས་ར་ས་ར།",
    "target": "ས་ ར་ས་ ར །"
  },
  {
    "source": "ཙ་ར་ཙ་ར།",
    "target": "ཙ་ར་ ཙ་ར །"
  },
  {
    "source": "བ་ར་བ་ར།",
    "target": "བ་ར་བ་ ར །"
  },
  {
    "source": "ཤི་གྷ་ཤི་གྷ།",
    "target": "ཤི་ གྷ་ ཤི་ གྷ །"
  },
  {
    "source": "རཤྨི་ཤི་ཧ་ས་ཧ་སྲ།",
    "target": "རཤྨི་ ཤི་ ཧ་ས་ ཧ་ སྲ །"
  },
  {
    "source": "པྲ་ཏི་མུ་ན་ཏི་ཏ།",
    "target": "པྲ་ཏི་ མུ་ན་ ཏི་ ཏ །"
  },
  {
    "source": "ཤ་རི་ཤ་རི།",
    "target": "ཤ་རི་ ཤ་རི །"
  },
  {
    "source": "ཛྭ་ལ་ཛྭ་ལ།",
    "target": "ཛྭ་ ལ་ ཛྭ་ ལ །"
  },
  {
    "source": "ཏ་པ་ཏ་པ།",
    "target": "ཏ་པ་ ཏ་པ །"
  },
  {
    "source": "བྷ་ག་བ་ནི།",
    "target": "བྷ་ག་བ་ ནི །"
  },
  {
    "source": "སོ་མ་ཨ་དི་ཏྱ།",
    "target": "སོ་མ་ ཨ་དི་ ཏྱ །"
  },
  {
    "source": "ས་མ་བ་རུ་ན་ཀུ་བེ་ར།",
    "target": "ས་མ་ བ་རུ་ ན་ཀུ་ བེ་ར །"
  },
  {
    "source": "པྲ་ཧྨེ་ན་དྲ་དྷ་ན་ད།",
    "target": "པྲ་ ཧྨེ་ ན་ དྲ་ དྷ་ ན་ ད །"
  },
  {
    "source": "ད་བ་རི་ཤིག་ན་ཨ་བྷེ་ཙི་ཏ་ཙ་ར་ན།",
    "target": "ད་ བ་རི་ ཤིག་ ན་ ཨ་བྷེ་ ཙི་ཏ་ ཙ་ར་ ན །"
  },
  {
    "source": "ས་ར་ས་ར།",
    "target": "ས་ ར་ས་ ར །"
  },
  {
    "source": "སི་རི་སི་རི།",
    "target": "སི་ རི་ སི་ རི །"
  },
  {
    "source": "སུ་རུ་སུ་རུ།",
    "target": "སུ་ རུ་ སུ་ རུ །"
  },
  {
    "source": "ཙུ་རུ་ཙ་རུ།",
    "target": "ཙུ་ རུ་ཙ་ རུ །"
  },
  {
    "source": "ཏུ་རུ་ཏུ་རུ།",
    "target": "ཏུ་ རུ་ ཏུ་ རུ །"
  },
  {
    "source": "མུ་རུ་མུ་རུ།",
    "target": "མུ་ རུ་ མུ་ རུ །"
  },
  {
    "source": "ས་ན་ད་ཀུ་མཱ་ར།",
    "target": "ས་ ན་ ད་ ཀུ་མཱ་ར །"
  },
  {
    "source": "རུ་དྲ་བ་ས་བས།",
    "target": "རུ་ དྲ་བ་ ས་བ ས །"
  },
  {
    "source": "བིཥྞྱ་དྷ་ན་ད་ཏ།",
    "target": "བིཥྞྱ་ དྷ་ན་ ད་ ཏ །"
  },
  {
    "source": "རི་ཥི་ན་ཡ་ཀ་བ་ཧུ།",
    "target": "རི་ཥི་ ན་ ཡ་ ཀ་ བ་ཧུ །"
  },
  {
    "source": "བི་དྷ་བེ་ཥ་དྷ་ར།",
    "target": "བི་དྷ་ བེ་ ཥ་ དྷ་ར །"
  },
  {
    "source": "དྷ་ར་དྷ་ར།",
    "target": "དྷ་ར་ དྷ་ར །"
  },
  {
    "source": "དྷི་རི་དྷི་རི།",
    "target": "དྷི་ རི་ དྷི་ རི །"
  },
  {
    "source": "དྷ་རུ་དྷུ་རུ།",
    "target": "དྷ་རུ་ དྷུ་ རུ །"
  },
  {
    "source": "ཐ་ར་ཐ་ར།",
    "target": "ཐ་ར་ ཐ་ར །"
  },
  {
    "source": "གྷ་ར་གྷ་ར།",
    "target": "གྷ་ ར་ གྷ་ ར །"
  },
  {
    "source": "ཡ་ར་ཡ་ར།",
    "target": "ཡ་ ར་ཡ་ ར །"
  },
  {
    "source": "ལ་ར་ལ་ར།",
    "target": "ལ་ ར་ ལ་ ར །"
  },
  {
    "source": "ཧ་ར་ཧ་ར།",
    "target": "ཧ་ར་ ཧ་ ར །"
  },
  {
    "source": "ས་ར་ས་ར།",
    "target": "ས་ ར་ས་ ར །"
  },
  {
    "source": "མ་ར་མ་ར།",
    "target": "མ་ར་མ་ར །"
  },
  {
    "source": "བ་ར་བ་ར།",
    "target": "བ་ར་བ་ ར །"
  },
  {
    "source": "དྷ་ཡ་ཀ།",
    "target": "དྷ་ཡ་ ཀ །"
  },
  {
    "source": "ན་ཡ་ཀ།",
    "target": "ན་ ཡ་ ཀ །"
  },
  {
    "source": "བི་ན་ཡ་ཀ།",
    "target": "བི་ན་ཡ་ ཀ །"
  },
  {
    "source": "ས་མནྟ།",
    "target": "ས་ མནྟ །"
  },
  {
    "source": "ཨ་བ་ལོ་ཀི་ཏེ།",
    "target": "ཨ་བ་ ལོ་ ཀི་ ཏེ །"
  },
  {
    "source": "བི་ལོ་ཀི་ཏེ་ལོ་ཀི་ཤྭ་ར་མུ་ཧུ་མུ་ཧུ།",
    "target": "བི་ལོ་ ཀི་ ཏེ་ ལོ་ ཀི་ ཤྭ་ ར་ མུ་ ཧུ་ མུ་ ཧུ །"
  },
  {
    "source": "མུ་རུ་མུ་རུ།",
    "target": "མུ་ རུ་ མུ་ རུ །"
  },
  {
    "source": "མུ་ཡ་མུ་ཡ།",
    "target": "མུ་ ཡ་ མུ་ ཡ །"
  },
  {
    "source": "མུན་ཛ་མུན་ཛ།",
    "target": "མུན་ཛ་ མུན་ ཛ །"
  },
  {
    "source": "ཤྲི་གྷ་ཤྲི་གྷ།",
    "target": "ཤྲི་ གྷ་ ཤྲི་ གྷ །"
  },
  {
    "source": "བདག་འཇིགས་པ་དང་།",
    "target": "བདག་ འཇིགས་པ་ དང་ །"
  },
  {
    "source": "གནོད་པ་དང་།",
    "target": "གནོད་པ་ དང་ །"
  },
  {
    "source": "ནད་འགོ་བ་ཐམས་ཅད་དང་།",
    "target": "ནད་ འགོ་བ་ ཐམས་ཅད་ དང་ །"
  },
  {
    "source": "འཁྲུག་པ་དང་།",
    "target": "འཁྲུག་པ་ དང་ །"
  },
  {
    "source": "དུག་ཐམས་ཅད་ལས་སྲུངས་ཤིག།",
    "target": "དུག་ ཐམས་ཅད་ ལས་ སྲུངས་ ཤིག །"
  },
  {
    "source": "དེ་བཞིན་དུ་བསད་པ་དང་།",
    "target": "དེ་ བཞིན་ དུ་ བསད་པ་ དང་ །"
  },
  {
    "source": "བཅིང་པ་དང་།",
    "target": "བཅིང་པ་ དང་ །"
  },
  {
    "source": "བརྡེག་པ་དང་།",
    "target": "བརྡེག་པ་ དང་ །"
  },
  {
    "source": "སྤྱོ་བ་དང་།",
    "target": "སྤྱོ་བ་ དང་ །"
  },
  {
    "source": "རྒྱལ་པོ་དང་།",
    "target": "རྒྱལ་པོ་ དང་ །"
  },
  {
    "source": "ཀུན་པོ་དང་།",
    "target": "ཀུན་པོ་ དང་ །"
  },
  {
    "source": "མེ་དང་།",
    "target": "མེ་ དང་ །"
  },
  {
    "source": "ཆུ་དང་།",
    "target": "ཆུ་ དང་ །"
  },
  {
    "source": "དུག་དང་།",
    "target": "དུག་ དང་ །"
  },
  {
    "source": "མཚོན་ལས་ཡོངས་སུ་ཐར་བར་གྱུར་ཅིག།",
    "target": "མཚོན་ ལས་ ཡོངས་ སུ་ ཐར་བ ར་ གྱུར་ ཅིག །"
  },
  {
    "source": "ཀ་ཎ་ཀ་ཎ།",
    "target": "ཀ་ཎ་ ཀ་ ཎ །"
  },
  {
    "source": "ཀི་ཎི་ཀི་ཎི།",
    "target": "ཀི་ ཎི་ ཀི་ ཎི །"
  },
  {
    "source": "ཀུ་ཎུ་ཀུ་ཎུ།",
    "target": "ཀུ་ ཎུ་ ཀུ་ ཎུ །"
  },
  {
    "source": "ཙ་ར་ཙ་ར།",
    "target": "ཙ་ར་ ཙ་ར །"
  },
  {
    "source": "ཙི་རི་ཙི་རི།",
    "target": "ཙི་ རི་ ཙི་ རི །"
  },
  {
    "source": "ཙུ་རུ་ཙུ་རུ།",
    "target": "ཙུ་ རུ་ ཙུ་ རུ །"
  },
  {
    "source": "ཨིན་དྲི་ཡ་བ་ལ་བོདྱཾ་ག།",
    "target": "ཨིན་ དྲི་ ཡ་བ་ ལ་ བོདྱཾ་ ག །"
  },
  {
    "source": "ཙ་ཏུར་ཨརྻ་སད་ཏྱ།",
    "target": "ཙ་ ཏུར་ ཨརྻ་ སད་ ཏྱ །"
  },
  {
    "source": "སཾ་པྲ་ཀཱ་ཤ་ཀ།",
    "target": "སཾ་ པྲ་ཀཱ་ཤ་ ཀ །"
  },
  {
    "source": "ཏ་མ་ཏ་མ།",
    "target": "ཏ་མ་ ཏ་མ །"
  },
  {
    "source": "ད་མ་ད་མ།",
    "target": "ད་ མ་ ད་ མ །"
  },
  {
    "source": "ས་མ་ས་མ།",
    "target": "ས་ མ་ ས་ མ །"
  },
  {
    "source": "ས་མ་ས་ཡ།",
    "target": "ས་ མ་ ས་ཡ །"
  },
  {
    "source": "མ་ཧཱ་ཏ་མ་ཨན་ཏ་ཀ་ར།",
    "target": "མ་ཧཱ་ ཏ་མ་ ཨན་ ཏ་ཀ་ར །"
  },
  {
    "source": "བྷི་ད་མ་ནི་ཀ་ར།",
    "target": "བྷི་ ད་མ་ ནི་ ཀ་ ར །"
  },
  {
    "source": "ཥ་ཊ་པ་ར་མི་ཏ།",
    "target": "ཥ་ ཊ་ པ་ར་ མི་ཏ །"
  },
  {
    "source": "ཙུ་ར་ཀ་པ་ར།",
    "target": "ཙུ་ར་ ཀ་ པ་ ར །"
  },
  {
    "source": "ཀི་ལི་ཀི་ལི།",
    "target": "ཀི་ ལི་ ཀི་ ལི །"
  },
  {
    "source": "ཊ་ཊ་ཊ་ཊ།",
    "target": "ཊ་ ཊ་ ཊ་ ཊ །"
  },
  {
    "source": "ཊི་ཊི་ཊི་ཊི།",
    "target": "ཊི་ ཊི་ ཊི་ ཊི །"
  },
  {
    "source": "ཊུ་ཊུ་ཊུ་ཊུ།",
    "target": "ཊུ་ ཊུ་ ཊུ་ ཊུ །"
  },
  {
    "source": "ཋ་ཋ་ཋ་ཋ།",
    "target": "ཋ་ ཋ་ ཋ་ ཋ །"
  },
  {
    "source": "ཋི་ཋི་ཋི་ཋི།",
    "target": "ཋི་ ཋི་ ཋི་ ཋི །"
  },
  {
    "source": "ཋུ་ཋུ་ཋུ་ཋུ།",
    "target": "ཋུ་ ཋུ་ ཋུ་ ཋུ །"
  },
  {
    "source": "ཨ་ཙརྨ་ཀྲི་ཏ་པ་རི་ཀ་ར།",
    "target": "ཨ་ ཙརྨ་ ཀྲི་ ཏ་པ་ རི་ ཀ་ ར །"
  },
  {
    "source": "ཨེ་ཧྱ་ཧི།",
    "target": "ཨེ་ ཧྱ་ ཧི །"
  },
  {
    "source": "མ་ཧཱ་ཀ་རུ་ཎི་ཀ།",
    "target": "མ་ཧཱ་ ཀ་རུ་ ཎི་ ཀ །"
  },
  {
    "source": "ཨི་ཀ་ར་མ་ཧེ།",
    "target": "ཨི་ ཀ་ར་ མ་ཧེ །"
  },
  {
    "source": "ཤ་ར་བུདྡྷ།",
    "target": "ཤ་ར་ བུདྡྷ །"
  },
  {
    "source": "ག་ན་བྷ་ན་ཛ་ཀ་ཀུ་རུ་ཀུ་རུ།",
    "target": "ག་ ན་ བྷ་ན་ ཛ་ ཀ་ ཀུ་རུ་ ཀུ་རུ །"
  },
  {
    "source": "བ་ར་བ་ར།",
    "target": "བ་ར་བ་ ར །"
  },
  {
    "source": "པ་ར་པར།",
    "target": "པ་ར་པ ར །"
  },
  {
    "source": "ས་ར་ས་ར།",
    "target": "ས་ ར་ས་ ར །"
  },
  {
    "source": "ཀ་ར་ཀ་ར།",
    "target": "ཀ་ར་ཀ་ར །"
  },
  {
    "source": "ཙུ་རུ་ཙུ་རུ།",
    "target": "ཙུ་ རུ་ ཙུ་ རུ །"
  },
  {
    "source": "ཀ་ཏ་ཀ་ཏ།",
    "target": "ཀ་ ཏ་ ཀ་ ཏ །"
  },
  {
    "source": "ཀི་ཊི་ཀི་ཊི།",
    "target": "ཀི་ཊི་ ཀི་ ཊི །"
  },
  {
    "source": "ཀུ་ཊུ་ཀུ་ཊུ།",
    "target": "ཀུ་ ཊུ་ ཀུ་ ཊུ །"
  },
  {
    "source": "པ་ཊ་པ་ཊ།",
    "target": "པ་ཊ་པ་ ཊ །"
  },
  {
    "source": "མ་ཊ་མ་ཊ།",
    "target": "མ་ཊ་ མ་ཊ །"
  },
  {
    "source": "མ་ཧཱ་བི་ཤུདྡྷ།",
    "target": "མ་ཧཱ་ བི་ ཤུདྡྷ །"
  },
  {
    "source": "བི་ཥ་ཡ་བ་ས་ནི།",
    "target": "བི་ ཥ་ ཡ་བ་ ས་ ནི །"
  },
  {
    "source": "མ་ཧཱ་ཀཱ་རུ་ཎི་ཀཱ་ཡ།",
    "target": "མ་ཧཱ་ ཀཱ་རུ་ ཎི་ ཀཱ་ཡ །"
  },
  {
    "source": "ཤ་བེ་ཏ་ཡ་ཛྙ་བེ་ཏཱ་ཡ།",
    "target": "ཤ་ བེ་ཏ་ ཡ་ ཛྙ་ བེ་ ཏཱ་ ཡ །"
  },
  {
    "source": "རཏྣ་མུ་ཀུ་ཊ།",
    "target": "རཏྣ་ མུ་ཀུ་ཊ །"
  },
  {
    "source": "མུ་ལ་བྷ་ར།",
    "target": "མུ་ལ་ བྷ་ ར །"
  },
  {
    "source": "སརྦ་ཛྙ་ཤ་རི།",
    "target": "སརྦ་ཛྙ་ ཤ་རི །"
  },
  {
    "source": "སྲི་ཀྲི་ཏི།",
    "target": "སྲི་ ཀྲི་ ཏི །"
  },
  {
    "source": "ཛ་ཏ་མུ་ཀ་ཏྲ།",
    "target": "ཛ་ ཏ་ མུ་ ཀ་ ཏྲ །"
  },
  {
    "source": "མ་ཙ་བྷ་ར་དྷ་ག་མ་ལ།",
    "target": "མ་ཙ་ བྷ་ར་ དྷ་ ག་ མ་ ལ །"
  },
  {
    "source": "ཨ་ལ་ཨ་ལྀངྐ་ཏ་ཀ་ར་ཨ་བྷ་ཝ་སྭ་བྷ་ཝ་ས་མཱ་དྷི་བི་མོཀྵ།",
    "target": "ཨ་ལ་ ཨ་ ལྀངྐ་ ཏ་ཀ་ར་ ཨ་བྷ་ཝ་ སྭ་བྷ་ ཝ་ ས་མཱ་དྷི་ བི་མོཀྵ །"
  },
  {
    "source": "ཨ་པྲ་ཀམྦྷ།",
    "target": "ཨ་པྲ་ ཀམྦྷ །"
  },
  {
    "source": "བ་ཧུ་ས་ཏྭ།",
    "target": "བ་ཧུ་ ས་ ཏྭ །"
  },
  {
    "source": "སན་ཏ་ཏི།",
    "target": "སན་ ཏ་ ཏི །"
  },
  {
    "source": "བ་རི་མོ་ཙཀྲ།",
    "target": "བ་རི་ མོ་ ཙཀྲ །"
  },
  {
    "source": "མ་ཧཱ་ཀཱ་རུ་ཎི་ཀ།",
    "target": "མ་ཧཱ་ ཀཱ་རུ་ ཎི་ ཀ །"
  },
  {
    "source": "སརྦ་ཀརྨ་ཨ་པ་ར་ཎ་བི་ཤོ་དྷ་ཀ།",
    "target": "སརྦ་ ཀརྨ་ ཨ་པ་ར་ ཎ་ བི་ ཤོ་ དྷ་ ཀ །"
  },
  {
    "source": "སརྦ་བྱི་ཧི་པྲ་མོ་ཙཀྲ།",
    "target": "སརྦ་ བྱི་ ཧི་ པྲ་མོ་ ཙཀྲ །"
  },
  {
    "source": "སརྦ་ས་ཏྭ་ས་མ་ཤ་ས་ར།",
    "target": "སརྦ་ ས་ ཏྭ་ས་ མ་ ཤ་ ས་ ར །"
  },
  {
    "source": "ན་མསྟུ་ར་སྭཱ་ཧཱ།",
    "target": "ན་ མསྟུ་ ར་ སྭཱ་ཧཱ །"
  },
  {
    "source": "ཀ་ལ་མྲིད་པྲ་ཤ་མ་ནཱ་ཡ་སྭཱ་ཧཱ།",
    "target": "ཀ་ལ་ མྲིད་ པྲ་ ཤ་ མ་ ནཱ་ཡ་ སྭཱ་ ཧཱ །"
  },
  {
    "source": "ཨ་མོ་གྷ་ཡ་སྭཱ་ཧཱ།",
    "target": "ཨ་ མོ་ གྷ་ ཡ་ སྭཱ་ཧཱ །"
  },
  {
    "source": "ཨོཾ་ཨ་མོ་གྷ་བཱ་ཤཱ་ཡ་སྭཱ་ཧཱ།",
    "target": "ཨོཾ་ ཨ་ མོ་ གྷ་ བཱ་ ཤཱ་ ཡ་ སྭཱ་ ཧཱ །"
  },
  {
    "source": "ཨ་ཛི་ཏཱ་ཡ་སྭཱ་ཧཱ།",
    "target": "ཨ་ ཛི་ ཏཱ་ ཡ་ སྭཱ་ཧཱ །"
  },
  {
    "source": "ཨ་པ་ར་ཛི་ཏ་ཡ་སྭཱ་ཧཱ།",
    "target": "ཨ་པ་ར་ ཛི་ཏ་ ཡ་ སྭཱ་ ཧཱ །"
  },
  {
    "source": "མཱ་ར་སྱ་ནི་པ་མརྡ་ནཱ་ཡ་སྭཱ་ཧཱ།",
    "target": "མཱ་ར་ སྱ་ ནི་ པ་ མརྡ་ ནཱ་ཡ་ སྭཱ་ ཧཱ །"
  },
  {
    "source": "བ་ར་དྲཱ་ཡ་སྭཱ་ཧཱ།",
    "target": "བ་ར་ དྲཱ་ ཡ་ སྭཱ་ཧཱ །"
  },
  {
    "source": "ཨེ་ད་ན་ཙ་མེ་ཀརྨ་ཀུ་རུ་སྭཱ་ཧཱ།",
    "target": "ཨེ་ ད་ན་ ཙ་ མེ་ ཀརྨ་ ཀུ་རུ་ སྭཱ་ཧཱ །"
  },
  {
    "source": "ཨོཾ་ཛ་ཡ་ཧཱུཾ་ཕཊ་སྭཱ་ཧཱ།",
    "target": "ཨོཾ་ ཛ་ཡ་ ཧཱུཾ་ ཕཊ་ སྭཱ་ཧཱ །"
  },
  {
    "source": "ཨོཾ་ཧྲི་ཏྲཻ་ལོ་ཀྱ་བི་ཛ་ཡ་ཨ་མོ་གྷ་པཱ་ཤཱ་ཡ་སྭཱ་ཧཱ།",
    "target": "ཨོཾ་ ཧྲི་ ཏྲཻ་ ལོ་ ཀྱ་ བི་ཛ་ཡ་ ཨ་མོ་གྷ་ པཱ་ ཤཱ་ ཡ་ སྭཱ་ ཧཱ །"
  },
  {
    "source": "ཨ་པྲ་ཏི་ཧ་ཏ་ཧྲི་ཧ་ཧཱུྃ་ཕཊ་སྭཱ་ཧཱ།།",
    "target": "ཨ་པྲ་ ཏི་ ཧ་ ཏ་ ཧྲི་ ཧ་ ཧཱུྃ་ ཕཊ་ སྭཱ་ཧཱ ། །"
  },
  {
    "source": "གཟུངས་སྔགས་འདིའི་ཆོ་ག་ནི་ཨ་མོ་གྷ་བཱ་ཤའི་གཟུངས་བུམ་པ་ལ་བཟླས་པས།",
    "target": "གཟུངས་སྔགས་ འདི འི་ ཆོ་ག་ ནི་ ཨ་ མོ་ གྷ་ བཱ་ ཤ འི་ གཟུངས་ བུམ་པ་ ལ་ བཟླས་པ ས །"
  },
  {
    "source": "གེགས་ཀྱིས་བརླ་མས་པའམ།",
    "target": "གེགས་ ཀྱིས་ བརླ་ མ ས་ པ འམ །"
  },
  {
    "source": "འདྲེ་གདོན་གྱིས་ཟིན་པའམ།",
    "target": "འདྲེ་ གདོན་ གྱིས་ ཟིན་པ འམ །"
  },
  {
    "source": "བྱད་དུ་ཚུད་པའམ།",
    "target": "བྱད་ དུ་ ཚུད་པ འམ །"
  },
  {
    "source": "བུད་མེད་བྱུར་ཆེ་ཞིང་བུ་མི་འབྱུང་བའམ།",
    "target": "བུད་མེད་ བྱུར་ ཆེ་ ཞིང་ བུ་ མི་ འབྱུང་བ འམ །"
  },
  {
    "source": "བུ་མི་གསོས་པ་རྣམས་ལ་ཕན་པར་བྱ་བའི་ཕྱིར།",
    "target": "བུ་ མི་ གསོས་པ་ རྣམས་ ལ་ ཕན་པ ར་ བྱ་བ འི་ ཕྱི ར །"
  },
  {
    "source": "འབབ་ཆུའི་འགྲམ་མམ།",
    "target": "འབབ་ཆུ འི་ འགྲམ་ མམ །"
  },
  {
    "source": "ཤིང་གཅིག་པའི་དྲུང་ངམ།",
    "target": "ཤིང་ གཅིག་པ འི་ དྲུང་ ངམ །"
  },
  {
    "source": "ལམ་གྱི་བཞི་མདོ་དང་།",
    "target": "ལམ་ གྱི་ བཞི་ མདོ་ དང་ །"
  },
  {
    "source": "ཁང་སྟོང་ལ་སོགས་པའི་གནས་སུ་དཀྱིལ་འཁོར་གྲུ་བཞི་སྒོ་བཞི་པ་ཅིག་ཚོན་རྩི་དཀར་པོས་བྲིས་ཏེ།",
    "target": "ཁང་ སྟོང་ ལ་ སོགས་པ འི་ གནས་ སུ་ དཀྱིལ་འཁོར་ གྲུ་བཞི་ སྒོ་ བཞི་པ་ ཅིག་ ཚོན་རྩི་ དཀར་པོ ས་ བྲིས་ ཏེ །"
  },
  {
    "source": "དབུས་སུ་ཡང་པདྨ་དཀར་པོ་འདབ་མ་བརྒྱད་པ་བྲིས་ལ།",
    "target": "དབུས་ སུ་ ཡང་ པདྨ་ དཀར་པོ་ འདབ་མ་ བརྒྱད་པ་ བྲིས་ ལ །"
  },
  {
    "source": "གསེར་དངུལ་ལམ།",
    "target": "གསེར་དངུལ་ ལམ །"
  },
  {
    "source": "ཟངས་ཀྱི་བུམ་པའམ།",
    "target": "ཟངས་ ཀྱི་ བུམ་པ འམ །"
  },
  {
    "source": "ཁམ་པའི་བུམ་པ་སོ་བཟང་པོ་བཏང་བ་ནག་པོ་དང་།",
    "target": "ཁམ་པ འི་ བུམ་པ་ སོ་ བཟང་པོ་ བཏང་བ་ ནག་པོ་ དང་ །"
  },
  {
    "source": "རབ་རིབ་མེད་པ།",
    "target": "རབ་རིབ་ མེད་པ །"
  },
  {
    "source": "གས་ཆག་མེད་པའི་ནང་དུ་ཆུ་གཙང་མས་གསུམ་གཉིས་བཀང་སྟེ།",
    "target": "གས་ཆག་ མེད་པ འི་ ནང་ དུ་ ཆུ་ གཙང་མ ས་ གསུམ་ གཉིས་ བཀང་ སྟེ །"
  },
  {
    "source": "རིན་པོ་ཆེ་ལྔ།",
    "target": "རིན་པོ་ཆེ་ ལྔ །"
  },
  {
    "source": "སྨན་སྣ་ལྔ།",
    "target": "སྨན་ སྣ་ ལྔ །"
  },
  {
    "source": "དྲི་ལྔ།",
    "target": "དྲི་ ལྔ །"
  },
  {
    "source": "འབྲུ་སྣ་ལྔ་རྣམས་བླུགས་ལ།",
    "target": "འབྲུ་སྣ་ ལྔ་ རྣམས་ བླུགས་ ལ །"
  },
  {
    "source": "མགུལ་ཆིངས་དཀར་པོ་རས་གསར་པ་ཁ་ཚར་ཅན་དང་།",
    "target": "མགུལ་ཆིངས་ དཀར་པོ་ རས་ གསར་པ་ ཁ་ ཚར་ ཅན་ དང་ །"
  },
  {
    "source": "ཁ་རྒྱན་ཤུག་པའམ།",
    "target": "ཁ་རྒྱན་ ཤུག་པ འམ །"
  },
  {
    "source": "ཐང་ཤིང་གི་ལོ་མ་འམ།",
    "target": "ཐང་ཤིང་ གི་ ལོ་མ་ འམ །"
  },
  {
    "source": "ཀུ་ཤ་མེ་ཏོག་དང་འབྲས་བུ་དང་བཅས་པ་ཅིག་པདྨའི་སྟེང་དུ་བཞག་ལ།",
    "target": "ཀུ་ཤ་ མེ་ཏོག་ དང་ འབྲས་བུ་ དང་ བཅས་པ་ ཅིག་ པདྨ འི་ སྟེང་ དུ་ བཞག་ ལ །"
  },
  {
    "source": "རང་ཉིད་འཕགས་པ་སྤྱན་རས་གཟིགས་དབང་ཕྱུག་གི་སྐུར་བསྒོམ་སྟེ།",
    "target": "རང་ ཉིད་ འཕགས་པ་ སྤྱན་རས་གཟིགས་ དབང་ཕྱུག་ གི་ སྐུ ར་ བསྒོམ་ སྟེ །"
  },
  {
    "source": "བུམ་པ་དེ་རིན་པོ་ཆེའི་རྫིང་བུ་བདུད་རྩིའི་ཆུས་གང་བར་བསམ་ལ།",
    "target": "བུམ་པ་ དེ་ རིན་པོ་ཆེ འི་ རྫིང་བུ་ བདུད་རྩི འི་ ཆུ ས་ གང་བ ར་ བསམ་ ལ །"
  },
  {
    "source": "ཆུ་དེའི་ནང་ནས་པདྨ་དཀར་པོ་ཅིག་བྱུང་བར་བསམ་ཞིང་།",
    "target": "ཆུ་ དེ འི་ ནང་ ནས་ པདྨ་ དཀར་པོ་ ཅིག་ བྱུང་བ ར་ བསམ་ ཞིང་ །"
  },
  {
    "source": "པདྨའི་ལྟེ་བར་ཧྲཱི་ཡིག་དཀར་པོ་ཡོངས་སུ་གྱུར་པ་ལས་འཕགས་པ་སྤྱན་རས་གཟིགས་དབང་ཕྱུག་ཏུ་གྱུར་བར་བསྐྱེད་ལ།",
    "target": "པདྨ འི་ ལྟེ་བ ར་ ཧྲཱི་ ཡིག་ དཀར་པོ་ ཡོངས་ སུ་ གྱུར་པ་ ལས་ འཕགས་པ་ སྤྱན་རས་གཟིགས་ དབང་ཕྱུག་ ཏུ་ གྱུར་བ ར་ བསྐྱེད་ ལ །"
  },
  {
    "source": "མཆོད་པ་དང་།",
    "target": "མཆོད་པ་ དང་ །"
  },
  {
    "source": "བསྟོད་པ་བྱས་ཏེ་གང་འདོད་པ་དེ་འགྲུབ་པར་གྱུར་ཅིག་ཅེས་གསོལ་བ་བཏབ་ལ།",
    "target": "བསྟོད་པ་ བྱས་ ཏེ་ གང་ འདོད་པ་ དེ་ འགྲུབ་པ ར་ གྱུར་ ཅིག་ ཅེས་ གསོལ་བ་ བཏབ་ ལ །"
  },
  {
    "source": "ཨ་མོ་གྷ་པཱ་ཤའི་གཟུངས་བུམ་ཆུ་དེ་ལ་ལན་བདུན་གསུམ་དུ་ཚིག་གཞན་མ་འདྲེས་པར་བཟླས་ཏེ།",
    "target": "ཨ་ མོ་ གྷ་ པཱ་ཤ འི་ གཟུངས་ བུམ་ཆུ་ དེ་ ལ་ ལན་ བདུན་ གསུམ་ དུ་ ཚིག་ གཞན་ མ་ འདྲེས་པ ར་ བཟླས་ ཏེ །"
  },
  {
    "source": "བུམ་ཆུ་དེས་དེའི་སྤྱི་བོ་ནས་བྱུགས་ནས་བཀྲུས་ན།",
    "target": "བུམ་ཆུ་ དེ ས་ དེ འི་ སྤྱི་བོ་ ནས་ བྱུགས་ ནས་ བཀྲུས་ ན །"
  },
  {
    "source": "གེགས་དང་གདོན་ཐམས་ཅད་ལས་ཐར་བར་འགྱུར་རོ།།",
    "target": "གེགས་ དང་ གདོན་ ཐམས་ཅད་ ལས་ ཐར་བ ར་ འགྱུར་ རོ ། །"
  },
  {
    "source": "ལུས་ཀྱི་ཕྱི་ནང་གཉིས་ཀ་དག་པར་བཀྲུས་ཏེ།",
    "target": "ལུས་ ཀྱི་ ཕྱི་ནང་ གཉིས་ ཀ་ དག་པ ར་ བཀྲུས་ ཏེ །"
  },
  {
    "source": "གོས་དཀར་པ་དྲི་མ་མེད་པ་གྱོན་ལ།",
    "target": "གོས་ དཀར་པ་ དྲི་མ་ མེད་པ་ གྱོན་ ལ །"
  },
  {
    "source": "སྤོས་དང་མེ་ཏོག་ལ་སོགས་པས་བརྒྱན་ལ་གཟུངས་དེ་ཉིད་བཀླགས་ཤིང་གདོན་པར་བྱའོ།།",
    "target": "སྤོས་ དང་ མེ་ཏོག་ ལ་ སོགས་པ ས་ བརྒྱན་ ལ་ གཟུངས་ དེ་ ཉིད་ བཀླགས་ ཤིང་ གདོན་པ ར་ བྱ འོ ། །"
  },
  {
    "source": "བཀྲ་ཤིས་ཀྱང་བྱའོ།།",
    "target": "བཀྲ་ཤིས་ ཀྱང་ བྱ འོ ། །"
  },
  {
    "source": "དཀྱིལ་འཁོར་དེའི་ཁོར་ཡུག་ཏུ་འཇིག་རྟེན་སྐྱོང་བ་བརྒྱད་ཀྱང་སོ་སོའི་མིང་ནས་སྨོས་ཏེ་སྤྱན་དྲངས་ལ་མཆོད་ནས་གང་འདོད་པ་དེ་འགྲུབ་པར་གྱུར་ཅིག་ཅེས་གསོལ་བ་བཏབ་ལ།",
    "target": "དཀྱིལ་འཁོར་ དེ འི་ ཁོར་ཡུག་ ཏུ་ འཇིག་རྟེན་ སྐྱོང་བ་ བརྒྱད་ ཀྱང་ སོ་སོ འི་ མིང་ ནས་ སྨོས་ ཏེ་ སྤྱན་ དྲངས་ ལ་ མཆོད་ ནས་ གང་ འདོད་པ་ དེ་ འགྲུབ་པ ར་ གྱུར་ ཅིག་ ཅེས་ གསོལ་བ་ བཏབ་ ལ །"
  },
  {
    "source": "འབྱུང་པོ་རྣམས་ལ་ཡང་མཆོད་པ་དང་གཏོར་མ་རྒྱ་ཆེར་སྦྱིན་ནོ།།",
    "target": "འབྱུང་པོ་ རྣམས་ ལ་ ཡང་ མཆོད་པ་ དང་ གཏོར་མ་ རྒྱ་ ཆེ ར་ སྦྱིན་ ནོ ། །"
  },
  {
    "source": "བདག་བསྲུང་བ་དང་།",
    "target": "བདག་ བསྲུང་བ་ དང་ །"
  },
  {
    "source": "མཚམས་བཅད་པ་ཡང་བྱས་ཏེ།",
    "target": "མཚམས་ བཅད་པ་ ཡང་ བྱས་ ཏེ །"
  },
  {
    "source": "ཚེས་བརྒྱད་ལ་བྱ་བར་རིགས་སོ།།",
    "target": "ཚེས་ བརྒྱད་ ལ་ བྱ་བ ར་ རིགས་ སོ ། །"
  },
  {
    "source": "དེ་ལྟར་བྱས་ན་གེགས་དང་བྱད་དང་།",
    "target": "དེ་ ལྟ ར་ བྱས་ ན་ གེགས་ དང་ བྱད་ དང་ །"
  },
  {
    "source": "ནད་འགོ་བ་ཐམས་ཅད་ཀྱིས་མི་ཚུགས་སོ།།",
    "target": "ནད་ འགོ་བ་ ཐམས་ཅད་ ཀྱིས་ མི་ ཚུགས་ སོ ། །"
  },
  {
    "source": "འཕགས་པ་སྤྱན་རས་གཟིགས་དོན་ཡོད་ཞགས་པའི་སྙིང་པོ་ཞེས་བྱ་བའི་གཟུངས་རྫོགས་སོ།།",
    "target": "འཕགས་པ་ སྤྱན་རས་གཟིགས་ དོན་ཡོད་ཞགས་པ འི་ སྙིང་པོ་ ཞེས་ བྱ་བ འི་ གཟུངས་ རྫོགས་ སོ ། །"
  },
  {
    "source": "།།",
    "target": "། །"
  },
  {
    "source": "མངྒ་ལ་མསྟུ།།",
    "target": "མངྒ་ ལ་ མསྟུ ། །"
  },
  {
    "source": "།།",
    "target": "། །"
  }
]
