[
  {
    "source": "༼༦༣༽༄༅།།",
    "target": "༼ ༦༣ ༽ ༄༅ ། །"
  },
  {
    "source": "ཤིན་ཏུ་སྤྲོས་མེད་ཀྱི་དབང་ཆོག་པདྨའི་དྲྭ་བ་བཞུགས་སོ།།",
    "target": "ཤིན་ ཏུ་ སྤྲོས་མེད་ ཀྱི་ དབང་ཆོག་ པདྨ འི་ དྲྭ་བ་ བཞུགས་ སོ ། །"
  },
  {
    "source": "།།",
    "target": "། །"
  },
  {
    "source": "༼༦༤༽༄༅།།",
    "target": "༼ ༦༤ ༽ ༄༅ ། །"
  },
  {
    "source": "བླ་མ་སངས་རྒྱས་ཀུན་དངོས་ལ།།",
    "target": "བླ་མ་ སངས་རྒྱས་ ཀུན་ དངོས་ ལ ། །"
  },
  {
    "source": "དངོས་གྲུབ་དོན་དུ་ཕྱག་འཚལ་ཏེ།།",
    "target": "དངོས་གྲུབ་ དོན་ དུ་ ཕྱག་ འཚལ་ ཏེ ། །"
  },
  {
    "source": "དཀྱིལ་འཁོར་ཤིན་ཏུ་སྤྲོས་མེད་ཀྱི།།",
    "target": "དཀྱིལ་འཁོར་ ཤིན་ ཏུ་ སྤྲོ ས་ མེད་ ཀྱི ། །"
  },
  {
    "source": "དབང་ཆོག་གསལ་བར་བདག་གིས་བཀོད།།",
    "target": "དབང་ ཆོག་ གསལ་བ ར་ བདག་ གིས་ བཀོད ། །"
  },
  {
    "source": "འདི་ལ་གཉིས་སྟེ།",
    "target": "འདི་ ལ་ གཉིས་ སྟེ །"
  },
  {
    "source": "སྔོན་འགྲོ་སྤྱོད་པ་བརྩམ་པ་དང་།",
    "target": "སྔོན་ འགྲོ་ སྤྱོད་པ་ བརྩམ་པ་ དང་ །"
  },
  {
    "source": "དངོས་གཞི་དབང་བསྐུར་བའོ།།",
    "target": "དངོས་གཞི་ དབང་ བསྐུར་ བ འོ ། །"
  },
  {
    "source": "དང་པོ་ནི།",
    "target": "དང་པོ་ ནི །"
  },
  {
    "source": "དཔོན་སློབ་ཀུན་རབ་ཏུ་དབེན་པའི་ལུང་སྟོང་ལ་སོགས་པར་སོང་ལ།།",
    "target": "དཔོན་སློབ་ ཀུན་ རབ་ ཏུ་ དབེན་པ འི་ ལུང་ སྟོང་ ལ་ སོགས་པ ར་ སོང་ ལ ། །"
  },
  {
    "source": "ཚོགས་དང་གཏོར་མ་དང་གསེར་གྱི་མཎྜལ་ལ་སོགས་པ་སྟ་གོན་དུ་བྱ་ཞིང་།",
    "target": "ཚོགས་ དང་ གཏོར་མ་ དང་ གསེར་ གྱི་ མཎྜལ་ ལ་ སོགས་པ་ སྟ་གོན་ དུ་ བྱ་ ཞིང་ །"
  },
  {
    "source": "བླ་མ་དང་མཁའ་འགྲོ་མཉེས་པར་བྱས་ནས་རིག་པར་སྒྲིབ་གཡོག་མེད་པར་མཚོན་པའི་ཕྱིར་དུ།",
    "target": "བླ་མ་ དང་ མཁའ་འགྲོ་ མཉེས་པ ར་ བྱས་ ནས་ རིག་པ ར་ སྒྲིབ་ གཡོག་ མེད་པ ར་ མཚོན་པ འི་ ཕྱི ར་ དུ །"
  },
  {
    "source": "གཅེར་བུའམ་སྟོད་གཡོགས་ཙམ་ཕུད་ལ།",
    "target": "གཅེར་བུ འམ་ སྟོད་གཡོགས་ ཙམ་ ཕུད་ ལ །"
  },
  {
    "source": "རྣམ་པར་ཤེས་པའི་ཚོགས་བརྒྱད་གནས་སུ་དག་པ་དང་།",
    "target": "རྣམ་པ ར་ ཤེས་པ འི་ ཚོགས་ བརྒྱད་ གནས་ སུ་ དག་པ་ དང་ །"
  },
  {
    "source": "བར་ཆད་ཞི་བར་བྱ་བའི་ཕྱིར་དུ་གོ་བགོ་བ་ནི།",
    "target": "བར་ཆད་ ཞི་བ ར་ བྱ་བ འི་ ཕྱི ར་ དུ་ གོ་ བགོ་བ་ ནི །"
  },
  {
    "source": "སློབ་མ་དེ་དག་བླ་མའི་སྐུ་སྔོ་ནག་རབ་ཏུ་འཇིགས་ཤིང་སྐུ་བརྫེས་པ།",
    "target": "སློབ་མ་ དེ་ དག་ བླ་མ འི་ སྐུ་ སྔོ་ ནག་ རབ་ ཏུ་ འཇིགས་ ཤིང་ སྐུ་ བརྫེས་པ །"
  },
  {
    "source": "མཆེ་བ་གཙིགས་ཤིང་ལྗགས་འགྱུར་བར་བསམས་པའི་སྤྱི་བོར་ལཾ་སེར་པོ།།",
    "target": "མཆེ་བ་ གཙིགས་ ཤིང་ ལྗགས་ འགྱུར་བ ར་ བསམས་པ འི་ སྤྱི་བོ ར་ ལཾ་ སེར་པོ ། །"
  },
  {
    "source": "དཔྲལ་བར་ཨེ་མཐིང་ག།",
    "target": "དཔྲལ་བ ར་ ཨེ་ མཐིང་ག །"
  },
  {
    "source": "ལྐོག་མར་སུ་སེར་པོ།།",
    "target": "ལྐོག་ མར་ སུ་ སེར་པོ ། །"
  },
  {
    "source": "མགྲིན་པར་ཁམ་དུད་ཁ།",
    "target": "མགྲིན་པ ར་ ཁམ་ དུད་ཁ །"
  },
  {
    "source": "ནུ་མ་གཉིས་ལ་ཧ་དཀར་༼༦༥༽པོ།།",
    "target": "ནུ་མ་ གཉིས་ ལ་ ཧ་ དཀར་ ༼ ༦༥ ༽ པོ ། །"
  },
  {
    "source": "ལྟེ་བར་རཾ་དམར་པོ།།",
    "target": "ལྟེ་བ ར་ རཾ་ དམར་པོ ། །"
  },
  {
    "source": "རྐང་མཐིལ་གཉིས་སུ་ཡཾ་ལྗང་གུ་རེ་བསམ་དུ་བཅུག་ལ།",
    "target": "རྐང་མཐིལ་ གཉིས་ སུ་ ཡཾ་ ལྗང་གུ་ རེ་ བསམ་ དུ་ བཅུག་ ལ །"
  },
  {
    "source": "བླ་མའི་ཐུགས་ཀ་ནས་ཧཱུྃ་སྔོན་པོ་འཕྲོས་པས་སློབ་མའི་སྙིང་ནང་དུ་སོང་བས་ཧཱུྃ་དུ་གྱུར་པར་བསྒོམ་ཞིང་།",
    "target": "བླ་མ འི་ ཐུགས་ ཀ་ ནས་ ཧཱུྃ་ སྔོན་པོ་ འཕྲོས་པ ས་ སློབ་མ འི་ སྙིང་ ནང་ དུ་ སོང་བ ས་ ཧཱུྃ་ དུ་ གྱུར་པ ར་ བསྒོམ་ ཞིང་ །"
  },
  {
    "source": "བླ་མས་ཧ་ཧ་ཞེས་ངར་བསྐྱེད་ལ་ལན་གསུམ་བརྗོད་ནས།",
    "target": "བླ་མ ས་ ཧ་ཧ་ ཞེས་ ངར་ བསྐྱེད་ ལ་ ལན་ གསུམ་ བརྗོད་ ནས །"
  },
  {
    "source": "སློབ་མ་ཀུན་དམིགས་པ་གསལ་པོས་གཏོར་མ་རེ་ཁྱེར་ནས་སོང་སྟེ་གཞི་བདག་དང་མཁའ་འགྲོ་རྣམས་ལ་བྱིན་ལ།",
    "target": "སློབ་མ་ ཀུན་ དམིགས་པ་ གསལ་པོ ས་ གཏོར་ མ་ རེ་ ཁྱེར་ ནས་ སོང་ སྟེ་ གཞི་བདག་ དང་ མཁའ་འགྲོ་ རྣམས་ ལ་ བྱིན་ ལ །"
  },
  {
    "source": "བདག་ལུང་པ་འདིར་སྤྱོད་པ་ཞག་གསུམ་བྱེད་པས་བར་དུ་གཅོད་པ་མ་བཏང་ཞིག།",
    "target": "བདག་ ལུང་པ་ འདི ར་ སྤྱོད་པ་ ཞག་ གསུམ་ བྱེད་པ ས་ བར་ དུ་ གཅོད་པ་ མ་ བཏང་ ཞིག །"
  },
  {
    "source": "ཅེས་བཀའ་བསྒོས་ལ།",
    "target": "ཅེས་ བཀའ་ བསྒོས་ ལ །"
  },
  {
    "source": "དང་པོ་ལུས་ཀྱི་སྤྱད་པ་བརྩམས་པ་ནི།",
    "target": "དང་པོ་ ལུས་ ཀྱི་ སྤྱད་པ་ བརྩམས་པ་ ནི །"
  },
  {
    "source": "གཅེར་བུར་བྱས་ཏེ་ཌཱ་མ་རུ་དཀྲོལ་ཞིང་ཁཾ་ག་ཐོགས་ནས་སྦ་བརྫེས་ལ་ལངས་ནས་རྒྱུག་པ་དང་།",
    "target": "གཅེར་བུ ར་ བྱས་ ཏེ་ ཌཱ་མ་རུ་ དཀྲོལ་ ཞིང་ ཁཾ་ ག་ ཐོགས་ ནས་ སྦ་ བརྫེ ས་ ལ་ ལངས་ ནས་ རྒྱུག་པ་ དང་ །"
  },
  {
    "source": "སྒུར་ནས་འགྲོ་བ་དང་།",
    "target": "སྒུར་ ནས་ འགྲོ་བ་ དང་ །"
  },
  {
    "source": "མཆོངས་པ་དང་།",
    "target": "མཆོངས་པ་ དང་ །"
  },
  {
    "source": "འཁྲབ་པ་དང་།",
    "target": "འཁྲབ་པ་ དང་ །"
  },
  {
    "source": "ལུས་བསིག་པ་དང་།",
    "target": "ལུས་ བསིག་པ་ དང་ །"
  },
  {
    "source": "སྤྱིའུ་ཚུགས་དང་།",
    "target": "སྤྱིའུ་ ཚུགས་ དང་ །"
  },
  {
    "source": "རྒྱབ་འགྲོས་དང་།",
    "target": "རྒྱབ་འགྲོས་ དང་ །"
  },
  {
    "source": "ཉལ་བ་དང་།",
    "target": "ཉལ་བ་ དང་ །"
  },
  {
    "source": "འཕྲས་པ་དང་།",
    "target": "འཕྲས་པ་ དང་ །"
  },
  {
    "source": "གར་བསྐྱུར་བ་དང་ཕྱག་རྒྱ་དང་ཡན་ལག་སྤྲུགས་པ་དང་།",
    "target": "ག ར་ བསྐྱུར་བ་ དང་ ཕྱག་རྒྱ་ དང་ ཡན་ལག་ སྤྲུགས་པ་ དང་ །"
  },
  {
    "source": "མགོ་བསྐུལ་བ་དང་།",
    "target": "མགོ་ བསྐུལ་བ་ དང་ །"
  },
  {
    "source": "ཨཾ་གཙིགས་དང་མཆེ་བ་གཉེར་བ་༼༦༦༽དང་།",
    "target": "ཨཾ་ གཙིགས་ དང་ མཆེ་བ་ གཉེར་ བ་ ༼ ༦༦ ༽ དང་ །"
  },
  {
    "source": "རྐང་ལག་ཡ་རེ་བཙུགས་ནས་འགྲོ་བ་དང་།",
    "target": "རྐང་ལག་ ཡ་ རེ་ བཙུགས་ ནས་ འགྲོ་བ་ དང་ །"
  },
  {
    "source": "འབུ་སྲིན་གྱི་ནུར་འགྲོས་དང་།",
    "target": "འབུ་ སྲིན་ གྱི་ ནུར་ འགྲོས་ དང་ །"
  },
  {
    "source": "སྟག་མོའི་མཆོངས་སྟངས་ལ་སོགས་པ་ལུས་ཀྱི་རྣམ་འགྱུར་དྲན་དགུ་ཅོག་བྱས་པའི་མཐར་ཕྱག་འཚལ་བ་དང་།",
    "target": "སྟག་མོ འི་ མཆོངས་ སྟངས་ ལ་ སོགས་པ་ ལུས་ ཀྱི་ རྣམ་འགྱུར་ དྲན་ དགུ་ ཅོག་ བྱས་པ འི་ མཐ ར་ ཕྱག་ འཚལ་བ་ དང་ །"
  },
  {
    "source": "བསྐོར་བ་དང་།",
    "target": "བསྐོར་བ་ དང་ །"
  },
  {
    "source": "ལྷའི་སྟངས་སྟབས་དང་ཕྱག་རྒྱ་བྱས་ལ་འཕྲོ་བཅད་ནས།",
    "target": "ལྷ འི་ སྟངས་ སྟབས་ དང་ ཕྱག་རྒྱ་ བྱས་ ལ་ འཕྲོ་ བཅད་ ནས །"
  },
  {
    "source": "མཚན་མོ་བདེ་བའི་མལ་དུ་འགུལ་འཕྲེགས་མེད་པར་ཉལ་བས་རྣལ་དུ་དབབ་བོ།།",
    "target": "མཚན་མོ་ བདེ་བ འི་ མལ་ དུ་ འགུལ་ འཕྲེགས་ མེད་པ ར་ ཉལ་བ ས་ རྣལ་ དུ་ དབབ་ བོ ། །"
  },
  {
    "source": "དེ་ལྟར་བྱས་པས་ལུས་རུ་ཤན་ཕྱད་པའི་ཉམས་རྟགས་ལ།",
    "target": "དེ་ ལྟ ར་ བྱས་པ ས་ ལུས་ རུ་ ཤན་ ཕྱད་པ འི་ ཉམས་ རྟགས་ ལ །"
  },
  {
    "source": "ལུས་ལ་ཆགས་ཞེན་མེད་པ་དང་།",
    "target": "ལུས་ ལ་ ཆགས་ ཞེན་ མེད་པ་ དང་ །"
  },
  {
    "source": "ལུས་མེད་པར་སྙམ་པ་དང་།",
    "target": "ལུས་ མེད་པ ར་ སྙམ་པ་ དང་ །"
  },
  {
    "source": "ཚ་གྲང་མེད་པ་དང་།",
    "target": "ཚ་གྲང་ མེད་པ་ དང་ །"
  },
  {
    "source": "བཀྲེས་སྐོམ་མེད་པ་དང་།",
    "target": "བཀྲེས་སྐོམ་ མེད་པ་ དང་ །"
  },
  {
    "source": "ངལ་དུབ་མེད་པ་དང་།",
    "target": "ངལ་དུབ་ མེད་པ་ དང་ །"
  },
  {
    "source": "ནམ་མཁའ་ལ་འགྲོ་བར་སྙམ་པ་དང་།",
    "target": "ནམ་མཁའ་ ལ་ འགྲོ་བ ར་ སྙམ་པ་ དང་ །"
  },
  {
    "source": "བདེ་དྲོད་འབར་བ་ལ་སོགས་པ་འབྱུང་ངོ་།།",
    "target": "བདེ་ དྲོད་ འབར་བ་ ལ་ སོགས་པ་ འབྱུང་ ངོ་ ། །"
  },
  {
    "source": "དེ་ལྟ་བུ་མ་བྱུང་གི་བར་དུ་བསྐྱར་བས་ལུས་ཀྱི་རུ་ཤན་ཕྱེད་ངེས་སོ།།",
    "target": "དེ་ ལྟ་བུ་ མ་ བྱུང་ གི་ བར་ དུ་ བསྐྱར་བ ས་ ལུས་ ཀྱི་ རུ་ ཤན་ ཕྱེད་ ངེས་ སོ ། །"
  },
  {
    "source": "དགོས་པ་ནི།",
    "target": "དགོས་པ་ ནི །"
  },
  {
    "source": "ལུས་ཀྱི་བར་ཆད་ཞི།",
    "target": "ལུས་ ཀྱི་ བར་ཆད་ ཞི །"
  },
  {
    "source": "སྡིག་སྒྲིབ་དག་སྤྲུལ་སྐུར་གྲོལ།",
    "target": "སྡིག་ སྒྲིབ་ དག་ སྤྲུལ་སྐུ ར་ གྲོལ །"
  },
  {
    "source": "སངས་རྒྱས་ཐམས་ཅད་ཀྱི་སྐུ་རྡོ་རྗེ་མི་འགྱུར་བ་དང་གཉིས་སུ་མེད་པར་འགྱུར་བ་ཡིན་ནོ།།",
    "target": "སངས་རྒྱས་ ཐམས་ཅད་ ཀྱི་ སྐུ་རྡོ་རྗེ་ མི་ འགྱུར་བ་ དང་ གཉིས་སུ་མེད་པ ར་ འགྱུར་བ་ ཡིན་ ནོ ། །"
  },
  {
    "source": "དེ་ནས་ངག་གི་སྤྱོད་པ་ནི།",
    "target": "དེ་ ནས་ ངག་ གི་ སྤྱོད་པ་ ནི །"
  },
  {
    "source": "རང་གི་སྒྲ་སྐད་ཐམས་ཅད་བླ་མའི་གསུང་དུ་བསམ་ལ།",
    "target": "རང་ གི་ སྒྲ་སྐད་ ཐམས་ཅད་ བླ་མ འི་ གསུང་ དུ་ བསམ་ ལ །"
  },
  {
    "source": "ངག་གི་བརྗོད་པ་སྣ་ཚོགས་བྱ་བ་ནི།",
    "target": "ངག་ གི་ བརྗོད་པ་ སྣ་ཚོགས་ བྱ་བ་ ནི །"
  },
  {
    "source": "ལྷའི་སྐད་སྙན་པའི་གླུ་དང་དབྱངས་གསལ་བྱེད་ཀྱི་ཡི་གེ་དང་།",
    "target": "ལྷ འི་ སྐད་ སྙན་པ འི་ གླུ་ དང་ དབྱངས་ གསལ་བྱེད་ ཀྱི་ ཡི་གེ་ དང་ །"
  },
  {
    "source": "སིལ་སྙན་ལྟ་བུ་ལ་སོགས་པ་དང་།",
    "target": "སིལ་སྙན་ ལྟ་བུ་ ལ་ སོགས་པ་ དང་ །"
  },
  {
    "source": "ཀླུའི་སྐད་པི་ཝང་ལྟ་བུ་དང་།",
    "target": "ཀླུ འི་ སྐད་ པི་ཝང་ ལྟ་བུ་ དང་ །"
  },
  {
    "source": "བུམ་ལྡིར་ལྟ་བུ་དང་།",
    "target": "བུམ་ ལྡིར་ ལྟ་བུ་ དང་ །"
  },
  {
    "source": "གནོད་སྦྱིན་གྱི་སྐད་བྲག་རི་ཉིལ་བ་ལྟ་བུ་དང་།",
    "target": "གནོད་སྦྱིན་ གྱི་ སྐད་ བྲག་རི་ ཉིལ་བ་ ལྟ་བུ་ དང་ །"
  },
  {
    "source": "མིའམ་ཅིའི་སྐད་རྒྱུད་མངས་དང་སྤྲིན་གྱི་ང་རོ་ལྟ་བུ་དང་།",
    "target": "མིའམ་ཅི འི་ སྐད་ རྒྱུད་ མངས་ དང་ སྤྲིན་ གྱི་ ང་ རོ་ ལྟ་བུ་ དང་ །"
  },
  {
    "source": "སྲིན་པོའི་སྐད་ར་ལ་ར་ལ་རི་ལི་རི་ལི་ལ་སོགས་པ་སེར་སྤྲིན་གྱི་འབྲུག་སྒྲ་ལྟ་བུ་དང་།",
    "target": "སྲིན་པོ འི་ སྐད་ ར་ ལ་ ར་ ལ་ རི་ ལི་ རི་ ལི་ ལ་ སོགས་པ་ སེར་ སྤྲིན་ གྱི་ འབྲུག་སྒྲ་ ལྟ་བུ་ དང་ །"
  },
  {
    "source": "ལྷ་མ་ཡིན་གྱི་སྐད་ཞི་བའི་འབྲུག་སྒྲ་ལྟ་བུ་དང་།",
    "target": "ལྷ་མ་ཡིན་ གྱི་ སྐད་ ཞི་བ འི་ འབྲུག་སྒྲ་ ལྟ་བུ་ དང་ །"
  },
  {
    "source": "དམྱལ་བའི་སྐད་ཚ་གྲང་གི་སྡུག་བསྔལ་སྨྲེ་སྔགས་འདོན་པ་དང་།",
    "target": "དམྱལ་བ འི་ སྐད་ ཚ་གྲང་ གི་ སྡུག་བསྔལ་ སྨྲེ་སྔགས་ འདོན་པ་ དང་ །"
  },
  {
    "source": "ཡི་དྭགས་བཀྲེས་སྐོམ་གྱི་འཁུན་སྒྲ་དང་།",
    "target": "ཡི་དྭགས་ བཀྲེས་སྐོམ་ གྱི་ འཁུན་སྒྲ་ དང་ །"
  },
  {
    "source": "དུད་འགྲོའི་མྱ་ངན་གྱི་བཤུག་སྒྲ་དང་།",
    "target": "དུད་འགྲོ འི་ མྱ་ངན་ གྱི་ བཤུག་ སྒྲ་ དང་ །"
  },
  {
    "source": "མི་སྐྱེ་རྒ་ན་འཆིའི་རང་སྒྲ་དང་།",
    "target": "མི་ སྐྱེ་རྒ་ན་འཆི འི་ རང་ སྒྲ་ དང་ །"
  },
  {
    "source": "གཞན་༼༦༧༽ཡང་སྐད་ཀྱི་རྣམ་པ་ཤེས་ཚད་བརྗོད་དོ།།",
    "target": "གཞན་ ༼ ༦༧ ༽ ཡང་ སྐད་ ཀྱི་ རྣམ་པ་ ཤེས་ ཚད་ བརྗོད་ དོ ། །"
  },
  {
    "source": "རྟ་དང་།",
    "target": "རྟ་ དང་ །"
  },
  {
    "source": "གླང་དང་།",
    "target": "གླང་ དང་ །"
  },
  {
    "source": "ར་ལུག་དང་།",
    "target": "ར་ལུག་ དང་ །"
  },
  {
    "source": "བོང་བུ་དང་།",
    "target": "བོང་བུ་ དང་ །"
  },
  {
    "source": "ཅེ་སྤྱང་དང་།",
    "target": "ཅེ་སྤྱང་ དང་ །"
  },
  {
    "source": "སྟག་གཟིག་དང་།",
    "target": "སྟག་ གཟིག་ དང་ །"
  },
  {
    "source": "དུར་བྱ་དང་།",
    "target": "དུར་བྱ་ དང་ །"
  },
  {
    "source": "འུག་པ་དང་།",
    "target": "འུག་པ་ དང་ །"
  },
  {
    "source": "བྱ་རོག་དང་།",
    "target": "བྱ་རོག་ དང་ །"
  },
  {
    "source": "སྐྱེ་ཀ་དང་།",
    "target": "སྐྱེ་ཀ་ དང་ །"
  },
  {
    "source": "ཁྱི་དང་།",
    "target": "ཁྱི་ དང་ །"
  },
  {
    "source": "ཝའི་སྐད་ལ་སོགས་པ་བརྗོད་པའི་བར་དུ་ཕཊཿམང་པོ་བརྗོད་ཅིང་།",
    "target": "ཝ འི་ སྐད་ ལ་ སོགས་པ་ བརྗོད་པ འི་ བར་ དུ་ ཕཊཿ མང་པོ་ བརྗོད་ ཅིང་ །"
  },
  {
    "source": "ཧ་དང་ཧཱུྃ་དང་ཨོཾ་ལ་སོགས་པ་ཆོས་སུ་འགྱུར་བའི་སྒྲ་སྐད་དང་།",
    "target": "ཧ་ དང་ ཧཱུྃ་ དང་ ཨོཾ་ ལ་ སོགས་པ་ ཆོས་ སུ་ འགྱུར་བ འི་ སྒྲ་སྐད་ དང་ །"
  },
  {
    "source": "ཆོས་འཆད་པའི་སྐད་ཀྱིས་མཐའ་བསྡུས་ནས།",
    "target": "ཆོས་ འཆད་པ འི་ སྐད་ ཀྱིས་ མཐའ་ བསྡུས་ ནས །"
  },
  {
    "source": "མཚན་མོ་གང་ཡང་མི་བརྗོད་པའི་ངང་ལ་ཉལ་བས་ངག་གི་རུ་ཤན་ཕྱེད་དོ།།",
    "target": "མཚན་མོ་ གང་ ཡང་ མི་ བརྗོད་པ འི་ ངང་ ལ་ ཉལ་བ ས་ ངག་ གི་ རུ་ ཤན་ ཕྱེད་ དོ ། །"
  },
  {
    "source": "དེ་ཡང་སཾ་སྐྲྀ་ཏའི་སྐད་རང་རྡོལ་བ་དང་།",
    "target": "དེ་ ཡང་ སཾ་སྐྲྀ་ཏ འི་ སྐད་ རང་ རྡོལ་བ་ དང་ །"
  },
  {
    "source": "སྔར་མེ་ཤེས་པའི་ཆོས་མང་པོ་རང་རྡོལ་བ་དང་།",
    "target": "སྔ ར་ མེ་ ཤེས་པ འི་ ཆོས་ མང་པོ་ རང་ རྡོལ་བ་ དང་ །"
  },
  {
    "source": "དབྱངས་སྙན་པོ་ལ་སོགས་པ་འབྱུང་ཞིང་།།",
    "target": "དབྱངས་ སྙན་པོ་ ལ་ སོགས་པ་ འབྱུང་ ཞིང་ ། །"
  },
  {
    "source": "ངག་སྨྲ་སྙིང་མི་འདོད་པ་དང་།",
    "target": "ངག་ སྨྲ་ སྙིང་ མི་ འདོད་པ་ དང་ །"
  },
  {
    "source": "མཆོག་ཏུ་བདེ་བ་དང་བརྗོད་དུ་མེད་པའི་དོན་ལ་སོགས་པ་འོང་ངོ་།།",
    "target": "མཆོག་ ཏུ་ བདེ་བ་ དང་ བརྗོད་ དུ་ མེད་པ འི་ དོན་ ལ་ སོགས་པ་ འོང་ ངོ་ ། །"
  },
  {
    "source": "མ་བྱུང་གི་བར་ལ་བསྐྱར་རོ།།",
    "target": "མ་ བྱུང་ གི་ བར་ ལ་ བསྐྱར་ རོ ། །"
  },
  {
    "source": "དགོས་པ་ནི།",
    "target": "དགོས་པ་ ནི །"
  },
  {
    "source": "ངག་གི་བར་ཆད་ཞི་བ་དང་།",
    "target": "ངག་ གི་ བར་ཆད་ ཞི་བ་ དང་ །"
  },
  {
    "source": "སྡིག་སྒྲིབ་འདག་པ་དང་།",
    "target": "སྡིག་ སྒྲིབ་ འདག་པ་ དང་ །"
  },
  {
    "source": "ལོངས་སྐུར་གྲོལ་བ་དང་།",
    "target": "ལོངས་སྐུ ར་ གྲོལ་བ་ དང་ །"
  },
  {
    "source": "གསུང་རྡོ་རྗེའི་ངོ་བོ་དང་དབྱེར་མེད་པའོ།།",
    "target": "གསུང་ རྡོ་རྗེ འི་ ངོ་བོ་ དང་ དབྱེར་ མེད་པ འོ ། །"
  },
  {
    "source": "དེ་ནས་སེམས་ཀྱི་སྤྱོད་པ་ནི་རང་གི་དྲན་བསམ་སྣ་ཚོགས་སུ་སྤྲོས་པ་ཐམས་ཅད་བླ་མའི་ཐུགས་སུ་དྲན་པས།",
    "target": "དེ་ ནས་ སེམས་ ཀྱི་ སྤྱོད་པ་ ནི་ རང་ གི་ དྲན་ བསམ་ སྣ་ཚོགས་ སུ་ སྤྲོས་པ་ ཐམས་ཅད་ བླ་མ འི་ ཐུགས་ སུ་ དྲན་པ ས །"
  },
  {
    "source": "འགྲོ་དྲུག་སོ་སོའི་བདེ་སྡུག་འཁོར་འདས་ཀྱི་རང་བཞིན་ཆོས་དང་ཆོས་མ་ཡིན་པ་དྲན་ཚད་སྤྲོ་ཞིང་།",
    "target": "འགྲོ་ དྲུག་ སོ་སོ འི་ བདེ་ སྡུག་ འཁོར་འདས་ ཀྱི་ རང་བཞིན་ ཆོས་ དང་ ཆོས་ མ་ ཡིན་པ་ དྲན་ ཚད་ སྤྲོ་ ཞིང་ །"
  },
  {
    "source": "སེམས་ནམ་མཁའི་དཀྱིལ་དུ་འཕངས་པ་དང་།",
    "target": "སེམས་ ནམ་ མཁ འི་ དཀྱིལ་ དུ་ འཕངས་པ་ དང་ །"
  },
  {
    "source": "རྒྱ་མཚོའི་གཏིང་དུ་འཕངས་པ་དང་།",
    "target": "རྒྱ་མཚོ འི་ གཏིང་ དུ་ འཕངས་པ་ དང་ །"
  },
  {
    "source": "རི་བྲག་གི་ནང་དུ་ཟང་ཐལ་དུ་འཕངས་པ་དང་།",
    "target": "རི་ བྲག་ གི་ ནང་ དུ་ ཟང་ ཐལ་ དུ་ འཕངས་པ་ དང་ །"
  },
  {
    "source": "དགའ་བ་དང་མི་དགའ་བ་དང་བདེ་བ་དང་སྡུག་བསྔལ་བ་དང་།",
    "target": "དགའ་བ་ དང་ མི་ དགའ་བ་ དང་ བདེ་བ་ དང་ སྡུག་ བསྔལ་བ་ དང་ །"
  },
  {
    "source": "སྐྱེ་ཤི་བཀྲེས་སྐོམ་ལ་སོགས་པ་དང་།",
    "target": "སྐྱེ་ ཤི་ བཀྲེས་སྐོམ་ ལ་ སོགས་པ་ དང་ །"
  },
  {
    "source": "སྔར་ཕྱིན་མྱོང་བ་དང་མ་མྱོང་བའི་ཡུལ་དུ་འགྲོ་བ་དང་།",
    "target": "སྔ ར་ ཕྱིན་ མྱོང་བ་ དང་ མ་ མྱོང་བ འི་ ཡུལ་ དུ་ འགྲོ་བ་ དང་ །"
  },
  {
    "source": "འགྲོ་དྲུག་སོ་སོའི་གནས་སུ་འཕངས་པ་དང་།",
    "target": "འགྲོ་ དྲུག་ སོ་སོ འི་ གནས་ སུ་ འཕངས་པ་ དང་ །"
  },
  {
    "source": "ནམ་མཁའ་དང་ས་གཞི་ཐམས་ཅད་དམྱལ་བ་དང་ཡི་དྭགས་དང་དུད་འགྲོ་དང་མི་དང་ལྷ་དང་ལྷ་མ་ཡིན་དང་།",
    "target": "ནམ་མཁའ་ དང་ ས་གཞི་ ཐམས་ཅད་ དམྱལ་བ་ དང་ ཡི་དྭགས་ དང་ དུད་འགྲོ་ དང་ མི་ དང་ ལྷ་ དང་ ལྷ་མ་ཡིན་ དང་ །"
  },
  {
    "source": "སངས་རྒྱས་དང་བྱང་ཆུབ་སེམས་དཔའ་༼༦༨༽དང་ཉན་རང་དང་མཆོད་རྟེན་དང་ལྷ་ཁང་དང་སྐྱེད་མོས་ཚལ་དང་དག་པའི་ཞིང་གིས་གང་བར་མོས་པ་བྱ་ཞིང་།",
    "target": "སངས་རྒྱས་ དང་ བྱང་ཆུབ་སེམས་དཔའ་ ༼ ༦༨ ༽ དང་ ཉན་རང་ དང་ མཆོད་རྟེན་ དང་ ལྷ་ཁང་ དང་ སྐྱེད་མོས་ཚལ་ དང་ དག་པ འི་ ཞིང་ གིས་ གང་བ ར་ མོས་པ་ བྱ་ ཞིང་ །"
  },
  {
    "source": "རང་གི་དགྲ་དང་གཉན་དང་བར་མས་གང་བར་བསམ་ལ།",
    "target": "རང་ གི་ དགྲ་ དང་ གཉན་ དང་ བར་མ ས་ གང་བ ར་ བསམ་ ལ །"
  },
  {
    "source": "ཆགས་སྡང་དུ་སྤྲོ་ཞིང་རྗེས་མེད་དུ་རྩལ་སྦྱོང་ངོ་།།",
    "target": "ཆགས་སྡང་ དུ་ སྤྲོ་ ཞིང་ རྗེས་ མེད་ དུ་ རྩལ་ སྦྱོང་ ངོ་ ། །"
  },
  {
    "source": "རྗེས་ལ་ཆོས་ཀྱི་ཚིག་དོན་ལ་བློ་བཞག་སྟེ།",
    "target": "རྗེས་ ལ་ ཆོས་ ཀྱི་ ཚིག་དོན་ ལ་ བློ་ བཞག་ སྟེ །"
  },
  {
    "source": "ལྟ་སྒོམ་སྤྱོད་འབྲས་ལ་གནས་པར་བྱའོ།།",
    "target": "ལྟ་ སྒོམ་ སྤྱོད་ འབྲས་ ལ་ གནས་པ ར་ བྱ འོ ། །"
  },
  {
    "source": "རྟགས་ནི་སེམས་གསལ་བ་དང་ཡང་བ་དང་འཁྲུལ་རྟོག་འགག་པ་དང་བྲོད་པ་དང་བདེ་གསལ་མི་རྟོག་པའི་ཏིང་ངེ་འཛིན་སྐྱེ་བ་དང་།",
    "target": "རྟགས་ ནི་ སེམས་ གསལ་བ་ དང་ ཡང་བ་ དང་ འཁྲུལ་ རྟོག་ འགག་པ་ དང་ བྲོད་པ་ དང་ བདེ་གསལ་ མི་ རྟོག་པ འི་ ཏིང་ངེ་འཛིན་ སྐྱེ་བ་ དང་ །"
  },
  {
    "source": "ཡེ་གྲོལ་ནམ་མཁའ་ལྟ་བུའི་རྟོགས་པ་ཁོང་ནས་འཆར་རོ།།",
    "target": "ཡེ་གྲོལ་ ནམ་མཁའ་ ལྟ་བུ འི་ རྟོགས་པ་ ཁོང་ ནས་ འཆར་ རོ ། །"
  },
  {
    "source": "དེ་ལྟར་མ་བྱུང་བར་དུ་བསྐྱར་རོ།།",
    "target": "དེ་ ལྟ ར་ མ་ བྱུང་བ ར་ དུ་ བསྐྱར་ རོ ། །"
  },
  {
    "source": "དགོས་པ་ནི་སེམས་ཀྱི་བར་ཆད་ཞི་བ་དང་།",
    "target": "དགོས་པ་ ནི་ སེམས་ ཀྱི་ བར་ཆད་ ཞི་བ་ དང་ །"
  },
  {
    "source": "སྡིག་པ་འདག་པ་དང་།",
    "target": "སྡིག་པ་ འདག་པ་ དང་ །"
  },
  {
    "source": "ཆོས་སྐུར་གྲོལ་བ་དང་།",
    "target": "ཆོས་ སྐུར་ གྲོལ་བ་ དང་ །"
  },
  {
    "source": "ཐུགས་རྡོ་རྗེའི་ངོ་བོར་སངས་རྒྱས་པའོ།།",
    "target": "ཐུགས་ རྡོ་རྗེ འི་ ངོ་བོ ར་ སངས་ རྒྱས་པ འོ ། །"
  },
  {
    "source": "དེ་ལྟར་སྔོན་འགྲོ་གསུམ་པོ་བྱེད་དུས་བླ་མས་རང་གི་གནས་སུ་ཆོས་ཉིད་མངོན་སུམ་གྱི་དོན་སྒོམ་ཞིང་།",
    "target": "དེ་ ལྟ ར་ སྔོན་ འགྲོ་ གསུམ་པོ་ བྱེད་ དུས་ བླ་མ ས་ རང་ གི་ གནས་ སུ་ ཆོས་ཉིད་ མངོན་སུམ་ གྱི་ དོན་ སྒོམ་ ཞིང་ །"
  },
  {
    "source": "སློབ་མ་རྣམས་འདུ་སླ་བའི་རི་ཟུར་དུ་སོང་ལ་རུ་ཤན་ཕྱེད་པའི་རྟགས་རྣམས་བྱུང་ངམ་ཞེས་སོ་སོར་དྲིས་ལ།",
    "target": "སློབ་མ་ རྣམས་ འདུ་ སླ་བ འི་ རི་ཟུར་ དུ་ སོང་ ལ་ རུ་ ཤན་ ཕྱེད་པ འི་ རྟགས་ རྣམས་ བྱུང་ ངམ་ ཞེས་ སོ་སོ ར་ དྲིས་ ལ །"
  },
  {
    "source": "མ་བྱང་ན་བསྐྱར་དུ་གཞུག་ཅིང་།",
    "target": "མ་ བྱང་ ན་ བསྐྱར་ དུ་ གཞུག་ ཅིང་ །"
  },
  {
    "source": "ཉིན་དུས་ལུས་ངག་ཡིད་གསུམ་གྱི་སྤྱོད་པ་དྲིལ་ནས་ཉམས་སུ་བླང་ཞིང་།",
    "target": "ཉིན་ དུས་ ལུས་ངག་ ཡིད་ གསུམ་ གྱི་ སྤྱོད་པ་ དྲིལ་ ནས་ ཉམས་ སུ་ བླང་ ཞིང་ །"
  },
  {
    "source": "མཚན་མོ་རྣལ་དུ་ཕབ་ལ་བརྩོན་པས་ཉམས་སུ་བླངས་པས་ཉི་མ་གསུམ་ལས་རྟགས་བྱུང་ན་དབང་པོ་ཡང་རབ།",
    "target": "མཚན་མོ་ རྣལ་ དུ་ ཕབ་ ལ་ བརྩོན་པ ས་ ཉམས་ སུ་ བླངས་པ ས་ ཉི་མ་ གསུམ་ ལས་ རྟགས་ བྱུང་ ན་ དབང་པོ་ ཡང་ རབ །"
  },
  {
    "source": "ལྔ་ལས་བྱུང་ན་འབྲིང་།",
    "target": "ལྔ་ ལས་ བྱུང་ ན་ འབྲིང་ །"
  },
  {
    "source": "བདུན་ཕན་ཆད་ནི་ཐ་མ་སྟེ།",
    "target": "བདུན་ ཕན་ཆད་ ནི་ ཐ་མ་ སྟེ །"
  },
  {
    "source": "དེ་དག་གི་དུས་སུ་ནམ་མཁའ་དྭངས་ཤིང་འཇའ་འོད་དང་བཅས་བྱུང་ན་འབྱོངས་པས་སྡིག་སྒྲིབ་ཟད་པ་ཡིན་ལ།",
    "target": "དེ་ དག་ གི་ དུས་ སུ་ ནམ་མཁའ་ དྭངས་ ཤིང་ འཇའ་འོད་ དང་ བཅས་ བྱུང་ ན་ འབྱོངས་པ ས་ སྡིག་སྒྲིབ་ ཟད་པ་ ཡིན་ ལ །"
  },
  {
    "source": "གཞན་དུ་སྡིག་སྒྲིབ་ཤས་ཆེ་བས།",
    "target": "གཞན་ དུ་ སྡིག་སྒྲིབ་ ཤས་ ཆེ་བ ས །"
  },
  {
    "source": "བསྐྱར་ལ་འབད་པར་བྱའོ།།",
    "target": "བསྐྱར་ ལ་ འབད་པ ར་ བྱ འོ ། །"
  },
  {
    "source": "དེས་ནི་འཁོར་འདས་རུ་ཤན་ཕྱེད་ནས་སླར་མི་ལྡོག་པའི་དགོས་པ་ཡོད་དོ།།",
    "target": "དེ ས་ ནི་ འཁོར་འདས་ རུ་ ཤན་ ཕྱེད་ ནས་ སླ ར་ མི་ ལྡོག་པ འི་ དགོས་པ་ ཡོད་ དོ ། །"
  },
  {
    "source": "དེ་དག་གིས་སློབ་མ་སྟ་གོན་དུ་བྱ་བའི་རིམ་པ་བཤད་ཟིན་ཏོ།།",
    "target": "དེ་ དག་ གིས་ སློབ་མ་ སྟ་གོན་ དུ་ བྱ་བ འི་ རིམ་པ་ བཤད་ ཟིན་ ཏོ ། །"
  },
  {
    "source": "དོན་གཉིས་པ་དབང་བསྐུར་བ་དངོས་ལ་གསུམ་སྟེ།",
    "target": "དོན་ གཉིས་པ་ དབང་ བསྐུར་བ་ དངོས་ ལ་ གསུམ་ སྟེ །"
  },
  {
    "source": "སྔོན་འགྲོ་སྟ་གོན་བྱ་བ།",
    "target": "སྔོན་ འགྲོ་ སྟ་གོན་ བྱ་བ །"
  },
  {
    "source": "དངོས་གཞི་དབང་བསྐུར་བ།",
    "target": "དངོས་གཞི་ དབང་ བསྐུར་བ །"
  },
  {
    "source": "རྗེས་གཟེངས་༼༦༩༽བསྟོད་པའོ།།",
    "target": "རྗེས་ གཟེངས་ ༼ ༦༩ ༽ བསྟོད་པ འོ ། །"
  },
  {
    "source": "དང་པོ་ནི།",
    "target": "དང་པོ་ ནི །"
  },
  {
    "source": "བླ་མས་གནས་དེར་དྲིའི་མཎྜལ་ཟླུམ་པོ་ལྟེ་བ་མུ་ཁྱུད་དང་བཅས་པའི་བར་ཁྱམས་འོད་ཟླུམ་བཞིས་བརྒྱན་པ་ལ།",
    "target": "བླ་མ ས་ གནས་ དེ ར་ དྲི འི་ མཎྜལ་ ཟླུམ་པོ་ ལྟེ་བ་ མུ་ཁྱུད་ དང་ བཅས་པ འི་ བར་ ཁྱམས་ འོད་ ཟླུམ་ བཞི ས་ བརྒྱན་པ་ ལ །"
  },
  {
    "source": "མེ་ཏོག་གི་ཚོམ་བུ་ལྔ་ཚན་ལྔ་བཀོད་ལ་མཐའ་བསྐོར་དུ་ཕྱི་ནང་གི་མཆོད་པ་དང་།",
    "target": "མེ་ཏོག་ གི་ ཚོམ་བུ་ ལྔ་ ཚན་ ལྔ་ བཀོད་ ལ་ མཐའ་ བསྐོར་ དུ་ ཕྱི་ནང་ གི་ མཆོད་པ་ དང་ །"
  },
  {
    "source": "འབྱོར་ན་དྲི་དང་སྤོས་དང་།",
    "target": "འབྱོར་ ན་ དྲི་ དང་ སྤོས་ དང་ །"
  },
  {
    "source": "སྨན་དང་རིན་པོ་ཆེ་དང་འབྲས་བུའི་མཎྜལ་ལྔ་ཚན་ལྔ་ཡང་བཤམ་མོ།།",
    "target": "སྨན་ དང་ རིན་པོ་ཆེ་ དང་ འབྲས་བུ འི་ མཎྜལ་ ལྔ་ ཚན་ ལྔ་ ཡང་ བཤམ་ མོ ། །"
  },
  {
    "source": "གཉིས་པ་ནི།",
    "target": "གཉིས་པ་ ནི །"
  },
  {
    "source": "དེ་ནས་ཉི་མ་རི་བོའི་རྩེ་ལ་ཤར་དུས་སུ།",
    "target": "དེ་ ནས་ ཉི་མ་ རི་བོ འི་ རྩེ་ ལ་ ཤར་ དུས་ སུ །"
  },
  {
    "source": "སློབ་མ་རྣམས་མེ་ཏོག་ཐོགས་ཏེ་འོང་བ་ལས།",
    "target": "སློབ་མ་ རྣམས་ མེ་ཏོག་ ཐོགས་ ཏེ་ འོང་བ་ ལས །"
  },
  {
    "source": "དྲི་བཟང་པོའི་ཆུས་ཁྲུས་བྱས་ཏེ།",
    "target": "དྲི་བཟང་པོ འི་ ཆུ ས་ ཁྲུས་ བྱས་ ཏེ །"
  },
  {
    "source": "བླ་མའི་མདུན་དུ་སྟོད་གཡོགས་ཕུད་ནས་ཐལ་མོར་སྙིང་ཁར་སྦྱར་ཏེ་འཁོད་པ་ལ།",
    "target": "བླ་མ འི་ མདུན་ དུ་ སྟོད་གཡོགས་ ཕུད་ ནས་ ཐལ་མོ ར་ སྙིང་ཁ ར་ སྦྱར་ ཏེ་ འཁོད་པ་ ལ །"
  },
  {
    "source": "བླ་མས་བུ་ཁྱོད་སུ་ཡིན་ཞེས་ལན་གསུམ་དྲིས་པའི་ལན་དུ།",
    "target": "བླ་མ ས་ བུ་ ཁྱོད་ སུ་ ཡིན་ ཞེས་ ལན་ གསུམ་ དྲིས་པ འི་ ལན་ དུ །"
  },
  {
    "source": "སློབ་མས་བདག་སྐལ་ལྡན་སེམས་ཀྱི་བུ་གཅིག་པུ་ལགས་ཤེས་གསུམ་བརྗོད་དུས།",
    "target": "སློབ་མ ས་ བདག་ སྐལ་ལྡན་ སེམས་ ཀྱི་ བུ་ གཅིག་པུ་ ལགས་ ཤེས་ གསུམ་ བརྗོད་ དུས །"
  },
  {
    "source": "བླ་མས་དེ་ལྟར་ཡིན་ཕན་ཆད་རང་བཞིན་རྫོགས་པ་ཆེན་པོའི་དཀྱིལ་འཁོར་བཟང་ཞིང་ཉམས་དགའ་བ་འདིར་ཞུགས་ཤིག།",
    "target": "བླ་མ ས་ དེ་ ལྟ ར་ ཡིན་ ཕན་ཆད་ རང་བཞིན་ རྫོགས་པ་ ཆེན་པོ འི་ དཀྱིལ་འཁོར་ བཟང་ ཞིང་ ཉམས་ དགའ་བ་ འདི ར་ ཞུགས་ ཤིག །"
  },
  {
    "source": "དེ་ཅིས་ཕྱིར་ཞེ་ན།",
    "target": "དེ་ ཅི ས་ ཕྱི ར་ ཞེ་ ན །"
  },
  {
    "source": "འཁོར་བ་འདི་ནི་སྙིང་པོ་མེད་ལ་རྟག་མི་ཐུབ་ཅིང་སྡུག་བསྔལ་བ་སྟེ།",
    "target": "འཁོར་བ་ འདི་ ནི་ སྙིང་པོ་ མེད་ ལ་ རྟག་ མི་ ཐུབ་ ཅིང་ སྡུག་བསྔལ་བ་ སྟེ །"
  },
  {
    "source": "དེ་ལས་ཐར་པའི་ཐབས་དམ་པ་ཡང་ཚེ་གཅིག་གིས་སངས་རྒྱས་པ་རང་བཞིན་རྫོགས་པ་ཆེན་པོ་ལས་གཞན་མེད་པས།",
    "target": "དེ་ ལས་ ཐར་པ འི་ ཐབས་ དམ་པ་ ཡང་ ཚེ་ གཅིག་ གིས་ སངས་རྒྱས་པ་ རང་བཞིན་ རྫོགས་པ་ ཆེན་པོ་ ལས་ གཞན་ མེད་པ ས །"
  },
  {
    "source": "དད་པ་ཆེན་པོ་བསྐྱེད་ལ་སེམས་ཅན་ཐམས་ཅད་ཀྱི་དོན་དུ་ཐོག་མར་བླ་མ་ལ་གསོལ་བ་གདབ་པར་བགྱི་བའི་རྗེས་ཟློས་མཛོད་ཅིག།",
    "target": "དད་པ་ ཆེན་པོ་ བསྐྱེད་ ལ་ སེམས་ཅན་ ཐམས་ཅད་ ཀྱི་ དོན་ དུ་ ཐོག་མ ར་ བླ་མ་ ལ་ གསོལ་བ་ གདབ་པ ར་ བགྱི་བ འི་ རྗེས་ ཟློས་ མཛོད་ ཅིག །"
  },
  {
    "source": "ཅེས་བརྗོད་ལ།",
    "target": "ཅེས་ བརྗོད་ ལ །"
  },
  {
    "source": "བླ་མ་རྡོ་རྗེ་འཛིན་པ་ཆེན་པོ་དགོངས་སུ་གསོལ་ལོ།།",
    "target": "བླ་མ་ རྡོ་རྗེ་ འཛིན་པ་ ཆེན་པོ་ དགོངས་ སུ་ གསོལ་ ལོ ། །"
  },
  {
    "source": "ཕྱོགས་བཅུའི་སངས་རྒྱས་དང་བྱང་ཆུབ་སེམས་དཔའ་རྣམས་ཏེ།",
    "target": "ཕྱོགས་ བཅུ འི་ སངས་རྒྱས་ དང་ བྱང་ཆུབ་སེམས་དཔའ་ རྣམས་ ཏེ །"
  },
  {
    "source": "རྡོ་རྗེ་དང་རིན་པོ་ཆེ་དང་པདྨ་དང་ལས་དང་བདེ་བར་གཤེགས་པའི་རིགས་ཐམས་ཅད་བདག་ལ་དགོངས་སུ་གསོལ་ལོ།།",
    "target": "རྡོ་རྗེ་ དང་ རིན་པོ་ཆེ་ དང་ པདྨ་ དང་ ལས་ དང་ བདེ་བར་གཤེགས་པ འི་ རིགས་ ཐམས་ཅད་ བདག་ ལ་ དགོངས་ སུ་ གསོལ་ ལོ ། །"
  },
  {
    "source": "བདག་མིང་འདི་ཞེས་བགྱི་བ་དུས་འདི་ནས་བཟུང་ནས།",
    "target": "བདག་ མིང་ འདི་ ཞེས་ བགྱི་བ་ དུས་ འདི་ ནས་ བཟུང་ ནས །"
  },
  {
    "source": "སྙིང་པོ་བྱང་ཆུབ་ལ་མཆིས་ཀྱི་བར་དུ།",
    "target": "སྙིང་པོ་ བྱང་ཆུབ་ ལ་ མཆིས་ ཀྱི་ བར་ དུ །"
  },
  {
    "source": "བླ་མ་རྡོ་རྗེ་འཛིན་པ་ཆེན་པོས།",
    "target": "བླ་མ་ རྡོ་རྗེ་ འཛིན་པ་ ཆེན་པོ ས །"
  },
  {
    "source": "བདག་གི་ལུས་བྱིན་གྱིས་བརླབ་ཏུ་གསོལ།།",
    "target": "བདག་ གི་ ལུས་ བྱིན་ གྱིས་ བརླབ་ ཏུ་ གསོལ ། །"
  },
  {
    "source": "༼༧༠༽བདག་གི་ངག་བྱིན་གྱིས་བརླབ་ཏུ་གསོལ།",
    "target": "༼ ༧༠ ༽ བདག་ གི་ ངག་ བྱིན་ གྱིས་ བརླབ་ ཏུ་ གསོལ །"
  },
  {
    "source": "བདག་གི་ཡིད་བྱིན་གྱིས་བརླབ་ཏུ་གསོལ།",
    "target": "བདག་ གི་ ཡིད་ བྱིན་ གྱིས་ བརླབ་ ཏུ་ གསོལ །"
  },
  {
    "source": "བདག་གི་སྣང་བ་བྱིན་གྱིས་བརླབ་ཏུ་གསོལ།",
    "target": "བདག་ གི་ སྣང་བ་ བྱིན་ གྱིས་ བརླབ་ ཏུ་ གསོལ །"
  },
  {
    "source": "སྨིན་པར་མཛད་དུ་གསོལ།",
    "target": "སྨིན་པ ར་ མཛད་ དུ་ གསོལ །"
  },
  {
    "source": "གྲོལ་བར་མཛད་དུ་གསོལ།",
    "target": "གྲོལ་བ ར་ མཛད་ དུ་ གསོལ །"
  },
  {
    "source": "གང་བར་མཛད་དུ་གསོལ།",
    "target": "གང་བ ར་ མཛད་ དུ་ གསོལ །"
  },
  {
    "source": "རྒྱས་པར་མཛད་དུ་གསོལ།",
    "target": "རྒྱས་པ ར་ མཛད་ དུ་ གསོལ །"
  },
  {
    "source": "ཆེར་འཕེལ་བར་མཛད་དུ་གསོལ།",
    "target": "ཆེ ར་ འཕེལ་བ ར་ མཛད་ དུ་ གསོལ །"
  },
  {
    "source": "ཞེས་པ་གསུམ་གྱིས་སྤྱིར་གསོལ་བ་བཏབ་ནས།",
    "target": "ཞེས་ པ་ གསུམ་ གྱིས་ སྤྱི ར་ གསོལ་བ་ བཏབ་ ནས །"
  },
  {
    "source": "བྱེ་བྲག་ཏུ་བརྒྱུད་པའི་བླ་མ་ལ་གསོལ་བ་གདབ་པ་ནི།",
    "target": "བྱེ་བྲག་ ཏུ་ བརྒྱུད་པ འི་ བླ་མ་ ལ་ གསོལ་བ་ གདབ་པ་ ནི །"
  },
  {
    "source": "ཀྱེ།།",
    "target": "ཀྱེ ། །"
  },
  {
    "source": "སངས་རྒྱས་ཀུན་གྱི་སྐུ་གསུང་ཐུགས་ལྡན་པ།།",
    "target": "སངས་རྒྱས་ ཀུན་ གྱི་ སྐུ་གསུང་ཐུགས་ ལྡན་པ ། །"
  },
  {
    "source": "ཟག་པ་རང་ཟད་དབྱིངས་ནས་སྐུར་གཤེགས་པའི།།",
    "target": "ཟག་པ་ རང་ ཟད་ དབྱིངས་ ནས་ སྐུར་ གཤེགས་ པ འི ། །"
  },
  {
    "source": "དྲི་མ་རང་དག་དབྱིངས་ནས་སྤྱན་གཟིགས་ནས།།",
    "target": "དྲི་མ་ རང་ དག་ དབྱིངས་ ནས་ སྤྱན་ གཟིགས་ ནས ། །"
  },
  {
    "source": "ཐུགས་རྗེ་ཆེན་པོས་འགྲོ་བའི་དོན་མཛད་པའི།།",
    "target": "ཐུགས་རྗེ་ ཆེན་པོ ས་ འགྲོ་བ འི་ དོན་ མཛད་ པ འི ། །"
  },
  {
    "source": "བདེ་གཤེགས་འཇིག་རྟེན་མཁྱེན་པའི་ཐུགས་མངའ་བ།།",
    "target": "བདེ་གཤེགས་ འཇིག་རྟེན་ མཁྱེན་པ འི་ ཐུགས་ མངའ་བ ། །"
  },
  {
    "source": "དགོངས་པ་ཉག་ཅིག་མི་གཡོ་དབྱེར་མེད་ཀྱང་།།",
    "target": "དགོངས་པ་ ཉག་ ཅིག་ མི་ གཡོ་ དབྱེར་མེད་ ཀྱང་ ། །"
  },
  {
    "source": "སྔོན་བཞུགས་དུར་ཁྲོད་གནས་ནས་རྗེས་དགོངས་ལ།།",
    "target": "སྔོན་ བཞུགས་ དུར་ཁྲོད་ གནས་ ནས་ རྗེས་ དགོངས་ ལ ། །"
  },
  {
    "source": "རང་བཞིན་མཛད་པ་གང་ཡང་མི་མངའ་ཡང་།།",
    "target": "རང་བཞིན་ མཛད་པ་ གང་ ཡང་ མི་ མངའ་ ཡང་ ། །"
  },
  {
    "source": "བདག་བློ་མོས་པའི་དོན་ཕྱིར་འདིར་གཤེགས་ཤིག",
    "target": "བདག་ བློ་མོས་པ འི་ དོན་ ཕྱི ར་ འདི ར་ གཤེགས་ ཤིག"
  },
  {
    "source": "།",
    "target": "།"
  },
  {
    "source": "ཨེ་མ་ཧོ།།",
    "target": "ཨེ་མ་ཧོ ། །"
  },
  {
    "source": "བྱིན་རླབས་རྩ་བ་བླ་མ་བརྒྱུད་པ་ཡི།།",
    "target": "བྱིན་རླབས་ རྩ་བ་ བླ་མ་ བརྒྱུད་པ་ ཡི ། །"
  },
  {
    "source": "རིམ་པ་ཉིད་ཀྱིས་རིམ་ནས་རིམ་བརྒྱུད་པའི།།",
    "target": "རིམ་པ་ ཉིད་ ཀྱིས་ རིམ་ ནས་ རིམ་ བརྒྱུད་ པ འི ། །"
  },
  {
    "source": "བདག་ཉིད་ཆེན་པོ་རོ་ལངས་བདེ་བ་དང་།།",
    "target": "བདག་ཉིད་ ཆེན་པོ་ རོ་ ལངས་ བདེ་བ་ དང་ ། །"
  },
  {
    "source": "མཁྱེན་པའི་ཐུགས་མངའ་རབ་ཏུ་སྦྱངས་དང་ལྡན།།",
    "target": "མཁྱེན་པ འི་ ཐུགས་ མངའ་ རབ་ ཏུ་ སྦྱངས་ དང་ ལྡན ། །"
  },
  {
    "source": "མཁྱེན་རབ་སྤྲུལ་པ་མཉྫུ་མི་ཏྲ་དང་།།",
    "target": "མཁྱེན་རབ་ སྤྲུལ་པ་ མཉྫུ་ མི་ ཏྲ་ དང་ ། །"
  },
  {
    "source": "ཐུགས་རྗེ་ཆེན་པོས་འགྲོ་བའི་སྡུག་བསྔལ་གཅོད།།",
    "target": "ཐུགས་རྗེ་ ཆེན་པོ ས་ འགྲོ་བ འི་ སྡུག་བསྔལ་ གཅོད ། །"
  },
  {
    "source": "རྗེ་བཙུན་ཐུགས་རྗེ་ཆེ་ལྡན་སིང་ཧ་དང་།།",
    "target": "རྗེ་བཙུན་ ཐུགས་རྗེ་ ཆེ་ ལྡན་ སིང་ ཧ་ དང་ ། །"
  },
  {
    "source": "མཁས་པ་ཐེག་པ་ཡོངས་ཀྱི་སྒྲོ་འདོགས་རབ་ཆོད་པའི།།",
    "target": "མཁས་པ་ ཐེག་པ་ ཡོངས་ ཀྱི་ སྒྲོ་འདོགས་ རབ་ ཆོད་ པ འི ། །"
  },
  {
    "source": "འཇིག་རྟེན་མུན་པ་སེལ་མཛད་ཛྙཱ་ན་སཱུ་ཏྲ་དང་།།",
    "target": "འཇིག་རྟེན་ མུན་པ་ སེལ་ མཛད་ ཛྙཱ་ན་ སཱུ་ ཏྲ་ དང་ ། །"
  },
  {
    "source": "སྐྱེ་ཤི་ཀུན་བྲལ་ཚེ་ལ་དབང་ཐོབ་པའི།།",
    "target": "སྐྱེ་ ཤི་ ཀུན་ བྲལ་ ཚེ་ ལ་ དབང་ ཐོབ་པ འི ། །"
  },
  {
    "source": "མཁས་པ་ཆེན་པོ་བི་མ་མི་ཏྲ་དང་།།",
    "target": "མཁས་པ་ ཆེན་པོ་ བི་མ་ མི་ཏྲ་ དང་ ། །"
  },
  {
    "source": "རྟག་ཏུ་མཉམ་གཞག་རྗེས་ཐོབ་དབྱེར་མེད་པའི།།",
    "target": "རྟག་ ཏུ་ མཉམ་ གཞག་ རྗེས་ ཐོབ་ དབྱེར་མེད་ པ འི ། །"
  },
  {
    "source": "སེམས་ལ་དབང་ཐོབ་ཏིང་འཛིན་བཟང་པོ་དང་།།",
    "target": "སེམས་ ལ་ དབང་ ཐོབ་ ཏིང་འཛིན་ བཟང་པོ་ དང་ ། །"
  },
  {
    "source": "རང་རྒྱུད་འཁྲུལ་པ་བློ་ལ་མི་གནས་པའི།།",
    "target": "རང་རྒྱུད་ འཁྲུལ་པ་ བློ་ ལ་ མི་ གནས་ པ འི ། །"
  },
  {
    "source": "བདུད་རྩིའི་བཅུད་སྟོན་ལྡང་མ་ལྷུན་རྒྱལ་དང་།།",
    "target": "བདུད་རྩི འི་ བཅུད་ སྟོན་ ལྡང་ མ་ ལྷུན་ རྒྱལ་ དང་ ། །"
  },
  {
    "source": "༼༧༡༽མཁའ་འགྲོས་ལུང་བསྟན་རྗེས་སུ་བཟུང་བ་ཡི།།",
    "target": "༼ ༧༡ ༽ མཁའ་འགྲོ ས་ ལུང་ བསྟན་ རྗེས་ སུ་ བཟུང་བ་ ཡི ། །"
  },
  {
    "source": "གྲུབ་ཐོབ་ཆེན་པོ་སེང་གེ་དབང་ཕྱུག་དང་།།",
    "target": "གྲུབ་ཐོབ་ ཆེན་པོ་ སེང་གེ་ དབང་ཕྱུག་ དང་ ། །"
  },
  {
    "source": "རྒྱལ་སྲས་སྤྲུལ་པས་འགྲོ་བ་འདྲེན་མཛད་པའི།།",
    "target": "རྒྱལ་སྲས་ སྤྲུལ་པ ས་ འགྲོ་བ་ འདྲེན་ མཛད་ པ འི ། །"
  },
  {
    "source": "བླ་མ་རྗེ་བཙུན་སྤྲུལ་སྐུ་ཞང་སྟོན་དང་།།",
    "target": "བླ་མ་ རྗེ་བཙུན་ སྤྲུལ་སྐུ་ ཞང་སྟོན་ དང་ ། །"
  },
  {
    "source": "མཁྱེན་པའི་འོད་ཀྱིས་འགྲོ་བ་འདྲེན་མཛད་པའི།།",
    "target": "མཁྱེན་པ འི་ འོད་ ཀྱིས་ འགྲོ་བ་ འདྲེན་ མཛད་ པ འི ། །"
  },
  {
    "source": "མ་རིག་མུན་སེལ་མཁས་པ་ཉི་འབུམ་དང་།།",
    "target": "མ་རིག་ མུན་ སེལ་ མཁས་པ་ ཉི་ འབུམ་ དང་ ། །"
  },
  {
    "source": "བླ་མེད་རྫོགས་ཆེན་སྙིང་པོ་དར་མཛད་པའི།།",
    "target": "བླ་མེད་ རྫོགས་ཆེན་ སྙིང་པོ་ དར་ མཛད་ པ འི ། །"
  },
  {
    "source": "རིག་འཛིན་ཆེན་པོ་གུ་རུ་ཇོ་འབེར་དང་།།",
    "target": "རིག་འཛིན་ ཆེན་པོ་ གུ་རུ་ ཇོ་ འབེར་ དང་ ། །"
  },
  {
    "source": "བྱང་ཆུབ་སེམས་འབྱོངས་འགྲོ་བའི་དཔལ་གྱུར་པའི།།",
    "target": "བྱང་ཆུབ་སེམས་ འབྱོངས་ འགྲོ་བ འི་ དཔལ་ གྱུར་ པ འི ། །"
  },
  {
    "source": "འཁྲུལ་ཞིག་ཆེན་པོ་སེང་གེ་རྒྱབ་པ་དང་།།",
    "target": "འཁྲུལ་ ཞིག་ ཆེན་པོ་ སེང་གེ་ རྒྱབ་པ་ དང་ ། །"
  },
  {
    "source": "གསལ་སྟོང་དབྱེར་མེད་བདེ་ཆེན་དོན་རྟོགས་པའི།།",
    "target": "གསལ་སྟོང་དབྱེར་མེད་ བདེ་ཆེན་ དོན་ རྟོགས་པ འི ། །"
  },
  {
    "source": "ཟླ་བ་མུན་སེལ་སྦས་པའི་རྣལ་འབྱོར་དང་།།",
    "target": "ཟླ་བ་ མུན་ སེལ་ སྦས་པ འི་ རྣལ་འབྱོར་ དང་ ། །"
  },
  {
    "source": "དགོངས་པ་མི་གཡོ་ཆོས་ཉིད་འོད་གསལ་དང་།།",
    "target": "དགོངས་པ་ མི་ གཡོ་ ཆོས་ཉིད་ འོད་གསལ་ དང་ ། །"
  },
  {
    "source": "རིག་འཛིན་ཆེན་པོ་ཀུ་མ་རཱ་ཛ་དང་།།",
    "target": "རིག་འཛིན་ ཆེན་པོ་ ཀུ་ མ་ རཱ་ ཛ་ དང་ ། །"
  },
  {
    "source": "སྙིང་པོའི་དོན་མཐོང་འཁྲུལ་པ་རང་སར་ཞིག།",
    "target": "སྙིང་པོ འི་ དོན་ མཐོང་ འཁྲུལ་པ་ རང་ ས ར་ ཞིག །"
  },
  {
    "source": "ཀུན་མཁྱེན་ཀློང་ཆེན་རབ་འབྱམས་ཐུགས་རྗེ་ཅན།།",
    "target": "ཀུན་མཁྱེན་ ཀློང་ཆེན་ རབ་འབྱམས་ ཐུགས་རྗེ་ ཅན ། །"
  },
  {
    "source": "མཁས་པ་དགོངས་པ་མི་འགྱུར་གཡོ་མེད་རྣམས།།",
    "target": "མཁས་པ་ དགོངས་པ་ མི་ འགྱུར་ གཡོ་ མེད་ རྣམས ། །"
  },
  {
    "source": "འབྱུང་བ་རང་དེངས་ཟག་མེད་དབྱིངས་བཞུགས་ཀྱང་།།",
    "target": "འབྱུང་བ་ རང་ དེངས་ ཟག་མེད་ དབྱིངས་ བཞུགས་ ཀྱང་ ། །"
  },
  {
    "source": "སྔོན་གྱི་ཐུགས་རྗེ་ཆེན་པོ་ཉིད་གཡོས་ལ།།",
    "target": "སྔོན་ གྱི་ ཐུགས་རྗེ་ཆེན་པོ་ ཉིད་ གཡོས་ ལ ། །"
  },
  {
    "source": "ཐུགས་རྗེས་དགོངས་ཤིག་བདག་ལ་བྱིན་གྱིས་རློབས།།",
    "target": "ཐུགས་རྗེ ས་ དགོངས་ ཤིག་ བདག་ ལ་ བྱིན་ གྱིས་ རློབས ། །"
  },
  {
    "source": "ཨོཾ་ཨཱཿཧཱུྃ་གུ་རུ་སརྦ་སིདྡྷི་ཧཱུྃ།",
    "target": "ཨོཾ་ ཨཱཿ ཧཱུྃ་ གུ་ རུ་ སརྦ་ སིདྡྷི་ ཧཱུྃ །"
  },
  {
    "source": "ཨོཾ་ཨཱཿཧཱུྃ།",
    "target": "ཨོཾ་ ཨཱཿཧཱུྃ །"
  },
  {
    "source": "དམ་པ་སངས་རྒྱས་ཀུན་གྱི་ཞལ་མཐོང་བདུད་རྩིའི་བཅུད་ལྡན་པའི།།",
    "target": "དམ་པ་ སངས་རྒྱས་ ཀུན་ གྱི་ ཞལ་ མཐོང་ བདུད་རྩི འི་ བཅུད་ལྡན་ པ འི ། །"
  },
  {
    "source": "རོ་ལངས་བདེ་བ་ལྷ་ཡི་ལྷ་མཆོག་དམ་པ་ཉིད།།",
    "target": "རོ་ ལངས་ བདེ་བ་ ལྷ་ ཡི་ ལྷ་ མཆོག་ དམ་པ་ ཉིད ། །"
  },
  {
    "source": "སངས་རྒྱས་སྤྲུལ་པས་འགྲོ་བའི་གདུང་བ་སེལ་མཛད་པའི།།",
    "target": "སངས་རྒྱས་ སྤྲུལ་པ ས་ འགྲོ་བ འི་ གདུང་ བ་ སེལ་ མཛད་པ འི ། །"
  },
  {
    "source": "དམ་པ་བདུད་རྩིའི་བདེ་བ་ཉིད་ལ་ཕྱག་འཚལ་བསྟོད།།",
    "target": "དམ་པ་ བདུད་རྩི འི་ བདེ་བ་ ཉིད་ ལ་ ཕྱག་ འཚལ་ བསྟོད ། །"
  },
  {
    "source": "དེ་ཡི་རྗེས་འཛིན་འཇམ་དཔལ་སྐུ་སྤྲུལ་པའི།།",
    "target": "དེ་ ཡི་ རྗེས་འཛིན་ འཇམ་དཔལ་ སྐུ་ སྤྲུལ་པ འི ། །"
  },
  {
    "source": "ཉོན་མོངས་རང་དག་མཁྱེན་པའི་ཐུགས་དང་ལྡན།།",
    "target": "ཉོན་མོངས་ རང་ དག་ མཁྱེན་པ འི་ ཐུགས་ དང་ ལྡན ། །"
  },
  {
    "source": "གསུང་གི་འོད་ཀྱིས་འགྲོ་བའི་སྡུག་བསྔལ་གཅོད།།",
    "target": "གསུང་ གི་ འོད་ ཀྱིས་ འགྲོ་བ འི་ སྡུག་བསྔལ་ གཅོད ། །"
  },
  {
    "source": "དམ་པ་ཡིད་བཞིན་མྱུ་གུ་དེ་ལ་ཕྱག་འཚལ་བསྟོད།།",
    "target": "དམ་པ་ ཡིད་ བཞིན་ མྱུ་གུ་ དེ་ ལ་ ཕྱག་ འཚལ་ བསྟོད ། །"
  },
  {
    "source": "དེ་ཡི་གདུང་འཛིན་མཁས་པ་སྡེ་སྣོད་རྣམས་ཀྱི་བདག།",
    "target": "དེ་ ཡི་ གདུང་ འཛིན་ མཁས་པ་ སྡེ་སྣོད་ རྣམས་ ཀྱི་ བདག །"
  },
  {
    "source": "ཐུགས་རྗེ་ཆེན་པོའི་སྤྲུལ་པ་འཛམ་༼༧༢༽གླིང་ཀུན་གྱི་རྒྱན།།",
    "target": "ཐུགས་རྗེ་ཆེན་པོ འི་ སྤྲུལ་པ་ འཛམ་ ༼ ༧༢ ༽ གླིང་ ཀུན་ གྱི་ རྒྱན ། །"
  },
  {
    "source": "དྲི་མེད་གསུང་མངའ་འགྲོ་བའི་ངལ་གསོའི་གནས།།",
    "target": "དྲི་མེད་ གསུང་ མངའ་ འགྲོ་བ འི་ ངལ་གསོ འི་ གནས ། །"
  },
  {
    "source": "དམ་པ་ཤེས་རབ་མྱུ་གུ་དེ་ལ་ཕྱག་འཚལ་བསྟོད།།",
    "target": "དམ་པ་ ཤེས་རབ་ མྱུ་གུ་ དེ་ ལ་ ཕྱག་ འཚལ་ བསྟོད ། །"
  },
  {
    "source": "དེ་ཡི་རྗེས་འཛིན་མཁས་པ་འཇིག་རྟེན་གསུམ་གྱི་མགོན།།",
    "target": "དེ་ ཡི་ རྗེས་འཛིན་ མཁས་པ་ འཇིག་རྟེན་ གསུམ་ གྱི་ མགོན ། །"
  },
  {
    "source": "རྡོ་རྗེ་སེམས་དཔའི་སྤྲུལ་པས་བདག་བློའི་འཆིང་གཅོད་པ།།",
    "target": "རྡོ་རྗེ་ སེམས་ དཔ འི་ སྤྲུལ་པ ས་ བདག་ བློ འི་ འཆིང་ གཅོད་པ ། །"
  },
  {
    "source": "ཚངས་པའི་གསུང་མངའ་འགྲོ་བ་ཀུན་ཡིད་འཕྲོག།",
    "target": "ཚངས་པ འི་ གསུང་ མངའ་ འགྲོ་བ་ ཀུན་ ཡིད་ འཕྲོག །"
  },
  {
    "source": "དམ་པ་བདེ་བའི་མྱུ་གུ་མགོན་ལ་ཕྱག་འཚལ་བསྟོད།།",
    "target": "དམ་པ་ བདེ་བ འི་ མྱུ་གུ་ མགོན་ ལ་ ཕྱག་ འཚལ་ བསྟོད ། །"
  },
  {
    "source": "དེ་ཡི་གདུང་འཛིན་མཁས་བློར་སྐྱེ་བ་གྲངས་མང་སྦྱངས།།",
    "target": "དེ་ ཡི་ གདུང་ འཛིན་ མཁས་ བློ ར་ སྐྱེ་བ་ གྲངས་ མང་ སྦྱངས ། །"
  },
  {
    "source": "མཁྱེན་རབ་མཆོག་གྱུར་སྡེ་སྣོད་ཀུན་ལ་རྨོངས་པ་མེད།།",
    "target": "མཁྱེན་རབ་ མཆོག་གྱུར་ སྡེ་སྣོད་ ཀུན་ ལ་ རྨོངས་པ་ མེད ། །"
  },
  {
    "source": "སྐྱེ་ཤིའི་འཇིག་བྲལ་སྤྲུལ་པས་འགྲོ་བའི་དོན་མཛད་པའི།།",
    "target": "སྐྱེ་ ཤི འི་ འཇིག་ བྲལ་ སྤྲུལ་པ ས་ འགྲོ་བ འི་ དོན་ མཛད་ པ འི ། །"
  },
  {
    "source": "དམ་པ་བདེ་གསལ་མྱུ་གུ་མགོན་ལ་ཕྱག་འཚལ་བསྟོད།།",
    "target": "དམ་པ་ བདེ་གསལ་ མྱུ་གུ་ མགོན་ ལ་ ཕྱག་ འཚལ་ བསྟོད ། །"
  },
  {
    "source": "དེ་ཡི་རྗེས་འཛིན་རྣམ་དག་ཤ་ཡི་སྤྱན་མངའ་བ།།",
    "target": "དེ་ ཡི་ རྗེས་འཛིན་ རྣམ་དག་ ཤ་ ཡི་ སྤྱན་ མངའ་བ ། །"
  },
  {
    "source": "མི་རྟོག་བཟང་པོའི་ཏིང་འཛིན་ཐུགས་ཀྱི་གནད་བཀྲོལ་ནས།།",
    "target": "མི་ རྟོག་ བཟང་པོ འི་ ཏིང་འཛིན་ ཐུགས་ ཀྱི་ གནད་ བཀྲོལ་ ནས ། །"
  },
  {
    "source": "འཛམ་གླིང་འགྲོ་རྣམས་མ་ལུས་བསམ་པའི་རྒྱུད་མཁྱེན་པའི།།",
    "target": "འཛམ་གླིང་ འགྲོ་ རྣམས་ མ་ ལུས་ བསམ་པ འི་ རྒྱུད་ མཁྱེན་པ འི ། །"
  },
  {
    "source": "དམ་པ་རྟོག་མེད་མྱུ་གུ་མགོན་ལ་ཕྱག་འཚལ་བསྟོད།།",
    "target": "དམ་པ་ རྟོག་ མེད་ མྱུ་གུ་ མགོན་ ལ་ ཕྱག་ འཚལ་ བསྟོད ། །"
  },
  {
    "source": "དེ་ཡི་རྗེས་འཛིན་སྐལ་ལྡན་ཆོས་ཀྱི་མཛོད་མངའ་བ།།",
    "target": "དེ་ ཡི་ རྗེས་འཛིན་ སྐལ་ལྡན་ ཆོས་ ཀྱི་ མཛོད་ མངའ་བ ། །"
  },
  {
    "source": "རིན་ཆེན་གཏེར་བརྙེས་འགྲོ་བའི་མ་རིག་མུན་པ་སེལ།།",
    "target": "རིན་ཆེན་ གཏེར་ བརྙེས་ འགྲོ་བ འི་ མ་རིག་ མུན་པ་ སེལ ། །"
  },
  {
    "source": "བདེ་གཤེགས་བཀའ་དང་བླ་མའི་མན་ངག་སྙིང་པོ་འཛིན།།",
    "target": "བདེ་གཤེགས་ བཀའ་ དང་ བླ་མ འི་ མན་ངག་ སྙིང་པོ་ འཛིན ། །"
  },
  {
    "source": "དམ་པ་པདྨའི་མྱུ་གུ་མགོན་ལ་ཕྱག་འཚལ་བསྟོད།།",
    "target": "དམ་པ་ པདྨ འི་ མྱུ་གུ་ མགོན་ ལ་ ཕྱག་ འཚལ་ བསྟོད ། །"
  },
  {
    "source": "དེ་ཡི་རྗེས་འཛིན་གསང་སྔགས་ཀུན་གྱི་མཛོད་མངའ་བ།།",
    "target": "དེ་ ཡི་ རྗེས་འཛིན་ གསང་སྔགས་ ཀུན་ གྱི་ མཛོད་ མངའ་བ ། །"
  },
  {
    "source": "གྲུབ་པ་མཆོག་བརྙེས་སྣང་བྱེད་འོད་ཀྱི་ལུས་གྲུབ་ནས།།",
    "target": "གྲུབ་པ་ མཆོག་ བརྙེས་ སྣང་ བྱེད་ འོད་ ཀྱི་ ལུས་ གྲུབ་ ནས ། །"
  },
  {
    "source": "གདོད་མའི་ཟད་སར་ཐུགས་རྗེས་གཤེགས་པར་མཛད་པ་གང་།།",
    "target": "གདོད་ མ འི་ ཟད་ ས ར་ ཐུགས་རྗེ ས་ གཤེགས་པ ར་ མཛད་པ་ གང་ ། །"
  },
  {
    "source": "དམ་པ་ཡེ་ཤེས་མྱུ་གུ་མགོན་ལ་ཕྱག་འཚལ་བསྟོད།།",
    "target": "དམ་པ་ ཡེ་ཤེས་ མྱུ་གུ་ མགོན་ ལ་ ཕྱག་ འཚལ་ བསྟོད ། །"
  },
  {
    "source": "དེ་ཡི་རྗེས་འཛིན་རྗེ་བཙུན་འགྲོ་བ་རྣམས་ཀྱི་མགོན།།",
    "target": "དེ་ ཡི་ རྗེས་འཛིན་ རྗེ་བཙུན་ འགྲོ་བ་ རྣམས་ ཀྱི་ མགོན ། །"
  },
  {
    "source": "གསང་སྔགས་རྣམས་ལ་དབང་བསྐྱུར་ལུང་བསྟན་རྗེས་སུ་འཛིན།།",
    "target": "གསང་སྔགས་ རྣམས་ ལ་ དབང་ བསྐྱུར་ ལུང་ བསྟན་ རྗེས་ སུ་ འཛིན ། །"
  },
  {
    "source": "མ་རིག་མུན་སེལ་འོད་གསལ་མཆོག་ལ་མངའ་བརྙེས་པའི།།",
    "target": "མ་རིག་ མུན་ སེལ་ འོད་གསལ་ མཆོག་ ལ་ མངའ་ བརྙེས་ པ འི ། །"
  },
  {
    "source": "དམ་པ་རིན་ཆེན་མྱུ་གུ་མགོན་ལ་ཕྱག་འཚལ་བསྟོད།།",
    "target": "དམ་པ་ རིན་ཆེན་ མྱུ་གུ་ མགོན་ ལ་ ཕྱག་ འཚལ་ བསྟོད ། །"
  },
  {
    "source": "དེ་ཡི་རྗེས་འཛིན་འཁོར་བའི་སྐྱབས་གནས་དཔའ་བོ་ཉིད།།",
    "target": "དེ་ ཡི་ རྗེས་འཛིན་ འཁོར་བ འི་ སྐྱབས་ གནས་ དཔའ་བོ་ ཉིད ། །"
  },
  {
    "source": "འགྲོ་བ་རྣམས་༼༧༣༽ཀྱི་མགོན་པོ་དྲི་མ་མེད་པའི་དཔལ།།",
    "target": "འགྲོ་བ་ རྣམས་ ༼ ༧༣ ༽ ཀྱི་ མགོན་པོ་ དྲི་མ་ མེད་པ འི་ དཔལ ། །"
  },
  {
    "source": "ཡོན་ཏན་མཆོག་མངའ་མཁྱེན་རབ་རྒྱ་མཚོའི་ཕ་རོལ་སོན།།",
    "target": "ཡོན་ཏན་ མཆོག་ མངའ་ མཁྱེན་རབ་ རྒྱ་མཚོ འི་ ཕ་རོལ་ སོན ། །"
  },
  {
    "source": "དམ་པ་བློ་གསལ་མྱུ་གུ་མགོན་ལ་ཕྱག་འཚལ་བསྟོད།།",
    "target": "དམ་པ་ བློ་གསལ་ མྱུ་གུ་ མགོན་ ལ་ ཕྱག་ འཚལ་ བསྟོད ། །"
  },
  {
    "source": "དེ་ཡི་རྗེས་འཛིན་བསྟན་པའི་སྙིང་པོ་དར་མཛད་ཅིང་།།",
    "target": "དེ་ ཡི་ རྗེས་འཛིན་ བསྟན་པ འི་ སྙིང་པོ་ དར་ མཛད་ ཅིང་ ། །"
  },
  {
    "source": "ས་ཆེན་མཆོག་བརྙེས་རྒྱུད་དོན་ཀུན་ལ་དབང་འབྱོར་བ།།",
    "target": "ས་ ཆེན་ མཆོག་ བརྙེས་ རྒྱུད་ དོན་ ཀུན་ ལ་ དབང་ འབྱོར་བ ། །"
  },
  {
    "source": "ཡེ་ཤེས་མིག་གཅིག་ཀུན་ནས་གཟིགས་པའི་སྤྱན་དང་ལྡན།།",
    "target": "ཡེ་ཤེས་ མིག་ གཅིག་ ཀུན་ ནས་ གཟིགས་པ འི་ སྤྱན་ དང་ ལྡན ། །"
  },
  {
    "source": "དམ་པ་བློ་མཚོའི་མྱུ་གུ་མགོན་ལ་ཕྱག་འཚལ་བསྟོད།།",
    "target": "དམ་པ་ བློ་ མཚོ འི་ མྱུ་གུ་ མགོན་ ལ་ ཕྱག་ འཚལ་ བསྟོད ། །"
  },
  {
    "source": "དེ་ཡི་རྗེས་འཛིན་མ་རིག་མུན་པའི་དཔུང་འཇོམས་ཤིང་།།",
    "target": "དེ་ ཡི་ རྗེས་འཛིན་ མ་རིག་ མུན་པ འི་ དཔུང་ འཇོམས་ ཤིང་ ། །"
  },
  {
    "source": "ཡེ་ཤེས་འོད་ཟེར་བྱེ་བའི་ཚོགས་མངའ་མཐའ་ཡས་ཀྱིས།།",
    "target": "ཡེ་ཤེས་འོད་ ཟེར་ བྱེ་བ འི་ ཚོགས་ མངའ་ མཐའ་ཡས་ ཀྱིས ། །"
  },
  {
    "source": "འགྲོ་བའི་སྡུག་བསྔལ་རྒྱ་མཚོ་མ་ལུས་སྐེམ་མཛད་པ།།",
    "target": "འགྲོ་བ འི་ སྡུག་བསྔལ་ རྒྱ་མཚོ་ མ་ ལུས་ སྐེམ་ མཛད་པ ། །"
  },
  {
    "source": "དམ་པ་སྣང་བྱེད་མྱུ་གུ་མགོན་ལ་ཕྱག་འཚལ་བསྟོད།།",
    "target": "དམ་པ་ སྣང་ བྱེད་ མྱུ་གུ་ མགོན་ ལ་ ཕྱག་ འཚལ་ བསྟོད ། །"
  },
  {
    "source": "དེ་ཡི་རྗེས་འཛིན་ཐེག་པ་མཆོག་གི་བློ་གྲོས་ཅན།།",
    "target": "དེ་ ཡི་ རྗེས་འཛིན་ ཐེག་པ་ མཆོག་ གི་ བློ་གྲོས་ ཅན ། །"
  },
  {
    "source": "འཆིང་བའི་དྲྭ་བ་མ་ལུས་གཅོད་མཛད་རེ་བ་སྐོང་།།",
    "target": "འཆིང་བ འི་ དྲྭ་བ་ མ་ལུས་ གཅོད་ མཛད་ རེ་བ་ སྐོང་ ། །"
  },
  {
    "source": "ཡིད་བཞིན་གྲུབ་པའི་ས་མཐོར་གཤེགས་པ་གང་ཡིན་པ།།",
    "target": "ཡིད་ བཞིན་ གྲུབ་པ འི་ ས་མཐོ ར་ གཤེགས་པ་ གང་ ཡིན་པ ། །"
  },
  {
    "source": "དམ་པ་ཆོས་ཉིད་མྱུ་གུ་མགོན་ལ་ཕྱག་འཚལ་བསྟོད།།",
    "target": "དམ་པ་ ཆོས་ཉིད་ མྱུ་གུ་ མགོན་ ལ་ ཕྱག་ འཚལ་ བསྟོད ། །"
  },
  {
    "source": "དེ་ཡི་རྗེས་འཛིན་འོད་གསལ་ཉི་མའི་སྙིང་པོ་བརྙེས།།",
    "target": "དེ་ ཡི་ རྗེས་འཛིན་ འོད་གསལ་ ཉི་མ འི་ སྙིང་པོ་ བརྙེས ། །"
  },
  {
    "source": "བརྒལ་དཀའི་མུན་ནག་འཐིབས་པོ་རབ་ཏུ་འཇོམས་མཛད་ཅིང་།།",
    "target": "བརྒལ་ དཀ འི་ མུན་ནག་ འཐིབས་པོ་ རབ་ ཏུ་ འཇོམས་ མཛད་ ཅིང་ ། །"
  },
  {
    "source": "ཐུགས་རྗེའི་འོད་ཟེར་བྱེ་བའི་འཛམ་གླིང་སྣང་མཛད་པའི།།",
    "target": "ཐུགས་རྗེ འི་ འོད་ཟེར་ བྱེ་བ འི་ འཛམ་གླིང་ སྣང་ མཛད་པ འི ། །"
  },
  {
    "source": "དམ་པ་རིག་འཛིན་མྱུ་གུ་མགོན་ལ་ཕྱག་འཚལ་བསྟོད།།",
    "target": "དམ་པ་ རིག་འཛིན་ མྱུ་གུ་ མགོན་ ལ་ ཕྱག་ འཚལ་ བསྟོད ། །"
  },
  {
    "source": "དེ་ཡི་རྗེས་འཛིན་སྡེ་སྣོད་རྒྱ་མཚོའི་ཕ་རོལ་ཕྱིན།།",
    "target": "དེ་ ཡི་ རྗེས་འཛིན་ སྡེ་སྣོད་ རྒྱ་མཚོ འི་ ཕ་རོལ་ ཕྱིན ། །"
  },
  {
    "source": "རྒྱུད་དོན་མངའ་བརྙེས་རྡོ་རྗེ་སྙིང་པོའི་དོན་ལ་མཁས།།",
    "target": "རྒྱུད་ དོན་ མངའ་ བརྙེས་ རྡོ་རྗེ་ སྙིང་པོ འི་ དོན་ ལ་ མཁས ། །"
  },
  {
    "source": "ཏིང་འཛིན་མི་གཡོ་ཆོས་དབྱིངས་ཞི་ལ་ཐུགས་གཞོལ་བའི།།",
    "target": "ཏིང་འཛིན་ མི་ གཡོ་ ཆོས་དབྱིངས་ ཞི་ ལ་ ཐུགས་གཞོལ་བ འི ། །"
  },
  {
    "source": "དམ་པ་ཆོས་མཆོག་མྱུ་གུ་མགོན་ལ་ཕྱག་འཚལ་བསྟོད།།",
    "target": "དམ་པ་ ཆོས་མཆོག་ མྱུ་གུ་ མགོན་ ལ་ ཕྱག་ འཚལ་ བསྟོད ། །"
  },
  {
    "source": "དངོས་གྲུབ་ཀུན་འབྱུང་ཡོན་ཏན་རྒྱ་མཚོའི་བླ་མ་ལ།།",
    "target": "དངོས་གྲུབ་ ཀུན་ འབྱུང་ ཡོན་ཏན་རྒྱ་མཚོ འི་ བླ་མ་ ལ ། །"
  },
  {
    "source": "གུས་པས་གསོལ་འདེབས་ཐུག་རྗེས་བྱིན་གྱིས་བརླབ་ཏུ་གསོལ།།",
    "target": "གུས་པ ས་ གསོལ་ འདེབས་ ཐུག་ རྗེ ས་ བྱིན་ གྱིས་ བརླབ་ ཏུ་ གསོལ ། །"
  },
  {
    "source": "ཨོཾ་ཨཱཿཧཱུྃ།",
    "target": "ཨོཾ་ ཨཱཿ ཧཱུྃ །"
  },
  {
    "source": "གུ་རུ་ན་མོ་མ་ཧཱ་སིདྡྷི་ས་མ་ཡ།",
    "target": "གུ་ རུ་ ན་ མོ་ མ་ཧཱ་ སིདྡྷི་ ས་མ་ཡ །"
  },
  {
    "source": "དྷརྨ་ཀཱ་ཡ་ས་མནྟ་བྷ་དྲཱ།",
    "target": "དྷརྨ་ ཀཱ་ཡ་ ས་མནྟ་བྷ་དྲཱ །"
  },
  {
    "source": "བཛྲ་བཱ་གི་ཤུ་ན་མོ།།",
    "target": "བཛྲ་ བཱ་ གི་ ཤུ་ན་ མོ ། །"
  },
  {
    "source": "ས་མེ་རཱ་ཐ་ཡ་སིང་།",
    "target": "ས་ མེ་ རཱ་ ཐ་ ཡ་ སིང་ །"
  },
  {
    "source": "མ་ཧཱ་སིདྡྷི་ས་མ་ཡཱ།",
    "target": "མ་ཧཱ་ སིདྡྷི་ ས་མ་ཡཱ །"
  },
  {
    "source": "ས་མ་བྷོ་ཀཱ་ཡ།",
    "target": "ས་ མ་ བྷོ་ ཀཱ་ཡ །"
  },
  {
    "source": "བཛྲ་༼༧༤༽དྷཱ་ར་ན་མོ།།",
    "target": "བཛྲ་ ༼ ༧༤ ༽ དྷཱ་ ར་ ན་མོ ། །"
  },
  {
    "source": "ས་མར་ཐཱ་ཡ་སིང་།",
    "target": "ས་ མ ར་ ཐཱ་ ཡ་ སིང་ །"
  },
  {
    "source": "མ་ཧཱ་སིདྡྷི་ས་མ་ཡཱ།",
    "target": "མ་ཧཱ་ སིདྡྷི་ ས་མ་ཡཱ །"
  },
  {
    "source": "ནི་ར་མ་ཀཱ་ཡ་བཛྲ་ས་ཏྭ་ན་མོ།།",
    "target": "ནི་ ར་མ་ ཀཱ་ཡ་ བཛྲ་ ས་ ཏྭ་ ན་མོ ། །"
  },
  {
    "source": "ས་མ་ར་ཐཱ་ཡ་སིང་།།",
    "target": "ས་མ་ ར་ ཐཱ་ ཡ་ སིང་ ། །"
  },
  {
    "source": "མ་ཧཱ་སིདྡྷི་ས་མ་ཡཱ།",
    "target": "མ་ཧཱ་ སིདྡྷི་ ས་མ་ཡཱ །"
  },
  {
    "source": "བཛྲ་པཱ་ནི་ན་མོ།།",
    "target": "བཛྲ་ པཱ་ ནི་ ན་མོ ། །"
  },
  {
    "source": "ས་མ་ར་ཐཱ་ཡ་སིང་།",
    "target": "ས་མ་ ར་ ཐཱ་ ཡ་ སིང་ །"
  },
  {
    "source": "མ་ཧཱ་སིདྡྷི་ས་མ་ཡཱ།",
    "target": "མ་ཧཱ་ སིདྡྷི་ ས་མ་ཡཱ །"
  },
  {
    "source": "པྲཛྙཱ་དྲ་ཝཱ་གུ་རུ་ན་མོ།",
    "target": "པྲཛྙཱ་ དྲ་ ཝཱ་ གུ་རུ་ ན་ མོ །"
  },
  {
    "source": "ས་མ་ར་ཐཱ་ཡ་སིང་།",
    "target": "ས་མ་ ར་ ཐཱ་ ཡ་ སིང་ །"
  },
  {
    "source": "མ་ཧཱ་སིདྡྷི་ས་མ་ཡ།",
    "target": "མ་ཧཱ་ སིདྡྷི་ ས་མ་ཡ །"
  },
  {
    "source": "མཉྫུ་ཤྲཱི་མི་ཏྲ་གུ་རུ་ན་མོ།།",
    "target": "མཉྫུ་ ཤྲཱི་ མི་ཏྲ་ གུ་རུ་ ན་ མོ ། །"
  },
  {
    "source": "ས་མ་རཱ་ཐཱ་ཡ་སིང་།",
    "target": "ས་ མ་ རཱ་ ཐཱ་ ཡ་ སིང་ །"
  },
  {
    "source": "མ་ཧཱ་སིདྡྷི་ས་མ་ཡཱ།",
    "target": "མ་ཧཱ་ སིདྡྷི་ ས་མ་ཡཱ །"
  },
  {
    "source": "ཤྲཱི་སིང་ཧ་གུ་རུ་ན་མ།།",
    "target": "ཤྲཱི་ སིང་ ཧ་ གུ་རུ་ ན་མ ། །"
  },
  {
    "source": "ས་མ་རཱ་ཐཱ་ཡ་སིང་།",
    "target": "ས་ མ་ རཱ་ ཐཱ་ ཡ་ སིང་ །"
  },
  {
    "source": "མ་ཧཱ་སིདྡྷི་ས་མ་ཡཱ།",
    "target": "མ་ཧཱ་ སིདྡྷི་ ས་མ་ཡཱ །"
  },
  {
    "source": "ཛྙཱ་ན་སཱུ་ཏྲ་གུ་རུ་ན་མོ།།",
    "target": "ཛྙཱ་ན་ སཱུ་ ཏྲ་ གུ་ རུ་ ན་ མོ ། །"
  },
  {
    "source": "ས་མ་ར་ཐཱ་ཡ་སིང་།",
    "target": "ས་མ་ ར་ ཐཱ་ ཡ་ སིང་ །"
  },
  {
    "source": "མ་ཧཱ་སིདྡྷི་ས་མ་ཡཱ།",
    "target": "མ་ཧཱ་ སིདྡྷི་ ས་མ་ཡཱ །"
  },
  {
    "source": "བི་མ་ལ་མི་ཏྲ་གུ་རུ་ན་མོ།།",
    "target": "བི་མ་ལ་མི་ཏྲ་ གུ་རུ་ ན་ མོ ། །"
  },
  {
    "source": "ས་མ་ར་ཐཱ་ཡ་སིང་།",
    "target": "ས་མ་ ར་ ཐཱ་ ཡ་ སིང་ །"
  },
  {
    "source": "མ་ཧཱ་སིདྡྷི་ས་མ་ཡཱ།",
    "target": "མ་ཧཱ་ སིདྡྷི་ ས་མ་ཡཱ །"
  },
  {
    "source": "ས་མ་ཏི་བྷ་དྲཱ་གུ་རུ་ན་མོ།།",
    "target": "ས་མ་ཏི་ བྷ་ དྲཱ་ གུ་རུ་ ན་ མོ ། །"
  },
  {
    "source": "ས་མ་ར་ཐཱ་ཡ་སིང་།",
    "target": "ས་མ་ ར་ ཐཱ་ ཡ་ སིང་ །"
  },
  {
    "source": "མ་ཧཱ་སིདྡྷི་ས་མ་ཡཱ།",
    "target": "མ་ཧཱ་ སིདྡྷི་ ས་མ་ཡཱ །"
  },
  {
    "source": "བྷ་ཧི་ར་ཧེ་གུ་རུ་ན་མོ།།",
    "target": "བྷ་ ཧི་ ར་ ཧེ་ གུ་རུ་ ན་ མོ ། །"
  },
  {
    "source": "ས་མ་ར་ཐཱ་ཡ་སིང་།",
    "target": "ས་མ་ ར་ ཐཱ་ ཡ་ སིང་ །"
  },
  {
    "source": "མ་ཧཱ་སིདྡྷི་ས་མ་ཡཱ།",
    "target": "མ་ཧཱ་ སིདྡྷི་ ས་མ་ཡཱ །"
  },
  {
    "source": "སིང་ཧ་ཤཱ་ར་གུ་རུ་ན་མོ།།",
    "target": "སིང་ ཧ་ ཤཱ་ ར་གུ་ རུ་ ན་ མོ ། །"
  },
  {
    "source": "ས་མ་ར་ཐཱ་ཡ་སིང་།",
    "target": "ས་མ་ ར་ ཐཱ་ ཡ་ སིང་ །"
  },
  {
    "source": "མ་ཧཱ་སིདྡྷི་ས་མ་ཡ།",
    "target": "མ་ཧཱ་ སིདྡྷི་ ས་མ་ཡ །"
  },
  {
    "source": "སྭ་སྟི་ཤྲཱི་གུ་རུ་ན་མོ།།",
    "target": "སྭ་སྟི་ ཤྲཱི་ གུ་ རུ་ ན་ མོ ། །"
  },
  {
    "source": "ས་མ་ར་ཐཱ་ཡ་སིང་།",
    "target": "ས་མ་ ར་ ཐཱ་ ཡ་ སིང་ །"
  },
  {
    "source": "མ་ཧཱ་སིདྡྷི་ས་མ་ཡ།",
    "target": "མ་ཧཱ་ སིདྡྷི་ ས་མ་ཡ །"
  },
  {
    "source": "སཱུ་ལཀྟི་གུ་རུ་ན་མོ།།",
    "target": "སཱུ་ ལཀྟི་ གུ་རུ་ ན་ མོ ། །"
  },
  {
    "source": "ས་མ་ར་ཐ་ཡ་སེང་།",
    "target": "ས་མ་ ར་ཐ་ ཡ་ སེང་ །"
  },
  {
    "source": "མ་ཧཱ་སིདྡྷི་ས་མ་ཡཱ།",
    "target": "མ་ཧཱ་ སིདྡྷི་ ས་མ་ཡཱ །"
  },
  {
    "source": "ཇོ་འབེར་གུ་རུ་ན་མོ།།",
    "target": "ཇོ་ འབེར་ གུ་རུ་ ན་ མོ ། །"
  },
  {
    "source": "ས་མ་ར་ཐཱ་ཡ་སིང་།",
    "target": "ས་མ་ ར་ ཐཱ་ ཡ་ སིང་ །"
  },
  {
    "source": "མ་ཧཱ་སིདྡྷི་ས་མ་ཡ།",
    "target": "མ་ཧཱ་ སིདྡྷི་ ས་མ་ཡ །"
  },
  {
    "source": "ཡོ་གི་ཛྙཱ་ན་གུ་རུ་ན་མོ།།",
    "target": "ཡོ་ གི་ ཛྙཱ་ན་ གུ་རུ་ ན་ མོ ། །"
  },
  {
    "source": "ས་མ་ར་ཐཱ་ཡ་སིང་།།",
    "target": "ས་མ་ ར་ ཐཱ་ ཡ་ སིང་ ། །"
  },
  {
    "source": "མ་ཧཱ་སིདྡྷི་ས་མ་ཡཱ།",
    "target": "མ་ཧཱ་ སིདྡྷི་ ས་མ་ཡཱ །"
  },
  {
    "source": "དྷེ་ཀི་བཛྲ་གུ་རུ་ན་མོ།།",
    "target": "དྷེ་ ཀི་ བཛྲ་ གུ་ རུ་ ན་ མོ ། །"
  },
  {
    "source": "ས་མ་ར་ཐཱ་ཡ་སིང་།",
    "target": "ས་མ་ ར་ ཐཱ་ ཡ་ སིང་ །"
  },
  {
    "source": "མ་ཧཱ་སིདྡྷི་ས་མ་ཡཱ།",
    "target": "མ་ཧཱ་ སིདྡྷི་ ས་མ་ཡཱ །"
  },
  {
    "source": "ཀུ་མ་རཱ་ཛ་གུ་རུ་ན་མོ།།",
    "target": "ཀུ་ མ་ རཱ་ཛ་ གུ་རུ་ ན་ མོ ། །"
  },
  {
    "source": "ས་མ་ར་ཐཱ་ཡ་སིང་།",
    "target": "ས་མ་ ར་ ཐཱ་ ཡ་ སིང་ །"
  },
  {
    "source": "མ་ཧཱ་སིདྡྷི་ས་མ་ཡཱ།",
    "target": "མ་ཧཱ་ སིདྡྷི་ ས་མ་ཡཱ །"
  },
  {
    "source": "ཤི་ལ་མ་ཏེ་གུ་རུ་ན་མོ།།",
    "target": "ཤི་ ལ་ མ་ ཏེ་ གུ་ རུ་ ན་མོ ། །"
  },
  {
    "source": "ས་མ་ར་ཐུ་ཡ་སིང་།",
    "target": "ས་མ་ ར་ ཐུ་ ཡ་ སིང་ །"
  },
  {
    "source": "མ་ཧཱ་སིདྡྷི་ས་མ་ཡཱ།",
    "target": "མ་ཧཱ་ སིདྡྷི་ ས་མ་ཡཱ །"
  },
  {
    "source": "ཨོཾ་ཨཱཿཧཱུྃ།",
    "target": "ཨོཾ་ ཨཱཿ ཧཱུྃ །"
  },
  {
    "source": "ཨེ་མ་དམ་པ་སངས་རྒྱས་ཐམས་ཅད་བསྐྱེད་མཛད་ངོ་བོ་ཉིད་ཀྱི་རྗེ།།",
    "target": "ཨེ་མ་ དམ་པ་ སངས་རྒྱས་ ཐམས་ཅད་ བསྐྱེད་ མཛད་ ངོ་བོ་ཉིད་ ཀྱི་ རྗེ ། །"
  },
  {
    "source": "སངས་རྒྱས་སྟོང་གི་དཀྱིལ་འཁོར་ཉིད་ལ་དབང་བསྐྱུར་བླ་མ་ཉིད།།",
    "target": "སངས་རྒྱས་ སྟོང་ གི་ དཀྱིལ་འཁོར་ ཉིད་ ལ་ དབང་ བསྐྱུར་ བླ་མ་ ཉིད ། །"
  },
  {
    "source": "བཛྲ་བྷ་ཝ་ལྷ་རྗེ་དཔའ་བོ་ཉིད་ཀྱི་ཞལ།།",
    "target": "བཛྲ་ བྷ་ ཝ་ ལྷ་རྗེ་ དཔའ་བོ་ ཉིད་ ཀྱི་ ཞལ ། །"
  },
  {
    "source": "བདག་བློའི་གཏི་མུག་མུན་པ་འཇོམས་ཕྱིར་བསྟན་དུ་གསོལ།།",
    "target": "བདག་ བློ འི་ གཏི་མུག་ མུན་པ་ འཇོམས་ ཕྱི ར་ བསྟན་ དུ་ གསོལ ། །"
  },
  {
    "source": "འཇིག་རྟེན་དྲི་མའི་སྐྱོན་མེད་ཉེས་པ་ཀུན་ལས་གྲོལ།།",
    "target": "འཇིག་རྟེན་ དྲི་མ འི་ སྐྱོན་ མེད་ ཉེས་པ་ ཀུན་ ལས་ གྲོལ ། །"
  },
  {
    "source": "རང་རྒྱུད་རྣམ་པར་དག་ཅིང་སངས་རྒྱས་སུམ་སྟོང་གི",
    "target": "རང་རྒྱུད་ རྣམ་པ ར་ དག་ ཅིང་ སངས་རྒྱས་ སུམ་ སྟོང་ གི"
  },
  {
    "source": "།",
    "target": "།"
  },
  {
    "source": "ཐུགས་ལ་མངའ་མཛད་མཉྫུ་མི་༼༧༥༽ཏྲའི་ཞལ།།",
    "target": "ཐུགས་ ལ་ མངའ་ མཛད་ མཉྫུ་ མི་ ༼ ༧༥ ༽ ཏྲ འི་ ཞལ ། །"
  },
  {
    "source": "བདག་བློའི་ཞེ་སྡང་མ་ལུས་འཇོམས་ཕྱིར་བསྟན་དུ་གསལ།།",
    "target": "བདག་ བློ འི་ ཞེ་སྡང་ མ་ ལུས་ འཇོམས་ ཕྱི ར་ བསྟན་ དུ་ གསལ ། །"
  },
  {
    "source": "ཐུགས་རྗེ་ཆེན་པོའི་གསུང་གི་འོད་ཟེར་ཅན།།",
    "target": "ཐུགས་རྗེ་ཆེན་པོ འི་ གསུང་ གི་ འོད་ཟེར་ ཅན ། །"
  },
  {
    "source": "ཚངས་པའི་དབྱངས་ཀྱིས་འགྲོ་བ་འདམ་ལས་འདྲེན།།",
    "target": "ཚངས་པ འི་ དབྱངས་ ཀྱིས་ འགྲོ་བ་ འདམ་ ལས་ འདྲེན ། །"
  },
  {
    "source": "ཤྲཱི་སིང་ཧ་མི་འགྱུར་རྡོ་རྗེའི་ཞལ།",
    "target": "ཤྲཱི་ སིང་ ཧ་ མི་ འགྱུར་ རྡོ་རྗེ འི་ ཞལ །"
  },
  {
    "source": "བདག་བློའི་ང་རྒྱལ་ཟད་མཛད་བསྟན་དུ་གསོལ།།",
    "target": "བདག་ བློ འི་ ང་ རྒྱལ་ ཟད་ མཛད་ བསྟན་ དུ་ གསོལ ། །"
  },
  {
    "source": "ཐེག་པའི་དོན་རྣམས་ཐུགས་ལ་ཇི་བཞིན་སྟོན་མཛད་པ།།",
    "target": "ཐེག་པ འི་ དོན་ རྣམས་ ཐུགས་ ལ་ ཇི་ བཞིན་ སྟོན་ མཛད་པ ། །"
  },
  {
    "source": "མི་བསྐྱོད་ཡེ་ཤེས་འགྲོ་བའི་དོན་ལ་ཕན་བརྩོན་གང་།།",
    "target": "མི་ བསྐྱོད་ ཡེ་ཤེས་ འགྲོ་བ འི་ དོན་ ལ་ ཕན་ བརྩོན་ གང་ ། །"
  },
  {
    "source": "ཛྙཱ་ན་སཱུ་ཏྲ་འཇིག་རྟེན་རྨོངས་པ་མེད་པའི་ཞལ།།",
    "target": "ཛྙཱ་ན་ སཱུ་ ཏྲ་ འཇིག་ རྟེན་ རྨོངས་པ་ མེད་པ འི་ ཞལ ། །"
  },
  {
    "source": "བདག་བློའི་འདོད་ཆགས་དྲི་མ་ཟད་མཛད་བསྟན་དུ་གསོལ།།",
    "target": "བདག་ བློ འི་ འདོད་ཆགས་ དྲི་མ་ ཟད་ མཛད་ བསྟན་ དུ་ གསོལ ། །"
  },
  {
    "source": "མཁྱེན་རབ་རྨད་བྱུང་སྒྲ་ཚིག་རྣམ་པ་མང་པོ་ཡིས།།",
    "target": "མཁྱེན་རབ་ རྨད་ བྱུང་ སྒྲ་ ཚིག་ རྣམ་པ་ མང་པོ་ ཡིས ། །"
  },
  {
    "source": "འགྲོ་མགོན་ཡེ་ཤེས་ཉི་མའི་འོད་ཀྱིས་འཛམ་གླིང་ཀུན་ལ་ཁྱབ།།",
    "target": "འགྲོ་མགོན་ ཡེ་ཤེས་ ཉི་མ འི་ འོད་ ཀྱིས་ འཛམ་གླིང་ ཀུན་ ལ་ ཁྱབ ། །"
  },
  {
    "source": "བི་མ་མི་ཏྲ་སྐྱེ་ཤི་ཀུན་བྲལ་རྡོ་རྗེའི་ཞལ།།",
    "target": "བི་མ་ མི་ཏྲ་ སྐྱེ་ ཤི་ ཀུན་ བྲལ་ རྡོ་རྗེ འི་ ཞལ ། །"
  },
  {
    "source": "བདག་བློའི་ཕྲག་དོག་དྲི་མ་ཟད་མཛད་བསྟན་དུ་གསོལ།།",
    "target": "བདག་ བློ འི་ ཕྲག་དོག་ དྲི་མ་ ཟད་ མཛད་ བསྟན་ དུ་ གསོལ ། །"
  },
  {
    "source": "དགོངས་པ་བར་མཚམས་མེད་པས་རླུང་གི་འགྲོ་འོང་ཟད།།",
    "target": "དགོངས་པ་ བར་མཚམས་ མེད་པ ས་ རླུང་ གི་ འགྲོ་འོང་ ཟད ། །"
  },
  {
    "source": "གཉིས་མེད་རྣམ་པར་དག་པ་གང་ཡང་གྲོགས་སུ་སྣང་།།",
    "target": "གཉིས་ མེད་ རྣམ་པ ར་ དག་པ་ གང་ ཡང་ གྲོགས་ སུ་ སྣང་ ། །"
  },
  {
    "source": "ཏིང་འཛིན་བཟང་པོ་གཟུང་དང་འཛིན་པ་བྲལ་བའི་ཞལ།།",
    "target": "ཏིང་འཛིན་ བཟང་པོ་ གཟུང་ དང་ འཛིན་པ་ བྲལ་བ འི་ ཞལ ། །"
  },
  {
    "source": "བདག་བློའི་ཁོང་ཁྲོའི་དྲི་མ་ཟད་མཛད་བསྟན་དུ་གསོལ།།",
    "target": "བདག་ བློ འི་ ཁོང་ ཁྲོ འི་ དྲི་མ་ ཟད་ མཛད་ བསྟན་ དུ་ གསོལ ། །"
  },
  {
    "source": "གདོད་ནས་ཆོས་ཀུན་མཉམ་ཉིད་རོ་གཅིག་རྟོག་གྱུར་ཅིང་།།",
    "target": "གདོད་ ནས་ ཆོས་ ཀུན་ མཉམ་ཉིད་ རོ་ གཅིག་ རྟོག་ གྱུར་ ཅིང་ ། །"
  },
  {
    "source": "བདག་གཞན་དབྱེར་མེད་གཞི་ནས་བྱང་ཆུབ་དག་པའི་ངང་།།",
    "target": "བདག་གཞན་ དབྱེར་མེད་ གཞི་ ནས་ བྱང་ཆུབ་ དག་པ འི་ ངང་ ། །"
  },
  {
    "source": "ལྷུན་གྱི་རྒྱལ་མཚན་བསོད་རྣམས་གཟི་བརྗིད་ཆེན་པོའི་ཞལ།།",
    "target": "ལྷུན་ གྱི་ རྒྱལ་མཚན་ བསོད་ རྣམས་ གཟི་བརྗིད་ ཆེན་པོ འི་ ཞལ ། །"
  },
  {
    "source": "བདག་བློའི་ཉོན་མོངས་དུག་ལྔ་ཟད་མཛད་བསྟན་དུ་གསོལ།།",
    "target": "བདག་ བློ འི་ ཉོན་ མོངས་ དུག་ ལྔ་ ཟད་ མཛད་ བསྟན་ དུ་ གསོལ ། །"
  },
  {
    "source": "ལུས་ངག་ཡིད་ཀྱི་ཞེན་པ་རང་ལོག་སྟེ།།",
    "target": "ལུས་ངག་ ཡིད་ ཀྱི་ ཞེན་པ་ རང་ ལོག་ སྟེ ། །"
  },
  {
    "source": "ཉམས་ལེན་མཐར་ཕྱིན་སྣང་བ་ཟད་སར་འཆོལ།།",
    "target": "ཉམས་ལེན་ མཐ ར་ ཕྱིན་ སྣང་བ་ ཟད་ ས ར་ འཆོལ ། །"
  },
  {
    "source": "སེང་གེ་དབང་ཕྱུག་འཁྲུལ་སྣང་དག་པའི་ཞལ།།",
    "target": "སེང་གེ་ དབང་ཕྱུག་ འཁྲུལ་སྣང་ དག་པ འི་ ཞལ ། །"
  },
  {
    "source": "བདག་བློའི་འཁྲུལ་སྣང་ཟད་མཛད་བསྟན་དུ་གསོལ།།",
    "target": "བདག་ བློ འི་ འཁྲུལ་སྣང་ ཟད་ མཛད་ བསྟན་ དུ་ གསོལ ། །"
  },
  {
    "source": "རྡོ་རྗེ་ཐེག་པའི་སྙིང་པོ་གསང་སྔགས་སྡོང་པོར་གྲགས།།",
    "target": "རྡོ་རྗེ་ཐེག་པ འི་ སྙིང་པོ་ གསང་སྔགས་ སྡོང་པོ ར་ གྲགས ། །"
  },
  {
    "source": "ངེས་པའི་དོན་རྟོགས་གཉིས་མེད་མཁའ་འདྲའི་ཐུགས་མངའ་བ།།",
    "target": "ངེས་པ འི་ དོན་ རྟོགས་ གཉིས་ མེད་ མཁའ་ འདྲ འི་ ཐུགས་ མངའ་བ ། །"
  },
  {
    "source": "བཀྲ་ཤིས་མི་འགྱུར་ཡིད་བཞིན་རྡོ་རྗེ་འཆང་༼༧༦༽གི་ཞལ།།",
    "target": "བཀྲ་ཤིས་ མི་ འགྱུར་ ཡིད་ བཞིན་ རྡོ་རྗེ་འཆང་ ༼ ༧༦ ༽ གི་ ཞལ ། །"
  },
  {
    "source": "བདག་བློའི་ལས་དང་བག་ཆགས་ཟད་མཛད་བསྟན་དུ་གསོལ།།",
    "target": "བདག་ བློ འི་ ལས་ དང་ བག་ཆགས་ ཟད་ མཛད་ བསྟན་ དུ་ གསོལ ། །"
  },
  {
    "source": "མཁྱེན་རབ་ཚད་མེད་ཐེག་མཆོག་སྙིང་པོའི་དོན་ལ་མཁས།།",
    "target": "མཁྱེན་རབ་ ཚད་ མེད་ ཐེག་ མཆོག་ སྙིང་པོ འི་ དོན་ ལ་ མཁས ། །"
  },
  {
    "source": "བསྟན་པའི་རིང་ལུགས་གསལ་བྱེད་རིན་ཆེན་འོད་ཟེར་ཅན།།",
    "target": "བསྟན་པ འི་ རིང་ལུགས་ གསལ་ བྱེད་ རིན་ཆེན་འོད་ཟེར་ ཅན ། །"
  },
  {
    "source": "རྗེ་བཙུན་ཆེན་པོ་སྤྲུལ་སྐུ་དོན་ཡོད་རྡོ་རྗེའི་ཞལ།།",
    "target": "རྗེ་བཙུན་ ཆེན་པོ་ སྤྲུལ་སྐུ་ དོན་ཡོད་ རྡོ་རྗེ འི་ ཞལ ། །"
  },
  {
    "source": "བདག་བློའི་འཁོར་བའི་ཉེས་སྐྱོན་ཟད་མཛད་བསྟན་དུ་གསོལ།།",
    "target": "བདག་ བློ འི་ འཁོར་བ འི་ ཉེས་སྐྱོན་ ཟད་ མཛད་ བསྟན་ དུ་ གསོལ ། །"
  },
  {
    "source": "འཁོར་བ་མུ་མཐའ་མེད་པའི་ཀློང་དཀྱིལ་ནས།།",
    "target": "འཁོར་བ་ མུ་མཐའ་ མེད་པ འི་ ཀློང་ དཀྱིལ་ ནས ། །"
  },
  {
    "source": "ཆོས་ཉིད་དག་པ་ཀུན་གསལ་གཅིག་ཏུ་རྟོགས།།",
    "target": "ཆོས་ཉིད་ དག་པ་ ཀུན་ གསལ་ གཅིག་ ཏུ་ རྟོགས ། །"
  },
  {
    "source": "ཡེ་ནས་ལྷུན་མཉམ་རྫོགས་པ་ཆེན་པོའི་ཞལ།།",
    "target": "ཡེ་ན ས་ ལྷུན་ མཉམ་ རྫོགས་པ་ ཆེན་པོ འི་ ཞལ ། །"
  },
  {
    "source": "བདག་བློའི་བཟང་རྟོག་ཟད་མཛད་བསྟན་དུ་གསོལ།།",
    "target": "བདག་ བློ འི་ བཟང་ རྟོག་ ཟད་ མཛད་ བསྟན་ དུ་ གསོལ ། །"
  },
  {
    "source": "འོད་གསལ་མངོན་གྱུར་བྱ་རྩོལ་གཉིས་སུ་མེད།།",
    "target": "འོད་གསལ་ མངོན་ གྱུར་ བྱ་རྩོལ་ གཉིས་ སུ་ མེད ། །"
  },
  {
    "source": "རང་བཞིན་ལྷུན་གྲུབ་འོད་གསལ་ཆེན་པོའི་དང་།།",
    "target": "རང་བཞིན་ ལྷུན་གྲུབ་ འོད་གསལ་ ཆེན་པོ འི་ དང་ ། །"
  },
  {
    "source": "རྟག་ཏུ་མི་གཡོ་ཀུན་ཏུ་བཟང་པོའི་ཞལ།།",
    "target": "རྟག་ ཏུ་ མི་ གཡོ་ ཀུན་ ཏུ་ བཟང་པོ འི་ ཞལ ། །"
  },
  {
    "source": "བདག་བློའི་འཛིན་རྟོག་ཟད་མཛད་བསྟན་དུ་གསོལ།།",
    "target": "བདག་ བློ འི་ འཛིན་ རྟོག་ ཟད་ མཛད་ བསྟན་ དུ་ གསོལ ། །"
  },
  {
    "source": "མཁའ་མཉམ་རྫོགས་པ་ཆེན་པོའི་དངོས་གྲུབ་བརྙེས།།",
    "target": "མཁའ་མཉམ་ རྫོགས་པ་ ཆེན་པོ འི་ དངོས་གྲུབ་ བརྙེས ། །"
  },
  {
    "source": "ཐམས་ཅད་ལྷུན་མཉམ་གཅིག་ཏུ་སྟོན་མཛད་ཅིང་།།",
    "target": "ཐམས་ཅད་ ལྷུན་ མཉམ་ གཅིག་ ཏུ་ སྟོན་ མཛད་ ཅིང་ ། །"
  },
  {
    "source": "ཚོགས་བསགས་རྒྱལ་པོ་རང་རིག་དྲི་མེད་ཞལ།།",
    "target": "ཚོགས་ བསགས་ རྒྱལ་པོ་ རང་ རིག་ དྲི་མེད་ ཞལ ། །"
  },
  {
    "source": "བདག་བློའི་མ་རིག་ཟད་མཛད་བསྟན་དུ་གསོལ།།",
    "target": "བདག་ བློ འི་ མ་རིག་ ཟད་ མཛད་ བསྟན་ དུ་ གསོལ ། །"
  },
  {
    "source": "གདོད་མའི་རང་བཞིན་དབྱིངས་ཀྱི་ངང་ཉིད་དུ།།",
    "target": "གདོད་ མ འི་ རང་བཞིན་ དབྱིངས་ ཀྱི་ ངང་ ཉིད་ དུ ། །"
  },
  {
    "source": "མ་བཅོས་སྤྲོས་བྲལ་འོད་གསལ་འཕོ་འགྱུར་མེད།།",
    "target": "མ་ བཅོས་ སྤྲོས་བྲལ་ འོད་གསལ་ འཕོ་འགྱུར་ མེད ། །"
  },
  {
    "source": "ཁམས་གསུམ་ཡོངས་སྒྲོལ་རིག་འཛིན་ཆེན་པོའི་ཞལ།།",
    "target": "ཁམས་ གསུམ་ ཡོངས་ སྒྲོལ་ རིག་འཛིན་ ཆེན་པོ འི་ ཞལ ། །"
  },
  {
    "source": "བདག་བློའི་བླང་དོར་ཟད་མཛད་བསྟན་དུ་གསོལ།།",
    "target": "བདག་ བློ འི་ བླང་དོར་ ཟད་ མཛད་ བསྟན་ དུ་ གསོལ ། །"
  },
  {
    "source": "ཡོན་ཏན་མཐའ་ཡས་ཡེ་ཤེས་དཔལ་འབར་ཞིང་།།",
    "target": "ཡོན་ཏན་ མཐའ་ཡས་ ཡེ་ཤེས་ དཔལ་འབར་ ཞིང་ ། །"
  },
  {
    "source": "དངོས་འཛིན་རང་ཞིག་བདག་འཛིན་ཀུན་ལས་འདས།།",
    "target": "དངོས་འཛིན་ རང་ ཞིག་ བདག་ འཛིན་ ཀུན་ ལས་ འདས ། །"
  },
  {
    "source": "རང་གྲོལ་རྒྱལ་པོ་དྲི་མེད་པདྨའི་ཞལ།།",
    "target": "རང་གྲོལ་ རྒྱལ་པོ་ དྲི་མེད་ པདྨ འི་ ཞལ ། །"
  },
  {
    "source": "བདག་བློའི་འཁྲུལ་རྟོག་ཟད་མཛད་བསྟན་དུ་གསོལ།།",
    "target": "བདག་ བློ འི་ འཁྲུལ་ རྟོག་ ཟད་ མཛད་ བསྟན་ དུ་ གསོལ ། །"
  },
  {
    "source": "ཨོཾ་ཨཱ་ཧཱུྃ་སྭཱ་ཧཱ།",
    "target": "ཨོཾ་ ཨཱ་ ཧཱུྃ་ སྭཱ་ཧཱ །"
  },
  {
    "source": "ཞེས་ལན་གསུམ་དུ་བརྗོད་པར་བྱའོ།།",
    "target": "ཞེས་ ལན་ གསུམ་ དུ་ བརྗོད་པ ར་ བྱ འོ ། །"
  },
  {
    "source": "དེ་ནས་གསེར་ལ་སོགས་པའི་རིན་པོ་ཆེ་དང་།",
    "target": "དེ་ ནས་ གསེར་ ལ་ སོགས་པ འི་ རིན་པོ་ཆེ་ དང་ །"
  },
  {
    "source": "འབྲུ་དང་།",
    "target": "འབྲུ་ དང་ །"
  },
  {
    "source": "དྲི་དང་།",
    "target": "དྲི་ དང་ །"
  },
  {
    "source": "སྨན་དང་མེ་ཏོག་ལ་སོགས་པའི་མཎྜལ་དངོས་སུ་༼༧༧༽བཤམས་ལ་འབུལ་དུས་སྟོང་གསུམ་གང་བར་དམིགས་ལ་རིམ་པར་འབུལ་ལོ།།",
    "target": "སྨན་ དང་ མེ་ཏོག་ ལ་ སོགས་པ འི་ མཎྜལ་ དངོས་ སུ་ ༼ ༧༧ ༽ བཤམས་ ལ་ འབུལ་ དུས་ སྟོང་ གསུམ་ གང་བ ར་ དམིགས་ ལ་ རིམ་པ ར་ འབུལ་ ལོ ། །"
  },
  {
    "source": "དགོས་པ་ནི།",
    "target": "དགོས་པ་ ནི །"
  },
  {
    "source": "མཆོག་དང་ཐུན་མོང་གཉིས་གཉིས་ཏེ།",
    "target": "མཆོག་ དང་ ཐུན་མོང་ གཉིས་ གཉིས་ ཏེ །"
  },
  {
    "source": "དེ་ཡང་རིན་པོ་ཆེས་མཆོག་ཡེ་ཤེས་ལྔ་ལ་སྤྱོད་ཅིང་།",
    "target": "དེ་ ཡང་ རིན་པོ་ཆེ ས་ མཆོག་ ཡེ་ཤེས་ ལྔ་ ལ་ སྤྱོད་ ཅིང་ །"
  },
  {
    "source": "ཐུན་མོང་དུ་ཡོ་བྱད་ཕུན་སུམ་ཚོགས་པ་ཚེ་འདིར་འགྲུབ་བོ།།",
    "target": "ཐུན་མོང་ དུ་ ཡོ་བྱད་ ཕུན་སུམ་ཚོགས་པ་ ཚེ་ འདི ར་ འགྲུབ་ བོ ། །"
  },
  {
    "source": "དེ་བཞིན་དུ་འབྲས་བུ་ནི་སྐུ་ལྔ་དང་མུ་གེའི་འཇིགས་པ་མེད་པར་འཐོབ་བོ།།",
    "target": "དེ་ བཞིན་ དུ་ འབྲས་བུ་ ནི་ སྐུ་ ལྔ་ དང་ མུ་གེ འི་ འཇིགས་པ་ མེད་པ ར་ འཐོབ་ བོ ། །"
  },
  {
    "source": "དྲིས་ནི་དབྱིངས་ཀ་དག་ཆེན་པོའི་ངོ་བོ་དང་དབང་པོ་གསལ་བ་ཆེན་པོ་འཐོབ་བོ།།",
    "target": "དྲིས་ ནི་ དབྱིངས་ ཀ་ དག་ ཆེན་པོ འི་ ངོ་བོ་ དང་ དབང་པོ་ གསལ་བ་ ཆེན་པོ་ འཐོབ་ བོ ། །"
  },
  {
    "source": "སྨན་གྱིས་འཁོར་བའི་སྡུག་བསྔལ་ལས་གྲོལ་བ་དང་ནད་མེད་པ་འཐོབ་བོ།།",
    "target": "སྨན་ གྱིས་ འཁོར་བ འི་ སྡུག་བསྔལ་ ལས་ གྲོལ་བ་ དང་ ནད་ མེད་པ་ འཐོབ་ བོ ། །"
  },
  {
    "source": "མེ་ཏོག་གིས་སྣང་བ་འོད་ལྔའི་ཞིང་དང་ཤེས་རབ་དང་རྣམ་པར་གྲོལ་བ་ཕུན་སུམ་ཚོགས་པ་འཐོབ་པར་བྱེད་དོ།།",
    "target": "མེ་ཏོག་ གིས་ སྣང་བ་ འོད་ ལྔ འི་ ཞིང་ དང་ ཤེས་རབ་ དང་ རྣམ་པ ར་ གྲོལ་བ་ ཕུན་སུམ་ཚོགས་པ་ འཐོབ་པ ར་ བྱེད་ དོ ། །"
  },
  {
    "source": "དེ་ནས་སློབ་མ་ཀུན་ལངས་ཏེ།",
    "target": "དེ་ ནས་ སློབ་མ་ ཀུན་ ལངས་ ཏེ །"
  },
  {
    "source": "སྟོད་གཡོགས་ཕུད་ནས་ཐལ་མོ་སྙིང་གར་སྦྱར།།",
    "target": "སྟོད་གཡོགས་ ཕུད་ ནས་ ཐལ་མོ་ སྙིང་ག ར་ སྦྱར ། །"
  },
  {
    "source": "རྐང་པའི་ལོང་བུ་གཤིབས་ནས།",
    "target": "རྐང་པ འི་ ལོང་ བུ་ གཤིབས་ ནས །"
  },
  {
    "source": "བླ་མའི་ཐུགས་ཀར་མིག་གཏད་དེ།",
    "target": "བླ་མ འི་ ཐུགས་ཀ ར་ མིག་ གཏད་ དེ །"
  },
  {
    "source": "ཤེས་པ་མ་ཡེངས་པར་བྱ་སྟེ།",
    "target": "ཤེས་པ་ མ་ ཡེངས་པ ར་ བྱ་ སྟེ །"
  },
  {
    "source": "བླ་མས་ཨ་དྲུག་བརྩེགས་ཡེངས་ལ་བོར་བའི་ཚུལ་དུ་དྲག་ལ་ཐུང་བར་བརྗོད་པས།",
    "target": "བླ་མ ས་ ཨ་ དྲུག་ བརྩེག ས་ ཡེངས་ ལ་ བོར་བ འི་ ཚུལ་ དུ་ དྲག་ ལ་ ཐུང་བ ར་ བརྗོད་པ ས །"
  },
  {
    "source": "སློབ་མའི་ལུས་འཕར་བ་དང་།",
    "target": "སློབ་མ འི་ ལུས་ འཕར་བ་ དང་ །"
  },
  {
    "source": "ངག་གསལ་ཞིང་སྨྲ་བ་སེམས་མི་རྟོག་པ་ཤར་བ་ནི་ཡེ་ཤེས་དབབ་པའོ།།",
    "target": "ངག་ གསལ་ ཞིང་ སྨྲ་བ་ སེམས་ མི་ རྟོག་པ་ ཤར་བ་ ནི་ ཡེ་ཤེས་ དབབ་པ འོ ། །"
  },
  {
    "source": "དེ་ནས་ཐུགས་ཀྱི་དཀྱིལ་འཁོར་དུ་གཞུག་པ་ནི།",
    "target": "དེ་ ནས་ ཐུགས་ ཀྱི་ དཀྱིལ་འཁོར་ དུ་ གཞུག་པ་ ནི །"
  },
  {
    "source": "སློབ་མ་རྣམས་ལུས་གནད་དེ་ཉིད་ཀྱིས་ཁ་ཤར་གྱི་ནམ་མཁར་གཏད་པ་ལ།",
    "target": "སློབ་མ་ རྣམས་ ལུས་ གནད་ དེ་ ཉིད་ ཀྱིས་ ཁ་ཤ ར་ གྱི་ ནམ་ མཁ ར་ གཏད་པ་ ལ །"
  },
  {
    "source": "བླ་མས་ངག་སྙན་པོས།",
    "target": "བླ་མ ས་ ངག་ སྙན་པོ ས །"
  },
  {
    "source": "ཨེ་མ་སྐལ་ལྡན་ཤར་ཕྱོགས་ཀྱི་ནམ་མཁའི་དཀྱིལ་ན་ཕར་གམ་གམ་སོགས་དང་།",
    "target": "ཨེ་མ་ སྐལ་ལྡན་ ཤར་ཕྱོགས་ ཀྱི་ ནམ་ མཁ འི་ དཀྱིལ་ ན་ ཕ ར་ གམ་ གམ་ སོགས་ དང་ །"
  },
  {
    "source": "ཞེས་གསུམ་བརྗོད་ནས།",
    "target": "ཞེས་ གསུམ་ བརྗོད་ ནས །"
  },
  {
    "source": "ཡང་འགྲོ་ན་འགྲོ་ས་འདུག་གམ།",
    "target": "ཡང་ འགྲོ་ ན་ འགྲོ་ས་ འདུག་ གམ །"
  },
  {
    "source": "འགྲོ་བའི་མཁན་པོ་འདུག་གམ།",
    "target": "འགྲོ་བ འི་ མཁན་པོ་ འདུག་ གམ །"
  },
  {
    "source": "ཞེས་བརྗོད་དོ།།",
    "target": "ཞེས་ བརྗོད་ དོ ། །"
  },
  {
    "source": "དེ་བཞིན་དུ་ལྷོ་དང་ནུབ་དང་བྱང་ལ་སྦྱར་བ་ནི།",
    "target": "དེ་ བཞིན་ དུ་ ལྷོ་ དང་ ནུབ་ དང་ བྱང་ ལ་ སྦྱར་བ་ ནི །"
  },
  {
    "source": "སེམས་སྟོང་པ་ཉིད་བསམ་ངོ་དང་བྲལ་བའི་ངང་དུ་འཇོག་པའོ།།",
    "target": "སེམས་ སྟོང་པ་ཉིད་ བསམ་ ངོ་ དང་ བྲལ་བ འི་ ངང་ དུ་ འཇོག་པ འོ ། །"
  },
  {
    "source": "དེ་ནས་བླ་མ་ཕྱག་མཛུབ་བསྒྲེངས་ཏེ།",
    "target": "དེ་ ནས་ བླ་མ་ ཕྱག་ མཛུབ་ བསྒྲེངས་ ཏེ །"
  },
  {
    "source": "ནམ་མཁའི་དབྱིངས་ལ་ཡུག་ཡུག་ལན་གསུམ་བྱས་ཏེ།",
    "target": "ནམ་ མཁ འི་ དབྱིངས་ ལ་ ཡུག་ ཡུག་ ལན་ གསུམ་ བྱས་ ཏེ །"
  },
  {
    "source": "ནམ་མཁའི་དབྱིངས་ལ་ལྟོས་ཤིག་གསུམ་བརྗོད་པ་ནི།",
    "target": "ནམ་ མཁ འི་ དབྱིངས་ ལ་ ལྟོས་ ཤིག་ གསུམ་ བརྗོད་པ་ ནི །"
  },
  {
    "source": "ཆོས་སྐུ་མཁའ་མཉམ་༼༧༨༽དག་པའི་དཀྱིལ་འཁོར་བསྟན་པའོ།།",
    "target": "ཆོས་སྐུ་ མཁའ་མཉམ་ ༼ ༧༨ ༽ དག་པ འི་ དཀྱིལ་འཁོར་ བསྟན་པ འོ ། །"
  },
  {
    "source": "དེ་ནས་ཡེ་ཤེས་ཀྱི་ལྷ་ངོ་བསྟན་པ་ནི།",
    "target": "དེ་ ནས་ ཡེ་ཤེས་ ཀྱི་ ལྷ་ ངོ་ བསྟན་པ་ ནི །"
  },
  {
    "source": "སློབ་མ་ཀུན་སྟོད་གཡོགས་གོན་ནས་སྐྱིལ་ཀྲུང་གིས་འདུག་པ་ལ།",
    "target": "སློབ་མ་ ཀུན་ སྟོད་གཡོགས་ གོན་ ནས་ སྐྱིལ་ཀྲུང་ གིས་ འདུག་པ་ ལ །"
  },
  {
    "source": "སྟེང་གི་ཉི་མའི་ཕྱོགས་བཞིར་ཉི་མ་བཞིས་བསྐོར་ཏེ།",
    "target": "སྟེང་ གི་ ཉི་མ འི་ ཕྱོགས་ བཞི ར་ ཉི་མ་ བཞི ས་ བསྐོར་ ཏེ །"
  },
  {
    "source": "ལྔ་ཤར་བ་ཇེ་མཐོར་སོང་ནས་མཐར་མི་མངོན་པའི་ངང་དུ་སོམས་ཤིག་པའི་དོན་བཤད་པ་ནི།",
    "target": "ལྔ་ ཤར་བ་ ཇེ་ མཐོ ར་ སོང་ ནས་ མཐ ར་ མི་ མངོན་པ འི་ ངང་ དུ་ སོམས་ ཤིག་པ འི་ དོན་ བཤད་པ་ ནི །"
  },
  {
    "source": "ཨེ་མ་སྐལ་ལྡན་ནམ་མཁའི་དཀྱིལ་ཡ་གི་ན།།",
    "target": "ཨེ་མ་ སྐལ་ལྡན་ ནམ་ མཁ འི་ དཀྱིལ་ ཡ་ གི་ ན ། །"
  },
  {
    "source": "ཉི་མའི་དཀྱིལ་འཁོར་འོད་འཕྲོ་བ་ལྔ་པོ་ལ་ཤེས་པ་གཏོད་ལ་ཇེ་མཐོ་ཇེ་མཐོར་སོང་ཞིག།",
    "target": "ཉི་མ འི་ དཀྱིལ་འཁོར་ འོད་ འཕྲོ་བ་ ལྔ་པོ་ ལ་ ཤེས་པ་ གཏོད་ ལ་ ཇེ་ མཐོ་ ཇེ་ མཐོ ར་ སོང་ ཞིག །"
  },
  {
    "source": "ཞེས་ལན་གསུམ་བརྗོད་ནས།",
    "target": "ཞེས་ ལན་ གསུམ་ བརྗོད་ ནས །"
  },
  {
    "source": "སླར་མ་ལྡོག་ཅིག་ཅེས་པ་ཡང་གསུམ་བརྗོད་དོ།།",
    "target": "སླ ར་ མ་ ལྡོག་ ཅིག་ ཅེས་ པ་ ཡང་ གསུམ་ བརྗོད་ དོ ། །"
  },
  {
    "source": "དེའང་ཉི་མ་ལྔ་ནི་ཡེ་ཤེས་ལྔའི་སྣང་བ་ཡིན་ལ་ཇེ་མཐོར་སོང་ནས་མི་དམིགས་པ་ནི་དབྱིངས་སུ་ཐིམ་པ་སྟེ།",
    "target": "དེ འང་ ཉི་མ་ ལྔ་ ནི་ ཡེ་ཤེས་ ལྔ འི་ སྣང་བ་ ཡིན་ ལ་ ཇེ་ མཐོ ར་ སོང་ ནས་ མི་ དམིགས་པ་ ནི་ དབྱིངས་ སུ་ ཐིམ་པ་ སྟེ །"
  },
  {
    "source": "སླར་མ་ལྡོག་ཅིག་གསུམ་ནི།",
    "target": "སླ ར་ མ་ ལྡོག་ ཅིག་ གསུམ་ ནི །"
  },
  {
    "source": "སྐུ་གསུམ་གྱི་ངང་ལས་ཕྱིར་མ་ལྡོག་ཅིག་ཏུ་མཚོན་པའོ།།",
    "target": "སྐུ་ གསུམ་ གྱི་ ངང་ ལས་ ཕྱི ར་ མ་ ལྡོག་ ཅིག་ ཏུ་ མཚོན་པ འོ ། །"
  },
  {
    "source": "དེ་ནས་བླ་མས་ལངས་ཏེ།།",
    "target": "དེ་ ནས་ བླ་མ ས་ ལངས་ ཏེ ། །"
  },
  {
    "source": "གཡས་བརྐྱང་གཡོན་བསྐུམ་མཛུབ་མོ་མིག་ལ་བཙུགས་ནས་ཨ་བརྩེགས་མར་བརྗོད་དེ།",
    "target": "གཡས་ བརྐྱང་ གཡོན་ བསྐུམ་ མཛུབ་མོ་ མིག་ ལ་ བཙུགས་ ནས་ ཨ་ བརྩེགས་མ ར་ བརྗོད་ དེ །"
  },
  {
    "source": "ཕྱོགས་བཞིར་ལན་བཞིར་དེ་ལྟར་བྱའོ།།",
    "target": "ཕྱོགས་ བཞི ར་ ལན་ བཞི ར་ དེ་ ལྟ ར་ བྱ འོ ། །"
  },
  {
    "source": "དེ་ཡང་གཡས་བརྐྱངས་པས་ནི་འཁོར་པའི་སྤྲོས་པ་གཅོད་ལ།",
    "target": "དེ་ ཡང་ གཡས་ བརྐྱངས་པ ས་ ནི་ འཁོར་པ འི་ སྤྲོས་པ་ གཅོད་ ལ །"
  },
  {
    "source": "གཡོན་བསྐུམས་པས་ནི་མྱ་ངན་ལས་འདས་པའི་སྣང་བ་མཚོན་ཞིང་།",
    "target": "གཡོན་ བསྐུམས་པ ས་ ནི་ མྱ་ངན་ ལས་ འདས་པ འི་ སྣང་བ་ མཚོན་ ཞིང་ །"
  },
  {
    "source": "མཛུབ་མོ་བཙུགས་པས་ཡེ་ཤེས་མིག་ནས་འཆར་བ་མཚོན་ཞིང་།",
    "target": "མཛུབ་མོ་ བཙུགས་པ ས་ ཡེ་ཤེས་ མིག་ ནས་ འཆར་བ་ མཚོན་ ཞིང་ །"
  },
  {
    "source": "ཨཿབརྗོད་པས་ཚེ་འདིར་སྐྱེ་མེད་དུ་གྲོལ་བའི་བརྡའོ།།",
    "target": "ཨཿ བརྗོད་པ ས་ ཚེ་ འདི ར་ སྐྱེ་མེད་ དུ་ གྲོལ་བ འི་ བརྡ འོ ། །"
  },
  {
    "source": "ཞེས་བསྟན་པར་བྱའོ།།",
    "target": "ཞེས་ བསྟན་པ ར་ བྱ འོ ། །"
  },
  {
    "source": "དེ་ནས་མཛུབ་མོ་ནམ་མཁར་བསྒྲེངས་ཤིང་།",
    "target": "དེ་ ནས་ མཛུབ་མོ་ ནམ་ མཁ ར་ བསྒྲེངས་ ཤིང་ །"
  },
  {
    "source": "མིག་ནམ་མཁར་ཧུར་ཕྱུངས་ནས་གཏད་ལ།",
    "target": "མིག་ ནམ་ མཁ ར་ ཧུ ར་ ཕྱུངས་ ནས་ གཏད་ ལ །"
  },
  {
    "source": "ནམ་མཁའ་འདི་ནི་རྒྱ་ཆེའོ།།",
    "target": "ནམ་མཁའ་ འདི་ ནི་ རྒྱ་ ཆེ འོ ། །"
  },
  {
    "source": "ཞེས་ལན་གསུམ་བརྗོད་དོ།།",
    "target": "ཞེས་ ལན་ གསུམ་ བརྗོད་ དོ ། །"
  },
  {
    "source": "དེ་ཡང་མཛུབ་མོ་བསྒྲེངས་པ་ནི།",
    "target": "དེ་ ཡང་ མཛུབ་མོ་ བསྒྲེངས་པ་ ནི །"
  },
  {
    "source": "ལུ་གུ་རྒྱུད་ནམ་མཁར་འཆར་བའི་བརྡའོ།།",
    "target": "ལུ་གུ་ རྒྱུད་ ནམ་ མཁ ར་ འཆར་བ འི་ བརྡ འོ ། །"
  },
  {
    "source": "མིག་ཧར་པོར་ལྟ་བ་ནི།",
    "target": "མིག་ ཧར་པོ ར་ ལྟ་བ་ ནི །"
  },
  {
    "source": "གཟིགས་སྟངས་མཚོན་པའོ།།",
    "target": "གཟིགས་ སྟངས་ མཚོན་པ འོ ། །"
  },
  {
    "source": "ཚིག་བརྗོད་པ་ནི་འཁྲུལ་སྣང་འགགས་ནས་ཡེ་ཤེས་ཀྱི་སྣང་བ་ཤར་ཏེ་དབྱིངས་སུ་ཐིམ་པ་མཚོན་པའོ།།",
    "target": "ཚིག་ བརྗོད་པ་ ནི་ འཁྲུལ་སྣང་ འགགས་ ནས་ ཡེ་ཤེས་ ཀྱི་ སྣང་བ་ ཤར་ ཏེ་ དབྱིངས་ སུ་ ཐིམ་པ་ མཚོན་པ འོ ། །"
  },
  {
    "source": "ཞེས་བཤད་པར་བྱའོ།།",
    "target": "ཞེས་ བཤད་པ ར་ བྱ འོ ། །"
  },
  {
    "source": "དེ་ནས་ཞར་ལ་མཎྜལ་གྱི་དག་པར་༼༧༩༽བཤད་པ་ནི།",
    "target": "དེ་ ནས་ ཞར་ ལ་ མཎྜལ་ གྱི་ དག་པ ར་ ༼ ༧༩ ༽ བཤད་པ་ ནི །"
  },
  {
    "source": "ཀྱེ་སྐལ་ལྡན་རྣམས་དྲིའི་མཎྜལ་ལ།",
    "target": "ཀྱེ་ སྐལ་ལྡན་ རྣམས་ དྲི འི་ མཎྜལ་ ལ །"
  },
  {
    "source": "མེ་ཏོག་ལྔའི་ཚོམ་བུ་བཀོད་པ་ནི།",
    "target": "མེ་ཏོག་ ལྔ འི་ ཚོམ་བུ་ བཀོད་པ་ ནི །"
  },
  {
    "source": "རྟེན་དང་བརྟེན་པའི་ཆོས་སུ་དབྱེར་མེད་པའི་ངོ་བོ་མཚོན་པ་སྟེ།",
    "target": "རྟེན་ དང་ བརྟེན་པ འི་ ཆོས་ སུ་ དབྱེར་ མེད་པ འི་ ངོ་བོ་ མཚོན་པ་ སྟེ །"
  },
  {
    "source": "དེ་ཡང་གདོད་མའི་དབྱིངས་ཀ་དག་གི་ངང་ནས་ཡེ་ཤེས་ལྷུན་གྲུབ་ཏུ་གནས་པ་དང་།",
    "target": "དེ་ ཡང་ གདོད་མ འི་ དབྱིངས་ ཀ་ དག་ གི་ ངང་ ནས་ ཡེ་ཤེས་ལྷུན་གྲུབ་ ཏུ་ གནས་པ་ དང་ །"
  },
  {
    "source": "ལམ་དུས་ཀྱི་རྟེན་ཙིཏྟ་རིན་པོ་ཆེའི་དབུས་ན་རིག་པ་འོད་གསལ་བའི་རང་བཞིན་བརྟེན་པར་གནས་པ་དང་།",
    "target": "ལམ་ དུས་ ཀྱི་ རྟེན་ ཙིཏྟ་ རིན་པོ་ཆེ འི་ དབུས་ ན་ རིག་པ་ འོད་གསལ་ བ འི་ རང་བཞིན་ བརྟེན་པ ར་ གནས་པ་ དང་ །"
  },
  {
    "source": "འབྲས་བུའི་དུས་ཀྱི་རྟེན་སྣང་བ་བཞི་མཐར་ཕྱིན་པ་དབྱིངས་ཆོས་ཉིད་ཆེན་པོར་བརྟེན་པ་ཡེ་ཤེས་ལྔའི་རང་གདངས་མཚོན་པའོ།།",
    "target": "འབྲས་བུ འི་ དུས་ ཀྱི་ རྟེན་ སྣང་བ་ བཞི་ མཐ ར་ ཕྱིན་པ་ དབྱིངས་ ཆོས་ཉིད་ ཆེན་པོ ར་ བརྟེན་པ་ ཡེ་ཤེས་ ལྔ འི་ རང་ གདངས་ མཚོན་པ འོ ། །"
  },
  {
    "source": "མཆོད་པའི་མཎྜལ་ལྔ་ཚན་ལྔས་ཡེ་ཤེས་ཉི་ཤུ་རྩ་ལྔ་ལ་ལོངས་སྤྱོད་པའི་ཐབས་སུ་མཚོན་པ་ཤེས་པར་གྱིས་ཤིག།",
    "target": "མཆོད་པ འི་ མཎྜལ་ ལྔ་ ཚན་ ལྔས་ ཡེ་ཤེས་ ཉི་ཤུ་ རྩ་ ལྔ་ ལ་ ལོངས་སྤྱོད་པ འི་ ཐབས་ སུ་ མཚོན་པ་ ཤེས་པ ར་ གྱིས་ ཤིག །"
  },
  {
    "source": "ཅེས་བརྗོད་དོ།།",
    "target": "ཅེས་ བརྗོད་ དོ ། །"
  },
  {
    "source": "དོན་གསུམ་པ་གཟེངས་བསྟོད་པ་ནི།",
    "target": "དོན་ གསུམ་པ་ གཟེངས་བསྟོད་པ་ ནི །"
  },
  {
    "source": "ཤིན་ཏུ་སྤྲོས་པ་མེད་པའི་དབང་ཐོབ་ནས་ཆོས་སྐུའི་ཞིང་ལ་སྤྱོད་པ་དང་།",
    "target": "ཤིན་ ཏུ་ སྤྲོས་པ་ མེད་པ འི་ དབང་ ཐོབ་ ནས་ ཆོས་སྐུ འི་ ཞིང་ ལ་ སྤྱོད་པ་ དང་ །"
  },
  {
    "source": "ཡིད་ཀྱི་སྒྲིབ་པ་འདག་པ་དང་།",
    "target": "ཡིད་ ཀྱི་ སྒྲིབ་པ་ འདག་པ་ དང་ །"
  },
  {
    "source": "འབར་བའི་གཞལ་ཡས་ཀྱི་ཁྲོ་བོའི་ཞིང་ལ་དབང་ཐོབ་བ་དང་།",
    "target": "འབར་བ འི་ གཞལ་ཡས་ ཀྱི་ ཁྲོ་བོ འི་ ཞིང་ ལ་ དབང་ ཐོབ་བ་ དང་ །"
  },
  {
    "source": "མ་འབད་ཀྱང་ཕྱི་མའི་བར་དོར་གྲོལ་ལ།",
    "target": "མ་ འབད་ ཀྱང་ ཕྱི་མ འི་ བར་ དོར་ གྲོལ་ ལ །"
  },
  {
    "source": "འབད་ན་ཚེ་འདིར་གྲོལ་ཞིང་ཆོས་ཉིད་སྟོང་པ་ཉིད་བསྒོམ་པ་ལ་དབང་བ་ཡིན་ནོ།།",
    "target": "འབད་ ན་ ཚེ་ འདི ར་ གྲོལ་ ཞིང་ ཆོས་ཉིད་ སྟོང་པ་ཉིད་བསྒོམ་པ་ ལ་ དབང་བ་ ཡིན་ ནོ ། །"
  },
  {
    "source": "ཞེས་བརྗོད་དོ།།",
    "target": "ཞེས་ བརྗོད་ དོ ། །"
  },
  {
    "source": "དེ་ལྟར་ཤིན་ཏུ་སྤྲོས་པ་ཞི་བའི་དབང་།།",
    "target": "དེ་ ལྟ ར་ ཤིན་ ཏུ་ སྤྲོས་པ་ ཞི་བ འི་ དབང་ ། །"
  },
  {
    "source": "ཕྲ་ཐིག་རིན་ཆེན་རྒྱན་སྤྲས་དོན་བསྡུས་ཏེ།།",
    "target": "ཕྲ་ ཐིག་ རིན་ཆེན་ རྒྱན་ སྤྲ ས་ དོན་བསྡུས་ ཏེ ། །"
  },
  {
    "source": "མ་འོངས་སྐལ་ལྡན་དོན་དུ་བཀོད་པ་འདིས།།",
    "target": "མ་ འོངས་ སྐལ་ལྡན་ དོན་ དུ་ བཀོད་པ་ འདི ས ། །"
  },
  {
    "source": "འགྲོ་ཀུན་བྱང་ཆུབ་ཀུན་བཟང་ཉིད་ཐོབ་ཤོག།",
    "target": "འགྲོ་ ཀུན་ བྱང་ཆུབ་ ཀུན་ བཟང་ ཉིད་ ཐོབ་ ཤོག །"
  },
  {
    "source": "གསང་བ་སྙིང་ཏིག་གི་དབང་རྣམ་པར་ཕྱེ་བ་ལས།",
    "target": "གསང་བ་ སྙིང་ཏིག་ གི་ དབང་ རྣམ་པ ར་ ཕྱེ་བ་ ལས །"
  },
  {
    "source": "ཤིན་ཏུ་སྤྲོས་པ་མེད་པའི་ཤེས་རབ་ཡེ་ཤེས་ཀྱི་དབང་གི་ཆོ་གའི་གསལ་བྱེད་པདྨའི་དྲྭ་བ་ཞེས་བྱ་བ།",
    "target": "ཤིན་ ཏུ་ སྤྲོས་པ་ མེད་པ འི་ ཤེས་རབ་ ཡེ་ ཤེས་ ཀྱི་ དབང་ གི་ ཆོ་ག འི་ གསལ་བྱེད་ པདྨ འི་ དྲྭ་བ་ ཞེས་ བྱ་བ །"
  },
  {
    "source": "ཐེག་པ་མཆོག་གི་རྣལ་འབྱོར་པ་ཀློང་ཆེན་རབ་འབྱམས་ཀྱིས་གངས་རི་ཐོད་དཀར་དུ་བཀོད་པ་རྫོགས་སོ།།",
    "target": "ཐེག་པ་ མཆོག་ གི་ རྣལ་འབྱོར་པ་ ཀློང་ཆེན་ རབ་འབྱམས་ ཀྱིས་ གངས་རི་ ཐོད་ དཀར་ དུ་ བཀོད་པ་ རྫོགས་ སོ ། །"
  },
  {
    "source": "།།",
    "target": "། །"
  },
  {
    "source": "དགེའོ།།",
    "target": "དགེ འོ ། །"
  },
  {
    "source": "དགེའོ།།",
    "target": "དགེ འོ ། །"
  },
  {
    "source": "དགེའོ།།",
    "target": "དགེ འོ ། །"
  },
  {
    "source": "།།",
    "target": "། །"
  }
]
