[
  {
    "source": "ཞྭ་དམར་ཐམས་ཅད་མཁྱེན་པ་ལྔ་པས་མཛད་པའི་བླ་མ་རྒྱང་འབོད་བཞུགས་སོ།།",
    "target": "ཞྭ་ དམར་ ཐམས་ཅད་ མཁྱེན་པ་ ལྔ་པ ས་ མཛད་པ འི་ བླ་མ་ རྒྱང་ འབོད་ བཞུགས་ སོ ། །"
  },
  {
    "source": "ཀྱེ་མ།",
    "target": "ཀྱེ་མ །"
  },
  {
    "source": "ཕ་རྗེ་བཙུན་བླ་མ་རིན་པོ་ཆེ།།",
    "target": "ཕ་ རྗེ་བཙུན་ བླ་མ་ རིན་པོ་ཆེ ། །"
  },
  {
    "source": "ཁྱེད་སངས་རྒྱས་ཀུན་དང་དབྱེར་མེད་པའི།།",
    "target": "ཁྱེད་ སངས་རྒྱས་ ཀུན་ དང་ དབྱེར་ མེད་ པ འི ། །"
  },
  {
    "source": "དེང་མོས་པའི་བུ་ལ་ཐུགས་བརྩེ་བས།།",
    "target": "དེང་ མོས་པ འི་ བུ་ ལ་ ཐུགས་ བརྩེ་བ ས ། །"
  },
  {
    "source": "འཕྲལ་རྒྱལ་སྲས་མཆོག་གི་ཚུལ་བཟུང་ནས།།",
    "target": "འཕྲལ་ རྒྱལ་སྲས་ མཆོག་ གི་ ཚུལ་ བཟུང་ ནས ། །"
  },
  {
    "source": "ལར་བསམ་ཞིང་སྐྱེ་བ་བཞེས་མཛད་པའི།།",
    "target": "ལ ར་ བསམ་ ཞིང་ སྐྱེ་བ་ བཞེས་ མཛད་ པ འི ། །"
  },
  {
    "source": "དཔལ་ཀརྨ་པ་ཞེས་ཡོངས་སུ་གྲགས།།",
    "target": "དཔལ་ ཀརྨ་པ་ ཞེས་ ཡོངས་ སུ་ གྲགས ། །"
  },
  {
    "source": "རྗེ་ཁྱེད་ཀྱི་བྱིན་རླབས་མི་དམན་ཡང་།།",
    "target": "རྗེ་ ཁྱེད་ ཀྱི་ བྱིན་རླབས་ མི་ དམན་ ཡང་ ། །"
  },
  {
    "source": "རྒྱུད་ཉོན་མོངས་དྲག་པོས་ཡོངས་བཟུང་ནས།།",
    "target": "རྒྱུད་ ཉོན་མོངས་ དྲག་པོ ས་ ཡོངས་ བཟུང་ ནས ། །"
  },
  {
    "source": "ལས་ནག་པོའི་སྤྱོད་པ་དར་བའི་ཚེ།།",
    "target": "ལས་ ནག་པོ འི་ སྤྱོད་པ་ དར་བ འི་ ཚེ ། །"
  },
  {
    "source": "དུས་སྙིགས་མ་ལྔ་བདོའི་སེམས་ཅན་རྣམས།།",
    "target": "དུས་ སྙིགས་མ་ ལྔ་ བདོ འི་ སེམས་ཅན་ རྣམས ། །"
  },
  {
    "source": "འོག་ངན་སོང་གཡང་ས་ཁོ་ནར་ལྷུང་།།",
    "target": "འོག་ ངན་སོང་ གཡང་ས་ ཁོ་ན ར་ ལྷུང་ ། །"
  },
  {
    "source": "ཕ་ཐུགས་རྗེས་ཟུང་ཞིག་ཀརྨ་པ།།",
    "target": "ཕ་ ཐུགས་རྗེ ས་ ཟུང་ ཞིག་ ཀརྨ་པ ། །"
  },
  {
    "source": "ལས་སྔར་བྱས་རྣམས་ལ་དོན་མ་མཆིས།།",
    "target": "ལས་ སྔ ར་ བྱས་ རྣམས་ ལ་ དོན་ མ་ མཆིས ། །"
  },
  {
    "source": "ཆོས་སྔར་བྱས་རྣམས་ལ་ཆོས་བརྒྱད་འདྲེས།།",
    "target": "ཆོས་ སྔ ར་ བྱས་ རྣམས་ ལ་ ཆོས་ བརྒྱད་ འདྲེས ། །"
  },
  {
    "source": "ལམ་རྣལ་མ་སྒྲུབ་པ་གཅིག་མ་དྲན།།",
    "target": "ལམ་ རྣལ་མ་ སྒྲུབ་པ་ གཅིག་ མ་ དྲན ། །"
  },
  {
    "source": "ད་ཁྱེད་རང་མིན་པ་རེ་ས་མེད།།",
    "target": "ད་ ཁྱེད་ རང་ མིན་པ་ རེ་ ས་ མེད ། །"
  },
  {
    "source": "ཕ་ཐུགས་རྗེས༴ལར་གཤིན་རྗེའི་སྐྱེས་བུའི་རྒྱབ་ནས་དེད།།",
    "target": "ཕ་ ཐུགས་རྗེས ༴ ལ ར་ གཤིན་རྗེ འི་ སྐྱེས་བུ འི་ རྒྱབ་ ནས་ དེད ། །"
  },
  {
    "source": "དུས་ལོ་ཟླ་ཞག་གི་མདུན་ནས་བསུ།།",
    "target": "དུས་ ལོ་ ཟླ་ ཞག་ གི་ མདུན་ ནས་ བསུ ། །"
  },
  {
    "source": "འཕྲལ་རྣམ་གཡེངས་བྱ་བས་བར་ནས་བྲིད།།",
    "target": "འཕྲལ་ རྣམ་ གཡེངས་ བྱ་བ ས་ བར་ ནས་ བྲིད ། །"
  },
  {
    "source": "དེ་མ་ཚོར་བསླུས་ཤིག་བྱུང་ཉན་འདུག།",
    "target": "དེ་ མ་ ཚོར་ བསླུས་ ཤིག་ བྱུང་ ཉན་ འདུག །"
  },
  {
    "source": "ཕ་ཐུགས་རྗེས༴གཞོན་དབང་པོ་གསལ་ཚེ་བྱིས་པའི་སེམས།།",
    "target": "ཕ་ ཐུགས་རྗེས ༴ གཞོན་ དབང་པོ་ གསལ་ ཚེ་ བྱིས་པ འི་ སེམས ། །"
  },
  {
    "source": "ལུས་དར་ལ་བབ་ཚེ་བྲེལ་བས་གཡེངས།།",
    "target": "ལུས་ དར་ ལ་ བབ་ ཚེ་ བྲེལ་བ ས་ གཡེངས ། །"
  },
  {
    "source": "ད་རྒས་ཤིང་འཁོག་པར་གྱུར་པའི་ཚེ།།",
    "target": "ད་ རྒས་ ཤིང་ འཁོག་པ ར་ གྱུར་པ འི་ ཚེ ། །"
  },
  {
    "source": "ཆོས་གཤའ་མ་དྲན་ཀྱང་ཕྱིས་ནས་སོང་།།",
    "target": "ཆོས་ གཤའ་ མ་ དྲན་ ཀྱང་ ཕྱི ས་ ནས་ སོང་ ། །"
  },
  {
    "source": "ཕ་ཐུགས་རྗེས༴རང་སྡོད་པར་འདོད་ཀྱང་སྡོད་དབང་མེད།།",
    "target": "ཕ་ ཐུགས་རྗེས ༴ རང་ སྡོད་པ ར་ འདོད་ ཀྱང་ སྡོད་ དབང་ མེད ། །"
  },
  {
    "source": "ནོར་ཁྱེར་བར་འདོད་ཀྱང་ཁྱེར་མི་གཏུབ།།",
    "target": "ནོར་ ཁྱེར་ བ ར་ འདོད་ ཀྱང་ ཁྱེར་ མི་ གཏུབ ། །"
  },
  {
    "source": "གྲོགས་འགྲོགས་པར་འདོད་ཀྱང་རང་གཅིག་པུ།།",
    "target": "གྲོགས་ འགྲོགས་པ ར་ འདོད་ ཀྱང་ རང་ གཅིག་ པུ ། །"
  },
  {
    "source": "སང་འཇིག་རྟེན་ཕ་རོལ་འགྲོ་བར་ངེས།།",
    "target": "སང་ འཇིག་རྟེན་ཕ་རོལ་ འགྲོ་བ ར་ ངེས ། །"
  },
  {
    "source": "ཕ་ཐུགས་རྗེས༴ཚེ་འདི་ཡི་བག་ཆགས་འཕེན་པའི་མཐུས།།",
    "target": "ཕ་ ཐུགས་རྗེས ༴ ཚེ་ འདི་ ཡི་ བག་ཆགས་ འཕེན་པ འི་ མཐུ ས ། །"
  },
  {
    "source": "ལམ་བར་དོའི་འཕྲང་ལ་ཅི་འདྲ་ཨང་།།",
    "target": "ལམ་བར་ དོ འི་ འཕྲང་ ལ་ ཅི་ འདྲ་ ཨང་ ། །"
  },
  {
    "source": "དཔེ་མདོང་སུམ་ཉལ་བའི་རྨི་ལམ་བཞིན།།",
    "target": "དཔེ་ མདོང་ སུམ་ ཉལ་བ འི་ རྨི་ལམ་ བཞིན ། །"
  },
  {
    "source": "ལར་རང་དབང་ཐོབ་པ་ཤིན་ཏུ་དཀའ།།",
    "target": "ལ ར་ རང་དབང་ ཐོབ་པ་ ཤིན་ ཏུ་ དཀའ ། །"
  },
  {
    "source": "ཕ་ཐུགས་རྗེས༴སྤྱིར་འཁོར་བའི་ཆོས་ལ་སྙིང་པོ་མེད།།",
    "target": "ཕ་ ཐུགས་རྗེས ༴ སྤྱི ར་ འཁོར་བ འི་ ཆོས་ ལ་ སྙིང་པོ་ མེད ། །"
  },
  {
    "source": "སྒོས་མི་རྟག་ལུས་ལ་སྙིང་པོ་མེད།།",
    "target": "སྒོས་ མི་ རྟག་ ལུས་ ལ་ སྙིང་པོ་ མེད ། །"
  },
  {
    "source": "འདི་ནམ་མཁར་ཤར་བའི་འཇའ་ཚོན་འདྲ།།",
    "target": "འདི་ ནམ་ མཁ ར་ ཤར་བ འི་ འཇའ་ཚོན་ འདྲ ། །"
  },
  {
    "source": "དེ་བདེན་པར་བཟུང་ཡང་ཡལ་ནས་འགྲོ།།",
    "target": "དེ་ བདེན་པ ར་ བཟུང་ ཡང་ ཡལ་ ནས་ འགྲོ ། །"
  },
  {
    "source": "ཕ་ཐུགས་རྗེས༴ཡར་སངས་རྒྱས་རྣམས་ལ་དད་པ་མེད།།",
    "target": "ཕ་ ཐུགས་རྗེས ༴ ཡར་ སངས་རྒྱས་ རྣམས་ ལ་ དད་པ་ མེད ། །"
  },
  {
    "source": "མར་སེམས་ཅན་རྣམས་ལ་སྙིང་རྗེ་ཆུང་།།",
    "target": "མར་ སེམས་ཅན་ རྣམས་ ལ་ སྙིང་རྗེ་ ཆུང་ ། །"
  },
  {
    "source": "གོས་ངུར་སྨྲིག་གྱོན་ཀྱང་གཟུགས་བརྙན་ཙམ།།",
    "target": "གོས་ ངུར་སྨྲིག་ གྱོན་ ཀྱང་ གཟུགས་བརྙན་ ཙམ ། །"
  },
  {
    "source": "སྐྲ་སྤུ་གྲི་བཞར་ཡང་དོན་སྒོ་ཆུང་།།",
    "target": "སྐྲ་ སྤུ་གྲི་ བཞ ར་ ཡང་ དོན་ སྒོ་ ཆུང་ ། །"
  },
  {
    "source": "ཕ་ཐུགས་རྗེས༴",
    "target": "ཕ་ ཐུགས་རྗེས ༴"
  },
  {
    "source": "ཆོས་ཐོས་པ་མང་ཡང་གནད་མ་ཁྲོལ།།",
    "target": "ཆོས་ ཐོས་པ་ མང་ ཡང་ གནད་ མ་ ཁྲོལ ། །"
  },
  {
    "source": "ཁ་བཤད་པ་ཚ་ཡང་རྒྱུད་མ་དུལ།།",
    "target": "ཁ་བཤད་པ་ ཚ་ ཡང་ རྒྱུད་ མ་ དུལ ། །"
  },
  {
    "source": "གནས་རི་ཁྲོད་འགྲིམ་ཀྱང་ཁྱིམ་ལ་སྲེད།།",
    "target": "གནས་ རི་ཁྲོད་ འགྲིམ་ ཀྱང་ ཁྱིམ་ ལ་ སྲེད ། །"
  },
  {
    "source": "མིག་ལྟ་སྟངས་བྱས་ཀྱང་ཉམས་མྱོང་མེད།།",
    "target": "མིག་ ལྟ་སྟངས་ བྱས་ ཀྱང་ ཉམས་ མྱོང་ མེད ། །"
  },
  {
    "source": "ཕ་ཐུགས་རྗེས༴མི་གཞན་གྱི་སྐྱོན་མཚང་ཆུང་ངུ་རིག།",
    "target": "ཕ་ ཐུགས་རྗེས ༴ མི་ གཞན་ གྱི་ སྐྱོན་ མཚང་ ཆུང་ངུ་ རིག །"
  },
  {
    "source": "རང་ཁོང་ནས་རུལ་བ་ཡེ་མ་ཚོར།།",
    "target": "རང་ ཁོང་ ནས་ རུལ་བ་ ཡེ་ མ་ ཚོར ། །"
  },
  {
    "source": "མི་གཞན་གྱི་མགོ་བོ་བསྐོར་བསྐོར་ནས།།",
    "target": "མི་ གཞན་ གྱི་ མགོ་བོ་ བསྐོར་ བསྐོར་ ནས ། །"
  },
  {
    "source": "སྡུག་རང་གིས་ཉོས་པ་མ་ལགས་སམ།།",
    "target": "སྡུག་ རང་ གིས་ ཉོས་ པ་ མ་ ལགས་ སམ ། །"
  },
  {
    "source": "ཕ་ཐུགས་རྗེས༴ཁོང་རྒྱལ་བའི་གསུང་རབ་མ་ལུས་ཀུན།།",
    "target": "ཕ་ ཐུགས་རྗེས ༴ ཁོང་ རྒྱལ་བ འི་ གསུང་རབ་ མ་ ལུས་ ཀུན ། །"
  },
  {
    "source": "སེམས་རྒྱུད་ལ་ཨེ་ཕན་མི་སེམས་པར།།",
    "target": "སེམས་རྒྱུད་ ལ་ ཨེ་ ཕན་ མི་ སེམས་པ ར ། །"
  },
  {
    "source": "ཁེ་དྲག་པ་སྒྲུབ་ཕྱིར་ཐོས་བསམ་བྱས།།",
    "target": "ཁེ་ དྲག་པ་ སྒྲུབ་ ཕྱི ར་ ཐོས་བསམ་ བྱས ། །"
  },
  {
    "source": "དེ་ཐར་པའི་ལམ་དུ་ཨེ་འགྲོ་ཨང་།།",
    "target": "དེ་ ཐར་པ འི་ ལམ་ དུ་ ཨེ་ འགྲོ་ ཨང་ ། །"
  },
  {
    "source": "ཕ་ཐུགས་རྗེས༴ཁྱོད་ཆོས་པའི་ཚུལ་གྱིས་འཇིག་རྟེན་བསྒྲུབ།།",
    "target": "ཕ་ ཐུགས་རྗེས ༴ ཁྱོད་ ཆོས་པ འི་ ཚུལ་ གྱིས་ འཇིག་རྟེན་ བསྒྲུབ ། །"
  },
  {
    "source": "ལར་སྐྱེ་བོ་ཀུན་གྱི་མཆོད་པ་ལེན།།",
    "target": "ལ ར་ སྐྱེ་བོ་ ཀུན་ གྱི་ མཆོད་པ་ ལེན ། །"
  },
  {
    "source": "ཚེ་ཡང་ཡེངས་བྱ་བའི་ངང་དུ་བཏང་།།",
    "target": "ཚེ་ ཡང་ ཡེངས་ བྱ་བ འི་ ངང་ དུ་ བཏང་ ། །"
  },
  {
    "source": "དབུགས་ཁྲོག་གེར་འགྲོ་དུས་ཅི་འདྲ་ཨང་།།",
    "target": "དབུགས་ ཁྲོག་ གེ ར་ འགྲོ་ དུས་ ཅི་ འདྲ་ ཨང་ ། །"
  },
  {
    "source": "ཕ་ཐུགས་རྗེས༴བདག་དེ་སླད་སྐྱོ་བ་གཏིང་ནས་སྐྱེས།།",
    "target": "ཕ་ ཐུགས་རྗེས ༴ བདག་ དེ་ སླད་ སྐྱོ་བ་ གཏིང་ ནས་ སྐྱེས ། །"
  },
  {
    "source": "ཡར་སངས་རྒྱས་རྣམས་ལ་གསོལ་བ་འདེབས།།",
    "target": "ཡ ར་ སངས་རྒྱས་ རྣམས་ ལ་ གསོལ་བ་ འདེབས ། །"
  },
  {
    "source": "སྤྱིར་སྙིགས་མའི་དུས་ཀྱི་སེམས་ཅན་དང་།།",
    "target": "སྤྱི ར་ སྙིགས་མ འི་ དུས་ ཀྱི་ སེམས་ཅན་ དང་ ། །"
  },
  {
    "source": "སྒོས་ཆོས་པའི་ཚུལ་ཅན་བདག་སོགས་ལ།།",
    "target": "སྒོས་ ཆོས་པ འི་ ཚུལ་ ཅན་ བདག་ སོགས་ ལ ། །"
  },
  {
    "source": "ཕ་ཐུགས་རྗེས་ཟུང་ཞིག་ཀརྨ་པ།།",
    "target": "ཕ་ ཐུགས་རྗེ ས་ ཟུང་ ཞིག་ ཀརྨ་པ ། །"
  },
  {
    "source": "བུ་ང་ལ་རེ་ས་གཞན་ན་མེད།།",
    "target": "བུ་ ང་ ལ་ རེ་ ས་ གཞན་ ན་ མེད ། །"
  },
  {
    "source": "བྱ་བྲལ་གྱི་སྐྱིད་སྡུག་ཁྱེད་རང་ཤེས།།",
    "target": "བྱ་བྲལ་ གྱི་ སྐྱིད་སྡུག་ ཁྱེད་ རང་ ཤེས ། །"
  },
  {
    "source": "དབྱིངས་ཟག་མེད་བདེ་ཆེན་ཕོ་བྲང་ནས།།",
    "target": "དབྱིངས་ ཟག་མེད་བདེ་ཆེན་ ཕོ་བྲང་ ནས ། །"
  },
  {
    "source": "མགོན་ཁྱེད་དང་དབྱེར་མེད་རོ་གཅིག་ཤོག།",
    "target": "མགོན་ ཁྱེད་ དང་ དབྱེར་ མེད་ རོ་ གཅིག་ ཤོག །"
  },
  {
    "source": "ཅེས་དཔལ་ཙཱ་རི་ཏྲའི་རིན་ཆེན་ཕུག་ཏུ་ཞྭ་དམར་དཀོན་མཆོག་ཡན་ལག་གིས་མཛད་པའོ།།",
    "target": "ཅེས་ དཔལ་ ཙཱ་རི་ཏྲ འི་ རིན་ཆེན་ ཕུག་ ཏུ་ ཞྭ་དམར་ དཀོན་མཆོག་ ཡན་ལག་ གིས་ མཛད་པ འོ ། །"
  }
]
